Workbook
Name CompoundingRate: Inputs!$D$2

Sheet Summary
A1: DETAILS | F1: EST. RETURNS | H1: DATE | L1: PRINCIPLE | R1: CASH FLOWS | X1: RETURNS
A2: Address | B2: Suburb | C2: FX | D2: Type | E2: Entity | F2: Return | G2: Months | H2: Start Date | I2: End Date | J2: Months | K2: Ownership | L2: Purchase Price | M2: Value | N2: Equity | O2: Debt | P2: LVR | Q2: Avg Equity | R2: Interest | S2: Other Costs | T2: Rent | U2: Income | V2: Sale Price | W2: Capital Gain | X2: Profit | Y2: Return | Z2: IRR | AA2: Net-tax IRR | AB2: real IRR
A3: 17|34 Hamilton St | B3: Rose Bay 2029 | C3: {=INDIRECT("'" & $A3& "'!R13")} -> AUD | D3: {=INDIRECT("'" & $A3& "'!R16")} -> Property | E3: {=INDIRECT("'" & $A3& "'!R10")} -> Shaun Reichman | F3: - | G3: - | H3: =MIN(INDIRECT("'" & $A3& "'!A:A")) -> 44351 | I3: {=IF(N3=0, LOOKUP(2, 1/(INDIRECT("'"&A3&"'!B:B")="Return"), INDIRECT("'"&A3&"'!A:A")), "")} | J3: =YEARFRAC(H3, IF(V3=0, NOW(), I3))*12 -> 48.8 | K3: {=INDIRECT("'" & $A3& "'!R6")} -> 1 | L3: {=INDIRECT("'" & $A3& "'!P3")} -> 3450000 | M3: {=INDIRECT("'" & $A3& "'!R3")} -> 3750000 | N3: {=INDIRECT("'" & $A3& "'!T3")} -> 215863.13 | O3: {=INDIRECT("'" & $A3& "'!V3")} -> 3534136.9 | P3: {=INDIRECT("'" & $A3& "'!V6")} -> 0.9424365 | Q3: {=INDIRECT("'" & $A3& "'!T6")} -> #VALUE! | R3: =-SUM(INDIRECT("'" & $A3& "'!G:G")) -> -318413.49 | S3: =-(SUM(INDIRECT("'"&$A3&"'!H:H"))) -> -279091.2 | T3: =SUM(INDIRECT("'" & $A3& "'!I:I")) -> 427960 | U3: =SUM(R3:T3) -> -169544.69 | V3: =SUM(INDIRECT("'" & $A3& "'!J:J")) -> 0 | W3: =IF(V3<>0, (V3-L3)*K3, 0) -> 0 | X3: =IF(V3>0, (V3-L3+R3+S3+T3)*K3, 0) -> 0 | Y3: =(X3/K3)/Q3 -> #VALUE! | Z3: {=IF(INDIRECT("'" & $A3& "'!X3")<>0, INDIRECT("'" & $A3& "'!X3"), "")} | AA3: {=IF(INDIRECT("'" & $A3& "'!X6")<>0, INDIRECT("'" & $A3& "'!X6"), "")} | AB3: {=IF(INDIRECT("'" & $A3& "'!X9")<>0, INDIRECT("'" & $A3& "'!X9"), "")}

Sheet 17|34 Hamilton St
G1: INTEREST | H1: COSTS | I1: RENT | J1: SALE | K1: TAX | AA1: VALUATION | AC1: AVERAGE BALANCE | AG1: IRR CALCULATIONS | AL1: NET IRR CALCULATIONS | AP1: FINANCING IRR CALCULATIONS
A2: Date | B2: Transaction | C2: Debt | D2: Equity | E2: Cash Flow | F2: Repayment | G2: Amount | H2: Amount | I2: Income | J2: Amount | K2: Earnings | L2: Rate | M2: Debt Cost (est.) | P2: Purchase Price | R2: Value | T2: Equity | V2: Debt | X2: IRR | AA2: Purchase Price | AB2: Value | AC2: Equity | AD2: Debt | AE2: Days | AG2: Cash Flows | AH2: Days | AI2: PV | AJ2: Sum To Zero | AL2: Cash Flows | AM2: PV | AN2: Sum To Zero | AP2: Last Date | AQ2: Date | AR2: Balance | AS2: Rate | AT2: Interest | AU2: Cash Flows | AV2: PV | AW2: Sum To Zero | AX2: Ave Rate
A3: 44351 | B3: Deposit to Vendor | D3: 172500 | E3: -172500 | M3: =IF($A3<>"", IF(ISNUMBER(SEARCH("Debt Cost (est.)",B3)), SUMIFS(AT:AT, AQ:AQ, ">="&DATE("20"&RIGHT(LEFT(B3,4),2)-1,7,1), AQ:AQ, "<="&DATE("20"&RIGHT(LEFT(B3,4),2),6,30)), ""), "") | P3: 3450000 | R3: =V3+T3 -> 3750000 | T3: {=LOOKUP(2,1/(AC:AC<>""),AC:AC)} -> 215863.13 | V3: {=LOOKUP(2,1/(AD:AD<>""),AD:AD)} -> 3534136.9 | AA3: =IF($A3<>"", MIN(AB3,$P$3), "") -> 172500 | AB3: =AD3+AC3 -> 172500 | AC3: =D3 -> 172500 | AD3: 0 | AE3: =IF(A5<>"", A5-A3, IF(A3<>"",IF(AC3<>0,TODAY()-A3,0), "")) -> 41 | AG3: =IF($A3<>"", I3+J3+E3-F3-H3, "") -> -172500 | AH3: =IF(A3<>"", A3-A$3, "") -> 0 | AI3: =IF(A3<>"", AG3*(1+$X$3)^-(AH3/365), "") -> -172500 | AJ3: =SUM(AI:AI) -> -85407.82 | AL3: =IF($A3<>"", AG3-IF(ISNUMBER(K3),K3*L3,0), "") -> -172500 | AM3: =IF(A3<>"", AL3*(1+$X$6/CompoundingRate)^-(AH3/(365/CompoundingRate)), "") -> -172500 | AN3: =SUM(AM:AM) -> -96003.982 | AP3: =IF(T3=0, MAX(A:A), TODAY()) -> 45836 | AQ3: =A3 -> 44351 | AR3: =IF($AQ3<>"", INDEX($AC$3:$AC$1055, MATCH($AQ3,$A$3:$A$1055,1)), "") -> 172500 | AS3: =IF($AQ3<>"", INDEX(Inputs!$B$3:$B$101, MATCH($AQ3,Inputs!$A$3:$A$101,1)), "") -> 0.001 | AT3: =IF($AQ3<>"", AR3*AS3/365, "") -> 0.47260274 | AU3: =IF($AQ3<>"", SUMIFS($AL$3:$AL$1054, $A$3:$A$1054,$AQ3) + SUMIFS($M$3:$M$1054, $A$3:$A$1054,$AQ3)*IFERROR(AVERAGEIFS($L$3:$L$1054, $A$3:$A$1054,$AQ3, $M$3:$M$1054,">0"),0) - AT3, "") -> -172500.47 | AV3: =IF(AQ3<>"", AU3*(1+$X$9/CompoundingRate)^-((AQ3-AQ$3)/(365/CompoundingRate)), "") -> -172500.47 | AW3: =SUM(AV:AV) -> -160561.45 | AX3: =SUMPRODUCT(AR:AR,AS:AS)/SUM(AR:AR) -> 0.030269514 | BA3: 42917 | BB3: 43281 | BC3: =COUNTIFS(AQ:AQ,">="&BA3, AQ:AQ,"<="&BB3, AR:AR, "<>0") -> 0 | BD3: =AVERAGEIFS(AR:AR, AQ:AQ,">="&BA3, AQ:AQ,"<="&BB3, AR:AR, "<>0") -> #DIV/0!
A4: 44377 | B4: FY21 Debt Cost (est.) | L4: 0.325 | M4: =IF($A4<>"", IF(ISNUMBER(SEARCH("Debt Cost (est.)",B4)), SUMIFS(AT:AT, AQ:AQ, ">="&DATE("20"&RIGHT(LEFT(B4,4),2)-1,7,1), AQ:AQ, "<="&DATE("20"&RIGHT(LEFT(B4,4),2),6,30)), ""), "") -> 12.760274 | AA4: =IF($A4<>"", MIN(AB4,$P$3), "") -> 172500 | AB4: =IF($A4<>"", AC4+AD4, "") -> 172500 | AC4: =IF(A4<>"", AC3+D4+F4-G4, "") -> 172500 | AD4: =IF(A4<>"", AD3+C4-F4+G4, "") -> 0 | AE4: =IF(A5<>"", A5-A4, IF(A4<>"",IF(AC4<>0,TODAY()-A4,0), "")) -> 15 | AG4: =IF($A4<>"", I4+J4+E4-F4-H4, "") -> 0 | AH4: =IF(A4<>"", A4-A$3, "") -> 26 | AI4: =IF(A4<>"", AG4*(1+$X$3)^-(AH4/365), "") -> 0 | AL4: =IF($A4<>"", AG4-IF(ISNUMBER(K4),K4*L4,0), "") -> 0 | AM4: =IF(A4<>"", AL4*(1+$X$6/CompoundingRate)^-(AH4/(365/CompoundingRate)), "") -> 0 | AQ4: =IF(AQ3<$AP$3,AQ3+1,"") -> 44352 | AR4: =IF($AQ4<>"", INDEX($AC$3:$AC$1055, MATCH($AQ4,$A$3:$A$1055,1)), "") -> 172500 | AS4: =IF($AQ4<>"", INDEX(Inputs!$B$3:$B$101, MATCH($AQ4,Inputs!$A$3:$A$101,1)), "") -> 0.001 | AT4: =IF($AQ4<>"", AR4*AS4/365, "") -> 0.47260274 | AU4: =IF($AQ4<>"", SUMIFS($AL$3:$AL$1054, $A$3:$A$1054,$AQ4) + SUMIFS($M$3:$M$1054, $A$3:$A$1054,$AQ4)*IFERROR(AVERAGEIFS($L$3:$L$1054, $A$3:$A$1054,$AQ4, $M$3:$M$1054,">0"),0) - AT4, "") -> -0.47260274 | AV4: =IF(AQ4<>"", AU4*(1+$X$9/CompoundingRate)^-((AQ4-AQ$3)/(365/CompoundingRate)), "") -> -0.47260274 | BA4: 43282 | BB4: 43646 | BC4: =COUNTIFS(AQ:AQ,">="&BA4, AQ:AQ,"<="&BB4, AR:AR, "<>0") -> 0 | BD4: =AVERAGEIFS(AR:AR, AQ:AQ,">="&BA4, AQ:AQ,"<="&BB4, AR:AR, "<>0") -> #DIV/0!
A5: 44392 | B5: Payment to Vendor | D5: 345000 | E5: -345000 | M5: =IF($A5<>"", IF(ISNUMBER(SEARCH("Debt Cost (est.)",B5)), SUMIFS(AT:AT, AQ:AQ, ">="&DATE("20"&RIGHT(LEFT(B5,4),2)-1,7,1), AQ:AQ, "<="&DATE("20"&RIGHT(LEFT(B5,4),2),6,30)), ""), "") | R5: Ownership | T5: Avg Equity | V5: LVR | X5: Net-tax IRR | AA5: =IF($A5<>"", MIN(AB5,$P$3), "") -> 517500 | AB5: =IF($A5<>"", AC5+AD5, "") -> 517500 | AC5: =IF(A5<>"", AC4+D5+F5-G5, "") -> 517500 | AD5: =IF(A5<>"", AD4+C5-F5+G5, "") -> 0 | AE5: =IF(A6<>"", A6-A5, IF(A5<>"",IF(AC5<>0,TODAY()-A5,0), "")) -> 0 | AG5: =IF($A5<>"", I5+J5+E5-F5-H5, "") -> -345000 | AH5: =IF(A5<>"", A5-A$3, "") -> 41 | AI5: =IF(A5<>"", AG5*(1+$X$3)^-(AH5/365), "") -> -345000 | AL5: =IF($A5<>"", AG5-IF(ISNUMBER(K5),K5*L5,0), "") -> -345000 | AM5: =IF(A5<>"", AL5*(1+$X$6/CompoundingRate)^-(AH5/(365/CompoundingRate)), "") -> -345000 | AQ5: =IF(AQ4<$AP$3,AQ4+1,"") -> 44353 | AR5: =IF($AQ5<>"", INDEX($AC$3:$AC$1055, MATCH($AQ5,$A$3:$A$1055,1)), "") -> 172500 | AS5: =IF($AQ5<>"", INDEX(Inputs!$B$3:$B$101, MATCH($AQ5,Inputs!$A$3:$A$101,1)), "") -> 0.001 | AT5: =IF($AQ5<>"", AR5*AS5/365, "") -> 0.47260274 | AU5: =IF($AQ5<>"", SUMIFS($AL$3:$AL$1054, $A$3:$A$1054,$AQ5) + SUMIFS($M$3:$M$1054, $A$3:$A$1054,$AQ5)*IFERROR(AVERAGEIFS($L$3:$L$1054, $A$3:$A$1054,$AQ5, $M$3:$M$1054,">0"),0) - AT5, "") -> -0.47260274 | AV5: =IF(AQ5<>"", AU5*(1+$X$9/CompoundingRate)^-((AQ5-AQ$3)/(365/CompoundingRate)), "") -> -0.47260274 | BA5: 43647 | BB5: 44012 | BC5: =COUNTIFS(AQ:AQ,">="&BA5, AQ:AQ,"<="&BB5, AR:AR, "<>0") -> 0 | BD5: =AVERAGEIFS(AR:AR, AQ:AQ,">="&BA5, AQ:AQ,"<="&BB5, AR:AR, "<>0") -> #DIV/0!
A6: 44392 | B6: NAB Mortgage #3063 | C6: 2432500 | M6: =IF($A6<>"", IF(ISNUMBER(SEARCH("Debt Cost (est.)",B6)), SUMIFS(AT:AT, AQ:AQ, ">="&DATE("20"&RIGHT(LEFT(B6,4),2)-1,7,1), AQ:AQ, "<="&DATE("20"&RIGHT(LEFT(B6,4),2),6,30)), ""), "") | R6: 1 | T6: =SUMPRODUCT(AC:AC,AE:AE)/SUM(AE:AE) -> #VALUE! | V6: =V3/R3 -> 0.9424365 | AA6: =IF($A6<>"", MIN(AB6,$P$3), "") -> 2950000 | AB6: =IF($A6<>"", AC6+AD6, "") -> 2950000 | AC6: =IF(A6<>"", AC5+D6+F6-G6, "") -> 517500 | AD6: =IF(A6<>"", AD5+C6-F6+G6, "") -> 2432500 | AE6: =IF(A7<>"", A7-A6, IF(A6<>"",IF(AC6<>0,TODAY()-A6,0), "")) -> 0 | AG6: =IF($A6<>"", I6+J6+E6-F6-H6, "") -> 0 | AH6: =IF(A6<>"", A6-A$3, "") -> 41 | AI6: =IF(A6<>"", AG6*(1+$X$3)^-(AH6/365), "") -> 0 | AL6: =IF($A6<>"", AG6-IF(ISNUMBER(K6),K6*L6,0), "") -> 0 | AM6: =IF(A6<>"", AL6*(1+$X$6/CompoundingRate)^-(AH6/(365/CompoundingRate)), "") -> 0 | AQ6: =IF(AQ5<$AP$3,AQ5+1,"") -> 44354 | AR6: =IF($AQ6<>"", INDEX($AC$3:$AC$1055, MATCH($AQ6,$A$3:$A$1055,1)), "") -> 172500 | AS6: =IF($AQ6<>"", INDEX(Inputs!$B$3:$B$101, MATCH($AQ6,Inputs!$A$3:$A$101,1)), "") -> 0.001 | AT6: =IF($AQ6<>"", AR6*AS6/365, "") -> 0.47260274 | AU6: =IF($AQ6<>"", SUMIFS($AL$3:$AL$1054, $A$3:$A$1054,$AQ6) + SUMIFS($M$3:$M$1054, $A$3:$A$1054,$AQ6)*IFERROR(AVERAGEIFS($L$3:$L$1054, $A$3:$A$1054,$AQ6, $M$3:$M$1054,">0"),0) - AT6, "") -> -0.47260274 | AV6: =IF(AQ6<>"", AU6*(1+$X$9/CompoundingRate)^-((AQ6-AQ$3)/(365/CompoundingRate)), "") -> -0.47260274 | BA6: 44013 | BB6: 44377 | BC6: =COUNTIFS(AQ:AQ,">="&BA6, AQ:AQ,"<="&BB6, AR:AR, "<>0") -> 27 | BD6: =AVERAGEIFS(AR:AR, AQ:AQ,">="&BA6, AQ:AQ,"<="&BB6, AR:AR, "<>0") -> 172500
A7: 44392 | B7: NAB Mortgage #2157 | C7: 500000 | M7: =IF($A7<>"", IF(ISNUMBER(SEARCH("Debt Cost (est.)",B7)), SUMIFS(AT:AT, AQ:AQ, ">="&DATE("20"&RIGHT(LEFT(B7,4),2)-1,7,1), AQ:AQ, "<="&DATE("20"&RIGHT(LEFT(B7,4),2),6,30)), ""), "") | AA7: =IF($A7<>"", MIN(AB7,$P$3), "") -> 3450000 | AB7: =IF($A7<>"", AC7+AD7, "") -> 3450000 | AC7: =IF(A7<>"", AC6+D7+F7-G7, "") -> 517500 | AD7: =IF(A7<>"", AD6+C7-F7+G7, "") -> 2932500 | AE7: =IF(A8<>"", A8-A7, IF(A7<>"",IF(AC7<>0,TODAY()-A7,0), "")) -> 0 | AG7: =IF($A7<>"", I7+J7+E7-F7-H7, "") -> 0 | AH7: =IF(A7<>"", A7-A$3, "") -> 41 | AI7: =IF(A7<>"", AG7*(1+$X$3)^-(AH7/365), "") -> 0 | AL7: =IF($A7<>"", AG7-IF(ISNUMBER(K7),K7*L7,0), "") -> 0 | AM7: =IF(A7<>"", AL7*(1+$X$6/CompoundingRate)^-(AH7/(365/CompoundingRate)), "") -> 0 | AQ7: =IF(AQ6<$AP$3,AQ6+1,"") -> 44355 | AR7: =IF($AQ7<>"", INDEX($AC$3:$AC$1055, MATCH($AQ7,$A$3:$A$1055,1)), "") -> 172500 | AS7: =IF($AQ7<>"", INDEX(Inputs!$B$3:$B$101, MATCH($AQ7,Inputs!$A$3:$A$101,1)), "") -> 0.001 | AT7: =IF($AQ7<>"", AR7*AS7/365, "") -> 0.47260274 | AU7: =IF($AQ7<>"", SUMIFS($AL$3:$AL$1054, $A$3:$A$1054,$AQ7) + SUMIFS($M$3:$M$1054, $A$3:$A$1054,$AQ7)*IFERROR(AVERAGEIFS($L$3:$L$1054, $A$3:$A$1054,$AQ7, $M$3:$M$1054,">0"),0) - AT7, "") -> -0.47260274 | AV7: =IF(AQ7<>"", AU7*(1+$X$9/CompoundingRate)^-((AQ7-AQ$3)/(365/CompoundingRate)), "") -> -0.47260274 | BA7: 44378 | BB7: 44742 | BC7: =COUNTIFS(AQ:AQ,">="&BA7, AQ:AQ,"<="&BB7, AR:AR, "<>0") -> 365 | BD7: =AVERAGEIFS(AR:AR, AQ:AQ,">="&BA7, AQ:AQ,"<="&BB7, AR:AR, "<>0") -> 540545.38
A8: 44392 | B8: Stamp Duty | H8: 180010 | M8: =IF($A8<>"", IF(ISNUMBER(SEARCH("Debt Cost (est.)",B8)), SUMIFS(AT:AT, AQ:AQ, ">="&DATE("20"&RIGHT(LEFT(B8,4),2)-1,7,1), AQ:AQ, "<="&DATE("20"&RIGHT(LEFT(B8,4),2),6,30)), ""), "") | X8: real IRR | AA8: =IF($A8<>"", MIN(AB8,$P$3), "") -> 3450000 | AB8: =IF($A8<>"", AC8+AD8, "") -> 3450000 | AC8: =IF(A8<>"", AC7+D8+F8-G8, "") -> 517500 | AD8: =IF(A8<>"", AD7+C8-F8+G8, "") -> 2932500 | AE8: =IF(A9<>"", A9-A8, IF(A8<>"",IF(AC8<>0,TODAY()-A8,0), "")) -> 0 | AG8: =IF($A8<>"", I8+J8+E8-F8-H8, "") -> -180010 | AH8: =IF(A8<>"", A8-A$3, "") -> 41 | AI8: =IF(A8<>"", AG8*(1+$X$3)^-(AH8/365), "") -> -180010 | AL8: =IF($A8<>"", AG8-IF(ISNUMBER(K8),K8*L8,0), "") -> -180010 | AM8: =IF(A8<>"", AL8*(1+$X$6/CompoundingRate)^-(AH8/(365/CompoundingRate)), "") -> -180010 | AQ8: =IF(AQ7<$AP$3,AQ7+1,"") -> 44356 | AR8: =IF($AQ8<>"", INDEX($AC$3:$AC$1055, MATCH($AQ8,$A$3:$A$1055,1)), "") -> 172500 | AS8: =IF($AQ8<>"", INDEX(Inputs!$B$3:$B$101, MATCH($AQ8,Inputs!$A$3:$A$101,1)), "") -> 0.001 | AT8: =IF($AQ8<>"", AR8*AS8/365, "") -> 0.47260274 | AU8: =IF($AQ8<>"", SUMIFS($AL$3:$AL$1054, $A$3:$A$1054,$AQ8) + SUMIFS($M$3:$M$1054, $A$3:$A$1054,$AQ8)*IFERROR(AVERAGEIFS($L$3:$L$1054, $A$3:$A$1054,$AQ8, $M$3:$M$1054,">0"),0) - AT8, "") -> -0.47260274 | AV8: =IF(AQ8<>"", AU8*(1+$X$9/CompoundingRate)^-((AQ8-AQ$3)/(365/CompoundingRate)), "") -> -0.47260274 | BA8: 44743 | BB8: 45107 | BC8: =COUNTIFS(AQ:AQ,">="&BA8, AQ:AQ,"<="&BB8, AR:AR, "<>0") -> 365 | BD8: =AVERAGEIFS(AR:AR, AQ:AQ,">="&BA8, AQ:AQ,"<="&BB8, AR:AR, "<>0") -> 636307
A9: 44392 | B9: Lawyer Settlement Fees | H9: 4622.8 | M9: =IF($A9<>"", IF(ISNUMBER(SEARCH("Debt Cost (est.)",B9)), SUMIFS(AT:AT, AQ:AQ, ">="&DATE("20"&RIGHT(LEFT(B9,4),2)-1,7,1), AQ:AQ, "<="&DATE("20"&RIGHT(LEFT(B9,4),2),6,30)), ""), "") | R9: Entity | AA9: =IF($A9<>"", MIN(AB9,$P$3), "") -> 3450000 | AB9: =IF($A9<>"", AC9+AD9, "") -> 3450000 | AC9: =IF(A9<>"", AC8+D9+F9-G9, "") -> 517500 | AD9: =IF(A9<>"", AD8+C9-F9+G9, "") -> 2932500 | AE9: =IF(A10<>"", A10-A9, IF(A9<>"",IF(AC9<>0,TODAY()-A9,0), "")) -> 0 | AG9: =IF($A9<>"", I9+J9+E9-F9-H9, "") -> -4622.8 | AH9: =IF(A9<>"", A9-A$3, "") -> 41 | AI9: =IF(A9<>"", AG9*(1+$X$3)^-(AH9/365), "") -> -4622.8 | AL9: =IF($A9<>"", AG9-IF(ISNUMBER(K9),K9*L9,0), "") -> -4622.8 | AM9: =IF(A9<>"", AL9*(1+$X$6/CompoundingRate)^-(AH9/(365/CompoundingRate)), "") -> -4622.8 | AQ9: =IF(AQ8<$AP$3,AQ8+1,"") -> 44357 | AR9: =IF($AQ9<>"", INDEX($AC$3:$AC$1055, MATCH($AQ9,$A$3:$A$1055,1)), "") -> 172500 | AS9: =IF($AQ9<>"", INDEX(Inputs!$B$3:$B$101, MATCH($AQ9,Inputs!$A$3:$A$101,1)), "") -> 0.001 | AT9: =IF($AQ9<>"", AR9*AS9/365, "") -> 0.47260274 | AU9: =IF($AQ9<>"", SUMIFS($AL$3:$AL$1054, $A$3:$A$1054,$AQ9) + SUMIFS($M$3:$M$1054, $A$3:$A$1054,$AQ9)*IFERROR(AVERAGEIFS($L$3:$L$1054, $A$3:$A$1054,$AQ9, $M$3:$M$1054,">0"),0) - AT9, "") -> -0.47260274 | AV9: =IF(AQ9<>"", AU9*(1+$X$9/CompoundingRate)^-((AQ9-AQ$3)/(365/CompoundingRate)), "") -> -0.47260274 | BA9: 45108 | BB9: 45473 | BC9: =COUNTIFS(AQ:AQ,">="&BA9, AQ:AQ,"<="&BB9, AR:AR, "<>0") -> 366 | BD9: =AVERAGEIFS(AR:AR, AQ:AQ,">="&BA9, AQ:AQ,"<="&BB9, AR:AR, "<>0") -> 729079.84
A10: 44392 | B10: NAB Mortgage Fee | H10: =9.87+147.7+147.7+147.7 -> 452.97 | M10: =IF($A10<>"", IF(ISNUMBER(SEARCH("Debt Cost (est.)",B10)), SUMIFS(AT:AT, AQ:AQ, ">="&DATE("20"&RIGHT(LEFT(B10,4),2)-1,7,1), AQ:AQ, "<="&DATE("20"&RIGHT(LEFT(B10,4),2),6,30)), ""), "") | R10: Shaun Reichman | AA10: =IF($A10<>"", MIN(AB10,$P$3), "") -> 3450000 | AB10: =IF($A10<>"", AC10+AD10, "") -> 3450000 | AC10: =IF(A10<>"", AC9+D10+F10-G10, "") -> 517500 | AD10: =IF(A10<>"", AD9+C10-F10+G10, "") -> 2932500 | AE10: =IF(A11<>"", A11-A10, IF(A10<>"",IF(AC10<>0,TODAY()-A10,0), "")) -> 0 | AG10: =IF($A10<>"", I10+J10+E10-F10-H10, "") -> -452.97 | AH10: =IF(A10<>"", A10-A$3, "") -> 41 | AI10: =IF(A10<>"", AG10*(1+$X$3)^-(AH10/365), "") -> -452.97 | AL10: =IF($A10<>"", AG10-IF(ISNUMBER(K10),K10*L10,0), "") -> -452.97 | AM10: =IF(A10<>"", AL10*(1+$X$6/CompoundingRate)^-(AH10/(365/CompoundingRate)), "") -> -452.97 | AQ10: =IF(AQ9<$AP$3,AQ9+1,"") -> 44358 | AR10: =IF($AQ10<>"", INDEX($AC$3:$AC$1055, MATCH($AQ10,$A$3:$A$1055,1)), "") -> 172500 | AS10: =IF($AQ10<>"", INDEX(Inputs!$B$3:$B$101, MATCH($AQ10,Inputs!$A$3:$A$101,1)), "") -> 0.001 | AT10: =IF($AQ10<>"", AR10*AS10/365, "") -> 0.47260274 | AU10: =IF($AQ10<>"", SUMIFS($AL$3:$AL$1054, $A$3:$A$1054,$AQ10) + SUMIFS($M$3:$M$1054, $A$3:$A$1054,$AQ10)*IFERROR(AVERAGEIFS($L$3:$L$1054, $A$3:$A$1054,$AQ10, $M$3:$M$1054,">0"),0) - AT10, "") -> -0.47260274 | AV10: =IF(AQ10<>"", AU10*(1+$X$9/CompoundingRate)^-((AQ10-AQ$3)/(365/CompoundingRate)), "") -> -0.47260274 | BA10: 45474 | BB10: 45838 | BC10: =COUNTIFS(AQ:AQ,">="&BA10, AQ:AQ,"<="&BB10, AR:AR, "<>0") -> 363 | BD10: =AVERAGEIFS(AR:AR, AQ:AQ,">="&BA10, AQ:AQ,"<="&BB10, AR:AR, "<>0") -> 562311.48
A11: 44392 | B11: Pexa Settlement Fee | H11: 117.92 | M11: =IF($A11<>"", IF(ISNUMBER(SEARCH("Debt Cost (est.)",B11)), SUMIFS(AT:AT, AQ:AQ, ">="&DATE("20"&RIGHT(LEFT(B11,4),2)-1,7,1), AQ:AQ, "<="&DATE("20"&RIGHT(LEFT(B11,4),2),6,30)), ""), "") | AA11: =IF($A11<>"", MIN(AB11,$P$3), "") -> 3450000 | AB11: =IF($A11<>"", AC11+AD11, "") -> 3450000 | AC11: =IF(A11<>"", AC10+D11+F11-G11, "") -> 517500 | AD11: =IF(A11<>"", AD10+C11-F11+G11, "") -> 2932500 | AE11: =IF(A12<>"", A12-A11, IF(A11<>"",IF(AC11<>0,TODAY()-A11,0), "")) -> 0 | AG11: =IF($A11<>"", I11+J11+E11-F11-H11, "") -> -117.92 | AH11: =IF(A11<>"", A11-A$3, "") -> 41 | AI11: =IF(A11<>"", AG11*(1+$X$3)^-(AH11/365), "") -> -117.92 | AL11: =IF($A11<>"", AG11-IF(ISNUMBER(K11),K11*L11,0), "") -> -117.92 | AM11: =IF(A11<>"", AL11*(1+$X$6/CompoundingRate)^-(AH11/(365/CompoundingRate)), "") -> -117.92 | AQ11: =IF(AQ10<$AP$3,AQ10+1,"") -> 44359 | AR11: =IF($AQ11<>"", INDEX($AC$3:$AC$1055, MATCH($AQ11,$A$3:$A$1055,1)), "") -> 172500 | AS11: =IF($AQ11<>"", INDEX(Inputs!$B$3:$B$101, MATCH($AQ11,Inputs!$A$3:$A$101,1)), "") -> 0.001 | AT11: =IF($AQ11<>"", AR11*AS11/365, "") -> 0.47260274 | AU11: =IF($AQ11<>"", SUMIFS($AL$3:$AL$1054, $A$3:$A$1054,$AQ11) + SUMIFS($M$3:$M$1054, $A$3:$A$1054,$AQ11)*IFERROR(AVERAGEIFS($L$3:$L$1054, $A$3:$A$1054,$AQ11, $M$3:$M$1054,">0"),0) - AT11, "") -> -0.47260274 | AV11: =IF(AQ11<>"", AU11*(1+$X$9/CompoundingRate)^-((AQ11-AQ$3)/(365/CompoundingRate)), "") -> -0.47260274
A12: 44392 | B12: Registration Fees | H12: 443.1 | M12: =IF($A12<>"", IF(ISNUMBER(SEARCH("Debt Cost (est.)",B12)), SUMIFS(AT:AT, AQ:AQ, ">="&DATE("20"&RIGHT(LEFT(B12,4),2)-1,7,1), AQ:AQ, "<="&DATE("20"&RIGHT(LEFT(B12,4),2),6,30)), ""), "") | R12: Currency | AA12: =IF($A12<>"", MIN(AB12,$P$3), "") -> 3450000 | AB12: =IF($A12<>"", AC12+AD12, "") -> 3450000 | AC12: =IF(A12<>"", AC11+D12+F12-G12, "") -> 517500 | AD12: =IF(A12<>"", AD11+C12-F12+G12, "") -> 2932500 | AE12: =IF(A13<>"", A13-A12, IF(A12<>"",IF(AC12<>0,TODAY()-A12,0), "")) -> 0 | AG12: =IF($A12<>"", I12+J12+E12-F12-H12, "") -> -443.1 | AH12: =IF(A12<>"", A12-A$3, "") -> 41 | AI12: =IF(A12<>"", AG12*(1+$X$3)^-(AH12/365), "") -> -443.1 | AL12: =IF($A12<>"", AG12-IF(ISNUMBER(K12),K12*L12,0), "") -> -443.1 | AM12: =IF(A12<>"", AL12*(1+$X$6/CompoundingRate)^-(AH12/(365/CompoundingRate)), "") -> -443.1 | AQ12: =IF(AQ11<$AP$3,AQ11+1,"") -> 44360 | AR12: =IF($AQ12<>"", INDEX($AC$3:$AC$1055, MATCH($AQ12,$A$3:$A$1055,1)), "") -> 172500 | AS12: =IF($AQ12<>"", INDEX(Inputs!$B$3:$B$101, MATCH($AQ12,Inputs!$A$3:$A$101,1)), "") -> 0.001 | AT12: =IF($AQ12<>"", AR12*AS12/365, "") -> 0.47260274 | AU12: =IF($AQ12<>"", SUMIFS($AL$3:$AL$1054, $A$3:$A$1054,$AQ12) + SUMIFS($M$3:$M$1054, $A$3:$A$1054,$AQ12)*IFERROR(AVERAGEIFS($L$3:$L$1054, $A$3:$A$1054,$AQ12, $M$3:$M$1054,">0"),0) - AT12, "") -> -0.47260274 | AV12: =IF(AQ12<>"", AU12*(1+$X$9/CompoundingRate)^-((AQ12-AQ$3)/(365/CompoundingRate)), "") -> -0.47260274
A13: 44392 | B13: Section 184 Certificate | H13: 119.9 | M13: =IF($A13<>"", IF(ISNUMBER(SEARCH("Debt Cost (est.)",B13)), SUMIFS(AT:AT, AQ:AQ, ">="&DATE("20"&RIGHT(LEFT(B13,4),2)-1,7,1), AQ:AQ, "<="&DATE("20"&RIGHT(LEFT(B13,4),2),6,30)), ""), "") | R13: AUD | AA13: =IF($A13<>"", MIN(AB13,$P$3), "") -> 3450000 | AB13: =IF($A13<>"", AC13+AD13, "") -> 3450000 | AC13: =IF(A13<>"", AC12+D13+F13-G13, "") -> 517500 | AD13: =IF(A13<>"", AD12+C13-F13+G13, "") -> 2932500 | AE13: =IF(A14<>"", A14-A13, IF(A13<>"",IF(AC13<>0,TODAY()-A13,0), "")) -> 0 | AG13: =IF($A13<>"", I13+J13+E13-F13-H13, "") -> -119.9 | AH13: =IF(A13<>"", A13-A$3, "") -> 41 | AI13: =IF(A13<>"", AG13*(1+$X$3)^-(AH13/365), "") -> -119.9 | AL13: =IF($A13<>"", AG13-IF(ISNUMBER(K13),K13*L13,0), "") -> -119.9 | AM13: =IF(A13<>"", AL13*(1+$X$6/CompoundingRate)^-(AH13/(365/CompoundingRate)), "") -> -119.9 | AQ13: =IF(AQ12<$AP$3,AQ12+1,"") -> 44361 | AR13: =IF($AQ13<>"", INDEX($AC$3:$AC$1055, MATCH($AQ13,$A$3:$A$1055,1)), "") -> 172500 | AS13: =IF($AQ13<>"", INDEX(Inputs!$B$3:$B$101, MATCH($AQ13,Inputs!$A$3:$A$101,1)), "") -> 0.001 | AT13: =IF($AQ13<>"", AR13*AS13/365, "") -> 0.47260274 | AU13: =IF($AQ13<>"", SUMIFS($AL$3:$AL$1054, $A$3:$A$1054,$AQ13) + SUMIFS($M$3:$M$1054, $A$3:$A$1054,$AQ13)*IFERROR(AVERAGEIFS($L$3:$L$1054, $A$3:$A$1054,$AQ13, $M$3:$M$1054,">0"),0) - AT13, "") -> -0.47260274 | AV13: =IF(AQ13<>"", AU13*(1+$X$9/CompoundingRate)^-((AQ13-AQ$3)/(365/CompoundingRate)), "") -> -0.47260274
A14: 44392 | B14: Discharge of Mortgage | H14: -147.7 | M14: =IF($A14<>"", IF(ISNUMBER(SEARCH("Debt Cost (est.)",B14)), SUMIFS(AT:AT, AQ:AQ, ">="&DATE("20"&RIGHT(LEFT(B14,4),2)-1,7,1), AQ:AQ, "<="&DATE("20"&RIGHT(LEFT(B14,4),2),6,30)), ""), "") | AA14: =IF($A14<>"", MIN(AB14,$P$3), "") -> 3450000 | AB14: =IF($A14<>"", AC14+AD14, "") -> 3450000 | AC14: =IF(A14<>"", AC13+D14+F14-G14, "") -> 517500 | AD14: =IF(A14<>"", AD13+C14-F14+G14, "") -> 2932500 | AE14: =IF(A15<>"", A15-A14, IF(A14<>"",IF(AC14<>0,TODAY()-A14,0), "")) -> 0 | AG14: =IF($A14<>"", I14+J14+E14-F14-H14, "") -> 147.7 | AH14: =IF(A14<>"", A14-A$3, "") -> 41 | AI14: =IF(A14<>"", AG14*(1+$X$3)^-(AH14/365), "") -> 147.7 | AL14: =IF($A14<>"", AG14-IF(ISNUMBER(K14),K14*L14,0), "") -> 147.7 | AM14: =IF(A14<>"", AL14*(1+$X$6/CompoundingRate)^-(AH14/(365/CompoundingRate)), "") -> 147.7 | AQ14: =IF(AQ13<$AP$3,AQ13+1,"") -> 44362 | AR14: =IF($AQ14<>"", INDEX($AC$3:$AC$1055, MATCH($AQ14,$A$3:$A$1055,1)), "") -> 172500 | AS14: =IF($AQ14<>"", INDEX(Inputs!$B$3:$B$101, MATCH($AQ14,Inputs!$A$3:$A$101,1)), "") -> 0.001 | AT14: =IF($AQ14<>"", AR14*AS14/365, "") -> 0.47260274 | AU14: =IF($AQ14<>"", SUMIFS($AL$3:$AL$1054, $A$3:$A$1054,$AQ14) + SUMIFS($M$3:$M$1054, $A$3:$A$1054,$AQ14)*IFERROR(AVERAGEIFS($L$3:$L$1054, $A$3:$A$1054,$AQ14, $M$3:$M$1054,">0"),0) - AT14, "") -> -0.47260274 | AV14: =IF(AQ14<>"", AU14*(1+$X$9/CompoundingRate)^-((AQ14-AQ$3)/(365/CompoundingRate)), "") -> -0.47260274
A15: 44392 | B15: Additional Settlement Amount | H15: 35 | M15: =IF($A15<>"", IF(ISNUMBER(SEARCH("Debt Cost (est.)",B15)), SUMIFS(AT:AT, AQ:AQ, ">="&DATE("20"&RIGHT(LEFT(B15,4),2)-1,7,1), AQ:AQ, "<="&DATE("20"&RIGHT(LEFT(B15,4),2),6,30)), ""), "") | R15: Type | AA15: =IF($A15<>"", MIN(AB15,$P$3), "") -> 3450000 | AB15: =IF($A15<>"", AC15+AD15, "") -> 3450000 | AC15: =IF(A15<>"", AC14+D15+F15-G15, "") -> 517500 | AD15: =IF(A15<>"", AD14+C15-F15+G15, "") -> 2932500 | AE15: =IF(A16<>"", A16-A15, IF(A15<>"",IF(AC15<>0,TODAY()-A15,0), "")) -> 0 | AG15: =IF($A15<>"", I15+J15+E15-F15-H15, "") -> -35 | AH15: =IF(A15<>"", A15-A$3, "") -> 41 | AI15: =IF(A15<>"", AG15*(1+$X$3)^-(AH15/365), "") -> -35 | AL15: =IF($A15<>"", AG15-IF(ISNUMBER(K15),K15*L15,0), "") -> -35 | AM15: =IF(A15<>"", AL15*(1+$X$6/CompoundingRate)^-(AH15/(365/CompoundingRate)), "") -> -35 | AQ15: =IF(AQ14<$AP$3,AQ14+1,"") -> 44363 | AR15: =IF($AQ15<>"", INDEX($AC$3:$AC$1055, MATCH($AQ15,$A$3:$A$1055,1)), "") -> 172500 | AS15: =IF($AQ15<>"", INDEX(Inputs!$B$3:$B$101, MATCH($AQ15,Inputs!$A$3:$A$101,1)), "") -> 0.001 | AT15: =IF($AQ15<>"", AR15*AS15/365, "") -> 0.47260274 | AU15: =IF($AQ15<>"", SUMIFS($AL$3:$AL$1054, $A$3:$A$1054,$AQ15) + SUMIFS($M$3:$M$1054, $A$3:$A$1054,$AQ15)*IFERROR(AVERAGEIFS($L$3:$L$1054, $A$3:$A$1054,$AQ15, $M$3:$M$1054,">0"),0) - AT15, "") -> -0.47260274 | AV15: =IF(AQ15<>"", AU15*(1+$X$9/CompoundingRate)^-((AQ15-AQ$3)/(365/CompoundingRate)), "") -> -0.47260274
A16: 44392 | B16: Shortfall of Funds | H16: 286.95 | M16: =IF($A16<>"", IF(ISNUMBER(SEARCH("Debt Cost (est.)",B16)), SUMIFS(AT:AT, AQ:AQ, ">="&DATE("20"&RIGHT(LEFT(B16,4),2)-1,7,1), AQ:AQ, "<="&DATE("20"&RIGHT(LEFT(B16,4),2),6,30)), ""), "") | R16: Property | AA16: =IF($A16<>"", MIN(AB16,$P$3), "") -> 3450000 | AB16: =IF($A16<>"", AC16+AD16, "") -> 3450000 | AC16: =IF(A16<>"", AC15+D16+F16-G16, "") -> 517500 | AD16: =IF(A16<>"", AD15+C16-F16+G16, "") -> 2932500 | AE16: =IF(A17<>"", A17-A16, IF(A16<>"",IF(AC16<>0,TODAY()-A16,0), "")) -> 0 | AG16: =IF($A16<>"", I16+J16+E16-F16-H16, "") -> -286.95 | AH16: =IF(A16<>"", A16-A$3, "") -> 41 | AI16: =IF(A16<>"", AG16*(1+$X$3)^-(AH16/365), "") -> -286.95 | AL16: =IF($A16<>"", AG16-IF(ISNUMBER(K16),K16*L16,0), "") -> -286.95 | AM16: =IF(A16<>"", AL16*(1+$X$6/CompoundingRate)^-(AH16/(365/CompoundingRate)), "") -> -286.95 | AQ16: =IF(AQ15<$AP$3,AQ15+1,"") -> 44364 | AR16: =IF($AQ16<>"", INDEX($AC$3:$AC$1055, MATCH($AQ16,$A$3:$A$1055,1)), "") -> 172500 | AS16: =IF($AQ16<>"", INDEX(Inputs!$B$3:$B$101, MATCH($AQ16,Inputs!$A$3:$A$101,1)), "") -> 0.001 | AT16: =IF($AQ16<>"", AR16*AS16/365, "") -> 0.47260274 | AU16: =IF($AQ16<>"", SUMIFS($AL$3:$AL$1054, $A$3:$A$1054,$AQ16) + SUMIFS($M$3:$M$1054, $A$3:$A$1054,$AQ16)*IFERROR(AVERAGEIFS($L$3:$L$1054, $A$3:$A$1054,$AQ16, $M$3:$M$1054,">0"),0) - AT16, "") -> -0.47260274 | AV16: =IF(AQ16<>"", AU16*(1+$X$9/CompoundingRate)^-((AQ16-AQ$3)/(365/CompoundingRate)), "") -> -0.47260274
A17: 44392 | B17: Council Rates | H17: 1470.73 | M17: =IF($A17<>"", IF(ISNUMBER(SEARCH("Debt Cost (est.)",B17)), SUMIFS(AT:AT, AQ:AQ, ">="&DATE("20"&RIGHT(LEFT(B17,4),2)-1,7,1), AQ:AQ, "<="&DATE("20"&RIGHT(LEFT(B17,4),2),6,30)), ""), "") | AA17: =IF($A17<>"", MIN(AB17,$P$3), "") -> 3450000 | AB17: =IF($A17<>"", AC17+AD17, "") -> 3450000 | AC17: =IF(A17<>"", AC16+D17+F17-G17, "") -> 517500 | AD17: =IF(A17<>"", AD16+C17-F17+G17, "") -> 2932500 | AE17: =IF(A18<>"", A18-A17, IF(A17<>"",IF(AC17<>0,TODAY()-A17,0), "")) -> 0 | AG17: =IF($A17<>"", I17+J17+E17-F17-H17, "") -> -1470.73 | AH17: =IF(A17<>"", A17-A$3, "") -> 41 | AI17: =IF(A17<>"", AG17*(1+$X$3)^-(AH17/365), "") -> -1470.73 | AL17: =IF($A17<>"", AG17-IF(ISNUMBER(K17),K17*L17,0), "") -> -1470.73 | AM17: =IF(A17<>"", AL17*(1+$X$6/CompoundingRate)^-(AH17/(365/CompoundingRate)), "") -> -1470.73 | AQ17: =IF(AQ16<$AP$3,AQ16+1,"") -> 44365 | AR17: =IF($AQ17<>"", INDEX($AC$3:$AC$1055, MATCH($AQ17,$A$3:$A$1055,1)), "") -> 172500 | AS17: =IF($AQ17<>"", INDEX(Inputs!$B$3:$B$101, MATCH($AQ17,Inputs!$A$3:$A$101,1)), "") -> 0.001 | AT17: =IF($AQ17<>"", AR17*AS17/365, "") -> 0.47260274 | AU17: =IF($AQ17<>"", SUMIFS($AL$3:$AL$1054, $A$3:$A$1054,$AQ17) + SUMIFS($M$3:$M$1054, $A$3:$A$1054,$AQ17)*IFERROR(AVERAGEIFS($L$3:$L$1054, $A$3:$A$1054,$AQ17, $M$3:$M$1054,">0"),0) - AT17, "") -> -0.47260274 | AV17: =IF(AQ17<>"", AU17*(1+$X$9/CompoundingRate)^-((AQ17-AQ$3)/(365/CompoundingRate)), "") -> -0.47260274
A18: 44392 | B18: Water Rates | H18: 131.66 | M18: =IF($A18<>"", IF(ISNUMBER(SEARCH("Debt Cost (est.)",B18)), SUMIFS(AT:AT, AQ:AQ, ">="&DATE("20"&RIGHT(LEFT(B18,4),2)-1,7,1), AQ:AQ, "<="&DATE("20"&RIGHT(LEFT(B18,4),2),6,30)), ""), "") | AA18: =IF($A18<>"", MIN(AB18,$P$3), "") -> 3450000 | AB18: =IF($A18<>"", AC18+AD18, "") -> 3450000 | AC18: =IF(A18<>"", AC17+D18+F18-G18, "") -> 517500 | AD18: =IF(A18<>"", AD17+C18-F18+G18, "") -> 2932500 | AE18: =IF(A19<>"", A19-A18, IF(A18<>"",IF(AC18<>0,TODAY()-A18,0), "")) -> 0 | AG18: =IF($A18<>"", I18+J18+E18-F18-H18, "") -> -131.66 | AH18: =IF(A18<>"", A18-A$3, "") -> 41 | AI18: =IF(A18<>"", AG18*(1+$X$3)^-(AH18/365), "") -> -131.66 | AL18: =IF($A18<>"", AG18-IF(ISNUMBER(K18),K18*L18,0), "") -> -131.66 | AM18: =IF(A18<>"", AL18*(1+$X$6/CompoundingRate)^-(AH18/(365/CompoundingRate)), "") -> -131.66 | AQ18: =IF(AQ17<$AP$3,AQ17+1,"") -> 44366 | AR18: =IF($AQ18<>"", INDEX($AC$3:$AC$1055, MATCH($AQ18,$A$3:$A$1055,1)), "") -> 172500 | AS18: =IF($AQ18<>"", INDEX(Inputs!$B$3:$B$101, MATCH($AQ18,Inputs!$A$3:$A$101,1)), "") -> 0.001 | AT18: =IF($AQ18<>"", AR18*AS18/365, "") -> 0.47260274 | AU18: =IF($AQ18<>"", SUMIFS($AL$3:$AL$1054, $A$3:$A$1054,$AQ18) + SUMIFS($M$3:$M$1054, $A$3:$A$1054,$AQ18)*IFERROR(AVERAGEIFS($L$3:$L$1054, $A$3:$A$1054,$AQ18, $M$3:$M$1054,">0"),0) - AT18, "") -> -0.47260274 | AV18: =IF(AQ18<>"", AU18*(1+$X$9/CompoundingRate)^-((AQ18-AQ$3)/(365/CompoundingRate)), "") -> -0.47260274
A19: 44392 | B19: Land Tax | H19: 3407.78 | M19: =IF($A19<>"", IF(ISNUMBER(SEARCH("Debt Cost (est.)",B19)), SUMIFS(AT:AT, AQ:AQ, ">="&DATE("20"&RIGHT(LEFT(B19,4),2)-1,7,1), AQ:AQ, "<="&DATE("20"&RIGHT(LEFT(B19,4),2),6,30)), ""), "") | AA19: =IF($A19<>"", MIN(AB19,$P$3), "") -> 3450000 | AB19: =IF($A19<>"", AC19+AD19, "") -> 3450000 | AC19: =IF(A19<>"", AC18+D19+F19-G19, "") -> 517500 | AD19: =IF(A19<>"", AD18+C19-F19+G19, "") -> 2932500 | AE19: =IF(A20<>"", A20-A19, IF(A19<>"",IF(AC19<>0,TODAY()-A19,0), "")) -> 0 | AG19: =IF($A19<>"", I19+J19+E19-F19-H19, "") -> -3407.78 | AH19: =IF(A19<>"", A19-A$3, "") -> 41 | AI19: =IF(A19<>"", AG19*(1+$X$3)^-(AH19/365), "") -> -3407.78 | AL19: =IF($A19<>"", AG19-IF(ISNUMBER(K19),K19*L19,0), "") -> -3407.78 | AM19: =IF(A19<>"", AL19*(1+$X$6/CompoundingRate)^-(AH19/(365/CompoundingRate)), "") -> -3407.78 | AQ19: =IF(AQ18<$AP$3,AQ18+1,"") -> 44367 | AR19: =IF($AQ19<>"", INDEX($AC$3:$AC$1055, MATCH($AQ19,$A$3:$A$1055,1)), "") -> 172500 | AS19: =IF($AQ19<>"", INDEX(Inputs!$B$3:$B$101, MATCH($AQ19,Inputs!$A$3:$A$101,1)), "") -> 0.001 | AT19: =IF($AQ19<>"", AR19*AS19/365, "") -> 0.47260274 | AU19: =IF($AQ19<>"", SUMIFS($AL$3:$AL$1054, $A$3:$A$1054,$AQ19) + SUMIFS($M$3:$M$1054, $A$3:$A$1054,$AQ19)*IFERROR(AVERAGEIFS($L$3:$L$1054, $A$3:$A$1054,$AQ19, $M$3:$M$1054,">0"),0) - AT19, "") -> -0.47260274 | AV19: =IF(AQ19<>"", AU19*(1+$X$9/CompoundingRate)^-((AQ19-AQ$3)/(365/CompoundingRate)), "") -> -0.47260274
A20: 44392 | B20: Strata Levies | H20: 325.22 | M20: =IF($A20<>"", IF(ISNUMBER(SEARCH("Debt Cost (est.)",B20)), SUMIFS(AT:AT, AQ:AQ, ">="&DATE("20"&RIGHT(LEFT(B20,4),2)-1,7,1), AQ:AQ, "<="&DATE("20"&RIGHT(LEFT(B20,4),2),6,30)), ""), "") | AA20: =IF($A20<>"", MIN(AB20,$P$3), "") -> 3450000 | AB20: =IF($A20<>"", AC20+AD20, "") -> 3450000 | AC20: =IF(A20<>"", AC19+D20+F20-G20, "") -> 517500 | AD20: =IF(A20<>"", AD19+C20-F20+G20, "") -> 2932500 | AE20: =IF(A21<>"", A21-A20, IF(A20<>"",IF(AC20<>0,TODAY()-A20,0), "")) -> 1 | AG20: =IF($A20<>"", I20+J20+E20-F20-H20, "") -> -325.22 | AH20: =IF(A20<>"", A20-A$3, "") -> 41 | AI20: =IF(A20<>"", AG20*(1+$X$3)^-(AH20/365), "") -> -325.22 | AL20: =IF($A20<>"", AG20-IF(ISNUMBER(K20),K20*L20,0), "") -> -325.22 | AM20: =IF(A20<>"", AL20*(1+$X$6/CompoundingRate)^-(AH20/(365/CompoundingRate)), "") -> -325.22 | AQ20: =IF(AQ19<$AP$3,AQ19+1,"") -> 44368 | AR20: =IF($AQ20<>"", INDEX($AC$3:$AC$1055, MATCH($AQ20,$A$3:$A$1055,1)), "") -> 172500 | AS20: =IF($AQ20<>"", INDEX(Inputs!$B$3:$B$101, MATCH($AQ20,Inputs!$A$3:$A$101,1)), "") -> 0.001 | AT20: =IF($AQ20<>"", AR20*AS20/365, "") -> 0.47260274 | AU20: =IF($AQ20<>"", SUMIFS($AL$3:$AL$1054, $A$3:$A$1054,$AQ20) + SUMIFS($M$3:$M$1054, $A$3:$A$1054,$AQ20)*IFERROR(AVERAGEIFS($L$3:$L$1054, $A$3:$A$1054,$AQ20, $M$3:$M$1054,">0"),0) - AT20, "") -> -0.47260274 | AV20: =IF(AQ20<>"", AU20*(1+$X$9/CompoundingRate)^-((AQ20-AQ$3)/(365/CompoundingRate)), "") -> -0.47260274
A21: 44393 | B21: Billi | H21: 2020 | M21: =IF($A21<>"", IF(ISNUMBER(SEARCH("Debt Cost (est.)",B21)), SUMIFS(AT:AT, AQ:AQ, ">="&DATE("20"&RIGHT(LEFT(B21,4),2)-1,7,1), AQ:AQ, "<="&DATE("20"&RIGHT(LEFT(B21,4),2),6,30)), ""), "") | AA21: =IF($A21<>"", MIN(AB21,$P$3), "") -> 3450000 | AB21: =IF($A21<>"", AC21+AD21, "") -> 3450000 | AC21: =IF(A21<>"", AC20+D21+F21-G21, "") -> 517500 | AD21: =IF(A21<>"", AD20+C21-F21+G21, "") -> 2932500 | AE21: =IF(A22<>"", A22-A21, IF(A21<>"",IF(AC21<>0,TODAY()-A21,0), "")) -> 0 | AG21: =IF($A21<>"", I21+J21+E21-F21-H21, "") -> -2020 | AH21: =IF(A21<>"", A21-A$3, "") -> 42 | AI21: =IF(A21<>"", AG21*(1+$X$3)^-(AH21/365), "") -> -2020 | AL21: =IF($A21<>"", AG21-IF(ISNUMBER(K21),K21*L21,0), "") -> -2020 | AM21: =IF(A21<>"", AL21*(1+$X$6/CompoundingRate)^-(AH21/(365/CompoundingRate)), "") -> -2020 | AQ21: =IF(AQ20<$AP$3,AQ20+1,"") -> 44369 | AR21: =IF($AQ21<>"", INDEX($AC$3:$AC$1055, MATCH($AQ21,$A$3:$A$1055,1)), "") -> 172500 | AS21: =IF($AQ21<>"", INDEX(Inputs!$B$3:$B$101, MATCH($AQ21,Inputs!$A$3:$A$101,1)), "") -> 0.001 | AT21: =IF($AQ21<>"", AR21*AS21/365, "") -> 0.47260274 | AU21: =IF($AQ21<>"", SUMIFS($AL$3:$AL$1054, $A$3:$A$1054,$AQ21) + SUMIFS($M$3:$M$1054, $A$3:$A$1054,$AQ21)*IFERROR(AVERAGEIFS($L$3:$L$1054, $A$3:$A$1054,$AQ21, $M$3:$M$1054,">0"),0) - AT21, "") -> -0.47260274 | AV21: =IF(AQ21<>"", AU21*(1+$X$9/CompoundingRate)^-((AQ21-AQ$3)/(365/CompoundingRate)), "") -> -0.47260274
A22: 44393 | B22: Locksmith | H22: 180 | M22: =IF($A22<>"", IF(ISNUMBER(SEARCH("Debt Cost (est.)",B22)), SUMIFS(AT:AT, AQ:AQ, ">="&DATE("20"&RIGHT(LEFT(B22,4),2)-1,7,1), AQ:AQ, "<="&DATE("20"&RIGHT(LEFT(B22,4),2),6,30)), ""), "") | AA22: =IF($A22<>"", MIN(AB22,$P$3), "") -> 3450000 | AB22: =IF($A22<>"", AC22+AD22, "") -> 3450000 | AC22: =IF(A22<>"", AC21+D22+F22-G22, "") -> 517500 | AD22: =IF(A22<>"", AD21+C22-F22+G22, "") -> 2932500 | AE22: =IF(A23<>"", A23-A22, IF(A22<>"",IF(AC22<>0,TODAY()-A22,0), "")) -> 0 | AG22: =IF($A22<>"", I22+J22+E22-F22-H22, "") -> -180 | AH22: =IF(A22<>"", A22-A$3, "") -> 42 | AI22: =IF(A22<>"", AG22*(1+$X$3)^-(AH22/365), "") -> -180 | AL22: =IF($A22<>"", AG22-IF(ISNUMBER(K22),K22*L22,0), "") -> -180 | AM22: =IF(A22<>"", AL22*(1+$X$6/CompoundingRate)^-(AH22/(365/CompoundingRate)), "") -> -180 | AQ22: =IF(AQ21<$AP$3,AQ21+1,"") -> 44370 | AR22: =IF($AQ22<>"", INDEX($AC$3:$AC$1055, MATCH($AQ22,$A$3:$A$1055,1)), "") -> 172500 | AS22: =IF($AQ22<>"", INDEX(Inputs!$B$3:$B$101, MATCH($AQ22,Inputs!$A$3:$A$101,1)), "") -> 0.001 | AT22: =IF($AQ22<>"", AR22*AS22/365, "") -> 0.47260274 | AU22: =IF($AQ22<>"", SUMIFS($AL$3:$AL$1054, $A$3:$A$1054,$AQ22) + SUMIFS($M$3:$M$1054, $A$3:$A$1054,$AQ22)*IFERROR(AVERAGEIFS($L$3:$L$1054, $A$3:$A$1054,$AQ22, $M$3:$M$1054,">0"),0) - AT22, "") -> -0.47260274 | AV22: =IF(AQ22<>"", AU22*(1+$X$9/CompoundingRate)^-((AQ22-AQ$3)/(365/CompoundingRate)), "") -> -0.47260274
A23: 44393 | B23: Insinkerator | H23: 1090 | M23: =IF($A23<>"", IF(ISNUMBER(SEARCH("Debt Cost (est.)",B23)), SUMIFS(AT:AT, AQ:AQ, ">="&DATE("20"&RIGHT(LEFT(B23,4),2)-1,7,1), AQ:AQ, "<="&DATE("20"&RIGHT(LEFT(B23,4),2),6,30)), ""), "") | AA23: =IF($A23<>"", MIN(AB23,$P$3), "") -> 3450000 | AB23: =IF($A23<>"", AC23+AD23, "") -> 3450000 | AC23: =IF(A23<>"", AC22+D23+F23-G23, "") -> 517500 | AD23: =IF(A23<>"", AD22+C23-F23+G23, "") -> 2932500 | AE23: =IF(A24<>"", A24-A23, IF(A23<>"",IF(AC23<>0,TODAY()-A23,0), "")) -> 0 | AG23: =IF($A23<>"", I23+J23+E23-F23-H23, "") -> -1090 | AH23: =IF(A23<>"", A23-A$3, "") -> 42 | AI23: =IF(A23<>"", AG23*(1+$X$3)^-(AH23/365), "") -> -1090 | AL23: =IF($A23<>"", AG23-IF(ISNUMBER(K23),K23*L23,0), "") -> -1090 | AM23: =IF(A23<>"", AL23*(1+$X$6/CompoundingRate)^-(AH23/(365/CompoundingRate)), "") -> -1090 | AQ23: =IF(AQ22<$AP$3,AQ22+1,"") -> 44371 | AR23: =IF($AQ23<>"", INDEX($AC$3:$AC$1055, MATCH($AQ23,$A$3:$A$1055,1)), "") -> 172500 | AS23: =IF($AQ23<>"", INDEX(Inputs!$B$3:$B$101, MATCH($AQ23,Inputs!$A$3:$A$101,1)), "") -> 0.001 | AT23: =IF($AQ23<>"", AR23*AS23/365, "") -> 0.47260274 | AU23: =IF($AQ23<>"", SUMIFS($AL$3:$AL$1054, $A$3:$A$1054,$AQ23) + SUMIFS($M$3:$M$1054, $A$3:$A$1054,$AQ23)*IFERROR(AVERAGEIFS($L$3:$L$1054, $A$3:$A$1054,$AQ23, $M$3:$M$1054,">0"),0) - AT23, "") -> -0.47260274 | AV23: =IF(AQ23<>"", AU23*(1+$X$9/CompoundingRate)^-((AQ23-AQ$3)/(365/CompoundingRate)), "") -> -0.47260274
A24: 44393 | B24: Blinds | H24: =2500+4749 -> 7249 | M24: =IF($A24<>"", IF(ISNUMBER(SEARCH("Debt Cost (est.)",B24)), SUMIFS(AT:AT, AQ:AQ, ">="&DATE("20"&RIGHT(LEFT(B24,4),2)-1,7,1), AQ:AQ, "<="&DATE("20"&RIGHT(LEFT(B24,4),2),6,30)), ""), "") | AA24: =IF($A24<>"", MIN(AB24,$P$3), "") -> 3450000 | AB24: =IF($A24<>"", AC24+AD24, "") -> 3450000 | AC24: =IF(A24<>"", AC23+D24+F24-G24, "") -> 517500 | AD24: =IF(A24<>"", AD23+C24-F24+G24, "") -> 2932500 | AE24: =IF(A25<>"", A25-A24, IF(A24<>"",IF(AC24<>0,TODAY()-A24,0), "")) -> 0 | AG24: =IF($A24<>"", I24+J24+E24-F24-H24, "") -> -7249 | AH24: =IF(A24<>"", A24-A$3, "") -> 42 | AI24: =IF(A24<>"", AG24*(1+$X$3)^-(AH24/365), "") -> -7249 | AL24: =IF($A24<>"", AG24-IF(ISNUMBER(K24),K24*L24,0), "") -> -7249 | AM24: =IF(A24<>"", AL24*(1+$X$6/CompoundingRate)^-(AH24/(365/CompoundingRate)), "") -> -7249 | AQ24: =IF(AQ23<$AP$3,AQ23+1,"") -> 44372 | AR24: =IF($AQ24<>"", INDEX($AC$3:$AC$1055, MATCH($AQ24,$A$3:$A$1055,1)), "") -> 172500 | AS24: =IF($AQ24<>"", INDEX(Inputs!$B$3:$B$101, MATCH($AQ24,Inputs!$A$3:$A$101,1)), "") -> 0.001 | AT24: =IF($AQ24<>"", AR24*AS24/365, "") -> 0.47260274 | AU24: =IF($AQ24<>"", SUMIFS($AL$3:$AL$1054, $A$3:$A$1054,$AQ24) + SUMIFS($M$3:$M$1054, $A$3:$A$1054,$AQ24)*IFERROR(AVERAGEIFS($L$3:$L$1054, $A$3:$A$1054,$AQ24, $M$3:$M$1054,">0"),0) - AT24, "") -> -0.47260274 | AV24: =IF(AQ24<>"", AU24*(1+$X$9/CompoundingRate)^-((AQ24-AQ$3)/(365/CompoundingRate)), "") -> -0.47260274
A25: 44393 | B25: Washer + Dryer | H25: 2669.95 | M25: =IF($A25<>"", IF(ISNUMBER(SEARCH("Debt Cost (est.)",B25)), SUMIFS(AT:AT, AQ:AQ, ">="&DATE("20"&RIGHT(LEFT(B25,4),2)-1,7,1), AQ:AQ, "<="&DATE("20"&RIGHT(LEFT(B25,4),2),6,30)), ""), "") | AA25: =IF($A25<>"", MIN(AB25,$P$3), "") -> 3450000 | AB25: =IF($A25<>"", AC25+AD25, "") -> 3450000 | AC25: =IF(A25<>"", AC24+D25+F25-G25, "") -> 517500 | AD25: =IF(A25<>"", AD24+C25-F25+G25, "") -> 2932500 | AE25: =IF(A26<>"", A26-A25, IF(A25<>"",IF(AC25<>0,TODAY()-A25,0), "")) -> 0 | AG25: =IF($A25<>"", I25+J25+E25-F25-H25, "") -> -2669.95 | AH25: =IF(A25<>"", A25-A$3, "") -> 42 | AI25: =IF(A25<>"", AG25*(1+$X$3)^-(AH25/365), "") -> -2669.95 | AL25: =IF($A25<>"", AG25-IF(ISNUMBER(K25),K25*L25,0), "") -> -2669.95 | AM25: =IF(A25<>"", AL25*(1+$X$6/CompoundingRate)^-(AH25/(365/CompoundingRate)), "") -> -2669.95 | AQ25: =IF(AQ24<$AP$3,AQ24+1,"") -> 44373 | AR25: =IF($AQ25<>"", INDEX($AC$3:$AC$1055, MATCH($AQ25,$A$3:$A$1055,1)), "") -> 172500 | AS25: =IF($AQ25<>"", INDEX(Inputs!$B$3:$B$101, MATCH($AQ25,Inputs!$A$3:$A$101,1)), "") -> 0.001 | AT25: =IF($AQ25<>"", AR25*AS25/365, "") -> 0.47260274 | AU25: =IF($AQ25<>"", SUMIFS($AL$3:$AL$1054, $A$3:$A$1054,$AQ25) + SUMIFS($M$3:$M$1054, $A$3:$A$1054,$AQ25)*IFERROR(AVERAGEIFS($L$3:$L$1054, $A$3:$A$1054,$AQ25, $M$3:$M$1054,">0"),0) - AT25, "") -> -0.47260274 | AV25: =IF(AQ25<>"", AU25*(1+$X$9/CompoundingRate)^-((AQ25-AQ$3)/(365/CompoundingRate)), "") -> -0.47260274
A26: 44393 | B26: Air Conditioning | H26: 198 | M26: =IF($A26<>"", IF(ISNUMBER(SEARCH("Debt Cost (est.)",B26)), SUMIFS(AT:AT, AQ:AQ, ">="&DATE("20"&RIGHT(LEFT(B26,4),2)-1,7,1), AQ:AQ, "<="&DATE("20"&RIGHT(LEFT(B26,4),2),6,30)), ""), "") | AA26: =IF($A26<>"", MIN(AB26,$P$3), "") -> 3450000 | AB26: =IF($A26<>"", AC26+AD26, "") -> 3450000 | AC26: =IF(A26<>"", AC25+D26+F26-G26, "") -> 517500 | AD26: =IF(A26<>"", AD25+C26-F26+G26, "") -> 2932500 | AE26: =IF(A27<>"", A27-A26, IF(A26<>"",IF(AC26<>0,TODAY()-A26,0), "")) -> 0 | AG26: =IF($A26<>"", I26+J26+E26-F26-H26, "") -> -198 | AH26: =IF(A26<>"", A26-A$3, "") -> 42 | AI26: =IF(A26<>"", AG26*(1+$X$3)^-(AH26/365), "") -> -198 | AL26: =IF($A26<>"", AG26-IF(ISNUMBER(K26),K26*L26,0), "") -> -198 | AM26: =IF(A26<>"", AL26*(1+$X$6/CompoundingRate)^-(AH26/(365/CompoundingRate)), "") -> -198 | AQ26: =IF(AQ25<$AP$3,AQ25+1,"") -> 44374 | AR26: =IF($AQ26<>"", INDEX($AC$3:$AC$1055, MATCH($AQ26,$A$3:$A$1055,1)), "") -> 172500 | AS26: =IF($AQ26<>"", INDEX(Inputs!$B$3:$B$101, MATCH($AQ26,Inputs!$A$3:$A$101,1)), "") -> 0.001 | AT26: =IF($AQ26<>"", AR26*AS26/365, "") -> 0.47260274 | AU26: =IF($AQ26<>"", SUMIFS($AL$3:$AL$1054, $A$3:$A$1054,$AQ26) + SUMIFS($M$3:$M$1054, $A$3:$A$1054,$AQ26)*IFERROR(AVERAGEIFS($L$3:$L$1054, $A$3:$A$1054,$AQ26, $M$3:$M$1054,">0"),0) - AT26, "") -> -0.47260274 | AV26: =IF(AQ26<>"", AU26*(1+$X$9/CompoundingRate)^-((AQ26-AQ$3)/(365/CompoundingRate)), "") -> -0.47260274
A27: 44393 | B27: General Repairs | H27: 720 | M27: =IF($A27<>"", IF(ISNUMBER(SEARCH("Debt Cost (est.)",B27)), SUMIFS(AT:AT, AQ:AQ, ">="&DATE("20"&RIGHT(LEFT(B27,4),2)-1,7,1), AQ:AQ, "<="&DATE("20"&RIGHT(LEFT(B27,4),2),6,30)), ""), "") | AA27: =IF($A27<>"", MIN(AB27,$P$3), "") -> 3450000 | AB27: =IF($A27<>"", AC27+AD27, "") -> 3450000 | AC27: =IF(A27<>"", AC26+D27+F27-G27, "") -> 517500 | AD27: =IF(A27<>"", AD26+C27-F27+G27, "") -> 2932500 | AE27: =IF(A28<>"", A28-A27, IF(A27<>"",IF(AC27<>0,TODAY()-A27,0), "")) -> 0 | AG27: =IF($A27<>"", I27+J27+E27-F27-H27, "") -> -720 | AH27: =IF(A27<>"", A27-A$3, "") -> 42 | AI27: =IF(A27<>"", AG27*(1+$X$3)^-(AH27/365), "") -> -720 | AL27: =IF($A27<>"", AG27-IF(ISNUMBER(K27),K27*L27,0), "") -> -720 | AM27: =IF(A27<>"", AL27*(1+$X$6/CompoundingRate)^-(AH27/(365/CompoundingRate)), "") -> -720 | AQ27: =IF(AQ26<$AP$3,AQ26+1,"") -> 44375 | AR27: =IF($AQ27<>"", INDEX($AC$3:$AC$1055, MATCH($AQ27,$A$3:$A$1055,1)), "") -> 172500 | AS27: =IF($AQ27<>"", INDEX(Inputs!$B$3:$B$101, MATCH($AQ27,Inputs!$A$3:$A$101,1)), "") -> 0.001 | AT27: =IF($AQ27<>"", AR27*AS27/365, "") -> 0.47260274 | AU27: =IF($AQ27<>"", SUMIFS($AL$3:$AL$1054, $A$3:$A$1054,$AQ27) + SUMIFS($M$3:$M$1054, $A$3:$A$1054,$AQ27)*IFERROR(AVERAGEIFS($L$3:$L$1054, $A$3:$A$1054,$AQ27, $M$3:$M$1054,">0"),0) - AT27, "") -> -0.47260274 | AV27: =IF(AQ27<>"", AU27*(1+$X$9/CompoundingRate)^-((AQ27-AQ$3)/(365/CompoundingRate)), "") -> -0.47260274
A28: 44393 | B28: Rent - Andre | I28: 1900 | M28: =IF($A28<>"", IF(ISNUMBER(SEARCH("Debt Cost (est.)",B28)), SUMIFS(AT:AT, AQ:AQ, ">="&DATE("20"&RIGHT(LEFT(B28,4),2)-1,7,1), AQ:AQ, "<="&DATE("20"&RIGHT(LEFT(B28,4),2),6,30)), ""), "") | AA28: =IF($A28<>"", MIN(AB28,$P$3), "") -> 3450000 | AB28: =IF($A28<>"", AC28+AD28, "") -> 3450000 | AC28: =IF(A28<>"", AC27+D28+F28-G28, "") -> 517500 | AD28: =IF(A28<>"", AD27+C28-F28+G28, "") -> 2932500 | AE28: =IF(A29<>"", A29-A28, IF(A28<>"",IF(AC28<>0,TODAY()-A28,0), "")) -> 3 | AG28: =IF($A28<>"", I28+J28+E28-F28-H28, "") -> 1900 | AH28: =IF(A28<>"", A28-A$3, "") -> 42 | AI28: =IF(A28<>"", AG28*(1+$X$3)^-(AH28/365), "") -> 1900 | AL28: =IF($A28<>"", AG28-IF(ISNUMBER(K28),K28*L28,0), "") -> 1900 | AM28: =IF(A28<>"", AL28*(1+$X$6/CompoundingRate)^-(AH28/(365/CompoundingRate)), "") -> 1900 | AQ28: =IF(AQ27<$AP$3,AQ27+1,"") -> 44376 | AR28: =IF($AQ28<>"", INDEX($AC$3:$AC$1055, MATCH($AQ28,$A$3:$A$1055,1)), "") -> 172500 | AS28: =IF($AQ28<>"", INDEX(Inputs!$B$3:$B$101, MATCH($AQ28,Inputs!$A$3:$A$101,1)), "") -> 0.001 | AT28: =IF($AQ28<>"", AR28*AS28/365, "") -> 0.47260274 | AU28: =IF($AQ28<>"", SUMIFS($AL$3:$AL$1054, $A$3:$A$1054,$AQ28) + SUMIFS($M$3:$M$1054, $A$3:$A$1054,$AQ28)*IFERROR(AVERAGEIFS($L$3:$L$1054, $A$3:$A$1054,$AQ28, $M$3:$M$1054,">0"),0) - AT28, "") -> -0.47260274 | AV28: =IF(AQ28<>"", AU28*(1+$X$9/CompoundingRate)^-((AQ28-AQ$3)/(365/CompoundingRate)), "") -> -0.47260274
A29: 44396 | B29: Landlords Insurance | H29: 587.76 | M29: =IF($A29<>"", IF(ISNUMBER(SEARCH("Debt Cost (est.)",B29)), SUMIFS(AT:AT, AQ:AQ, ">="&DATE("20"&RIGHT(LEFT(B29,4),2)-1,7,1), AQ:AQ, "<="&DATE("20"&RIGHT(LEFT(B29,4),2),6,30)), ""), "") | AA29: =IF($A29<>"", MIN(AB29,$P$3), "") -> 3450000 | AB29: =IF($A29<>"", AC29+AD29, "") -> 3450000 | AC29: =IF(A29<>"", AC28+D29+F29-G29, "") -> 517500 | AD29: =IF(A29<>"", AD28+C29-F29+G29, "") -> 2932500 | AE29: =IF(A30<>"", A30-A29, IF(A29<>"",IF(AC29<>0,TODAY()-A29,0), "")) -> 4 | AG29: =IF($A29<>"", I29+J29+E29-F29-H29, "") -> -587.76 | AH29: =IF(A29<>"", A29-A$3, "") -> 45 | AI29: =IF(A29<>"", AG29*(1+$X$3)^-(AH29/365), "") -> -587.76 | AL29: =IF($A29<>"", AG29-IF(ISNUMBER(K29),K29*L29,0), "") -> -587.76 | AM29: =IF(A29<>"", AL29*(1+$X$6/CompoundingRate)^-(AH29/(365/CompoundingRate)), "") -> -587.76 | AQ29: =IF(AQ28<$AP$3,AQ28+1,"") -> 44377 | AR29: =IF($AQ29<>"", INDEX($AC$3:$AC$1055, MATCH($AQ29,$A$3:$A$1055,1)), "") -> 172500 | AS29: =IF($AQ29<>"", INDEX(Inputs!$B$3:$B$101, MATCH($AQ29,Inputs!$A$3:$A$101,1)), "") -> 0.001 | AT29: =IF($AQ29<>"", AR29*AS29/365, "") -> 0.47260274 | AU29: =IF($AQ29<>"", SUMIFS($AL$3:$AL$1054, $A$3:$A$1054,$AQ29) + SUMIFS($M$3:$M$1054, $A$3:$A$1054,$AQ29)*IFERROR(AVERAGEIFS($L$3:$L$1054, $A$3:$A$1054,$AQ29, $M$3:$M$1054,">0"),0) - AT29, "") -> 3.6744863 | AV29: =IF(AQ29<>"", AU29*(1+$X$9/CompoundingRate)^-((AQ29-AQ$3)/(365/CompoundingRate)), "") -> 3.6744863
A30: 44400 | B30: Rent - Andre | I30: 1900 | M30: =IF($A30<>"", IF(ISNUMBER(SEARCH("Debt Cost (est.)",B30)), SUMIFS(AT:AT, AQ:AQ, ">="&DATE("20"&RIGHT(LEFT(B30,4),2)-1,7,1), AQ:AQ, "<="&DATE("20"&RIGHT(LEFT(B30,4),2),6,30)), ""), "") | AA30: =IF($A30<>"", MIN(AB30,$P$3), "") -> 3450000 | AB30: =IF($A30<>"", AC30+AD30, "") -> 3450000 | AC30: =IF(A30<>"", AC29+D30+F30-G30, "") -> 517500 | AD30: =IF(A30<>"", AD29+C30-F30+G30, "") -> 2932500 | AE30: =IF(A31<>"", A31-A30, IF(A30<>"",IF(AC30<>0,TODAY()-A30,0), "")) -> 7 | AG30: =IF($A30<>"", I30+J30+E30-F30-H30, "") -> 1900 | AH30: =IF(A30<>"", A30-A$3, "") -> 49 | AI30: =IF(A30<>"", AG30*(1+$X$3)^-(AH30/365), "") -> 1900 | AL30: =IF($A30<>"", AG30-IF(ISNUMBER(K30),K30*L30,0), "") -> 1900 | AM30: =IF(A30<>"", AL30*(1+$X$6/CompoundingRate)^-(AH30/(365/CompoundingRate)), "") -> 1900 | AQ30: =IF(AQ29<$AP$3,AQ29+1,"") -> 44378 | AR30: =IF($AQ30<>"", INDEX($AC$3:$AC$1055, MATCH($AQ30,$A$3:$A$1055,1)), "") -> 172500 | AS30: =IF($AQ30<>"", INDEX(Inputs!$B$3:$B$101, MATCH($AQ30,Inputs!$A$3:$A$101,1)), "") -> 0.001 | AT30: =IF($AQ30<>"", AR30*AS30/365, "") -> 0.47260274 | AU30: =IF($AQ30<>"", SUMIFS($AL$3:$AL$1054, $A$3:$A$1054,$AQ30) + SUMIFS($M$3:$M$1054, $A$3:$A$1054,$AQ30)*IFERROR(AVERAGEIFS($L$3:$L$1054, $A$3:$A$1054,$AQ30, $M$3:$M$1054,">0"),0) - AT30, "") -> -0.47260274 | AV30: =IF(AQ30<>"", AU30*(1+$X$9/CompoundingRate)^-((AQ30-AQ$3)/(365/CompoundingRate)), "") -> -0.47260274
A31: 44407 | B31: Rent - Andre | I31: 1900 | M31: =IF($A31<>"", IF(ISNUMBER(SEARCH("Debt Cost (est.)",B31)), SUMIFS(AT:AT, AQ:AQ, ">="&DATE("20"&RIGHT(LEFT(B31,4),2)-1,7,1), AQ:AQ, "<="&DATE("20"&RIGHT(LEFT(B31,4),2),6,30)), ""), "") | AA31: =IF($A31<>"", MIN(AB31,$P$3), "") -> 3450000 | AB31: =IF($A31<>"", AC31+AD31, "") -> 3450000 | AC31: =IF(A31<>"", AC30+D31+F31-G31, "") -> 517500 | AD31: =IF(A31<>"", AD30+C31-F31+G31, "") -> 2932500 | AE31: =IF(A32<>"", A32-A31, IF(A31<>"",IF(AC31<>0,TODAY()-A31,0), "")) -> 0 | AG31: =IF($A31<>"", I31+J31+E31-F31-H31, "") -> 1900 | AH31: =IF(A31<>"", A31-A$3, "") -> 56 | AI31: =IF(A31<>"", AG31*(1+$X$3)^-(AH31/365), "") -> 1900 | AL31: =IF($A31<>"", AG31-IF(ISNUMBER(K31),K31*L31,0), "") -> 1900 | AM31: =IF(A31<>"", AL31*(1+$X$6/CompoundingRate)^-(AH31/(365/CompoundingRate)), "") -> 1900 | AQ31: =IF(AQ30<$AP$3,AQ30+1,"") -> 44379 | AR31: =IF($AQ31<>"", INDEX($AC$3:$AC$1055, MATCH($AQ31,$A$3:$A$1055,1)), "") -> 172500 | AS31: =IF($AQ31<>"", INDEX(Inputs!$B$3:$B$101, MATCH($AQ31,Inputs!$A$3:$A$101,1)), "") -> 0.001 | AT31: =IF($AQ31<>"", AR31*AS31/365, "") -> 0.47260274 | AU31: =IF($AQ31<>"", SUMIFS($AL$3:$AL$1054, $A$3:$A$1054,$AQ31) + SUMIFS($M$3:$M$1054, $A$3:$A$1054,$AQ31)*IFERROR(AVERAGEIFS($L$3:$L$1054, $A$3:$A$1054,$AQ31, $M$3:$M$1054,">0"),0) - AT31, "") -> -0.47260274 | AV31: =IF(AQ31<>"", AU31*(1+$X$9/CompoundingRate)^-((AQ31-AQ$3)/(365/CompoundingRate)), "") -> -0.47260274
A32: 44407 | B32: NAB #3063 - Interest | G32: 1940.67 | M32: =IF($A32<>"", IF(ISNUMBER(SEARCH("Debt Cost (est.)",B32)), SUMIFS(AT:AT, AQ:AQ, ">="&DATE("20"&RIGHT(LEFT(B32,4),2)-1,7,1), AQ:AQ, "<="&DATE("20"&RIGHT(LEFT(B32,4),2),6,30)), ""), "") | AA32: =IF($A32<>"", MIN(AB32,$P$3), "") -> 3450000 | AB32: =IF($A32<>"", AC32+AD32, "") -> 3450000 | AC32: =IF(A32<>"", AC31+D32+F32-G32, "") -> 515559.33 | AD32: =IF(A32<>"", AD31+C32-F32+G32, "") -> 2934440.7 | AE32: =IF(A33<>"", A33-A32, IF(A32<>"",IF(AC32<>0,TODAY()-A32,0), "")) -> 0 | AG32: =IF($A32<>"", I32+J32+E32-F32-H32, "") -> 0 | AH32: =IF(A32<>"", A32-A$3, "") -> 56 | AI32: =IF(A32<>"", AG32*(1+$X$3)^-(AH32/365), "") -> 0 | AL32: =IF($A32<>"", AG32-IF(ISNUMBER(K32),K32*L32,0), "") -> 0 | AM32: =IF(A32<>"", AL32*(1+$X$6/CompoundingRate)^-(AH32/(365/CompoundingRate)), "") -> 0 | AQ32: =IF(AQ31<$AP$3,AQ31+1,"") -> 44380 | AR32: =IF($AQ32<>"", INDEX($AC$3:$AC$1055, MATCH($AQ32,$A$3:$A$1055,1)), "") -> 172500 | AS32: =IF($AQ32<>"", INDEX(Inputs!$B$3:$B$101, MATCH($AQ32,Inputs!$A$3:$A$101,1)), "") -> 0.001 | AT32: =IF($AQ32<>"", AR32*AS32/365, "") -> 0.47260274 | AU32: =IF($AQ32<>"", SUMIFS($AL$3:$AL$1054, $A$3:$A$1054,$AQ32) + SUMIFS($M$3:$M$1054, $A$3:$A$1054,$AQ32)*IFERROR(AVERAGEIFS($L$3:$L$1054, $A$3:$A$1054,$AQ32, $M$3:$M$1054,">0"),0) - AT32, "") -> -0.47260274 | AV32: =IF(AQ32<>"", AU32*(1+$X$9/CompoundingRate)^-((AQ32-AQ$3)/(365/CompoundingRate)), "") -> -0.47260274
A33: 44407 | B33: NAB #2157 - Interest | G33: =171.71-2.44 -> 169.27 | M33: =IF($A33<>"", IF(ISNUMBER(SEARCH("Debt Cost (est.)",B33)), SUMIFS(AT:AT, AQ:AQ, ">="&DATE("20"&RIGHT(LEFT(B33,4),2)-1,7,1), AQ:AQ, "<="&DATE("20"&RIGHT(LEFT(B33,4),2),6,30)), ""), "") | AA33: =IF($A33<>"", MIN(AB33,$P$3), "") -> 3450000 | AB33: =IF($A33<>"", AC33+AD33, "") -> 3450000 | AC33: =IF(A33<>"", AC32+D33+F33-G33, "") -> 515390.06 | AD33: =IF(A33<>"", AD32+C33-F33+G33, "") -> 2934609.9 | AE33: =IF(A34<>"", A34-A33, IF(A33<>"",IF(AC33<>0,TODAY()-A33,0), "")) -> 7 | AG33: =IF($A33<>"", I33+J33+E33-F33-H33, "") -> 0 | AH33: =IF(A33<>"", A33-A$3, "") -> 56 | AI33: =IF(A33<>"", AG33*(1+$X$3)^-(AH33/365), "") -> 0 | AL33: =IF($A33<>"", AG33-IF(ISNUMBER(K33),K33*L33,0), "") -> 0 | AM33: =IF(A33<>"", AL33*(1+$X$6/CompoundingRate)^-(AH33/(365/CompoundingRate)), "") -> 0 | AQ33: =IF(AQ32<$AP$3,AQ32+1,"") -> 44381 | AR33: =IF($AQ33<>"", INDEX($AC$3:$AC$1055, MATCH($AQ33,$A$3:$A$1055,1)), "") -> 172500 | AS33: =IF($AQ33<>"", INDEX(Inputs!$B$3:$B$101, MATCH($AQ33,Inputs!$A$3:$A$101,1)), "") -> 0.001 | AT33: =IF($AQ33<>"", AR33*AS33/365, "") -> 0.47260274 | AU33: =IF($AQ33<>"", SUMIFS($AL$3:$AL$1054, $A$3:$A$1054,$AQ33) + SUMIFS($M$3:$M$1054, $A$3:$A$1054,$AQ33)*IFERROR(AVERAGEIFS($L$3:$L$1054, $A$3:$A$1054,$AQ33, $M$3:$M$1054,">0"),0) - AT33, "") -> -0.47260274 | AV33: =IF(AQ33<>"", AU33*(1+$X$9/CompoundingRate)^-((AQ33-AQ$3)/(365/CompoundingRate)), "") -> -0.47260274
A34: 44414 | B34: Rent - Andre | I34: 1900 | M34: =IF($A34<>"", IF(ISNUMBER(SEARCH("Debt Cost (est.)",B34)), SUMIFS(AT:AT, AQ:AQ, ">="&DATE("20"&RIGHT(LEFT(B34,4),2)-1,7,1), AQ:AQ, "<="&DATE("20"&RIGHT(LEFT(B34,4),2),6,30)), ""), "") | AA34: =IF($A34<>"", MIN(AB34,$P$3), "") -> 3450000 | AB34: =IF($A34<>"", AC34+AD34, "") -> 3450000 | AC34: =IF(A34<>"", AC33+D34+F34-G34, "") -> 515390.06 | AD34: =IF(A34<>"", AD33+C34-F34+G34, "") -> 2934609.9 | AE34: =IF(A35<>"", A35-A34, IF(A34<>"",IF(AC34<>0,TODAY()-A34,0), "")) -> 7 | AG34: =IF($A34<>"", I34+J34+E34-F34-H34, "") -> 1900 | AH34: =IF(A34<>"", A34-A$3, "") -> 63 | AI34: =IF(A34<>"", AG34*(1+$X$3)^-(AH34/365), "") -> 1900 | AL34: =IF($A34<>"", AG34-IF(ISNUMBER(K34),K34*L34,0), "") -> 1900 | AM34: =IF(A34<>"", AL34*(1+$X$6/CompoundingRate)^-(AH34/(365/CompoundingRate)), "") -> 1900 | AQ34: =IF(AQ33<$AP$3,AQ33+1,"") -> 44382 | AR34: =IF($AQ34<>"", INDEX($AC$3:$AC$1055, MATCH($AQ34,$A$3:$A$1055,1)), "") -> 172500 | AS34: =IF($AQ34<>"", INDEX(Inputs!$B$3:$B$101, MATCH($AQ34,Inputs!$A$3:$A$101,1)), "") -> 0.001 | AT34: =IF($AQ34<>"", AR34*AS34/365, "") -> 0.47260274 | AU34: =IF($AQ34<>"", SUMIFS($AL$3:$AL$1054, $A$3:$A$1054,$AQ34) + SUMIFS($M$3:$M$1054, $A$3:$A$1054,$AQ34)*IFERROR(AVERAGEIFS($L$3:$L$1054, $A$3:$A$1054,$AQ34, $M$3:$M$1054,">0"),0) - AT34, "") -> -0.47260274 | AV34: =IF(AQ34<>"", AU34*(1+$X$9/CompoundingRate)^-((AQ34-AQ$3)/(365/CompoundingRate)), "") -> -0.47260274
A35: 44421 | B35: Rent - Andre | I35: 1900 | M35: =IF($A35<>"", IF(ISNUMBER(SEARCH("Debt Cost (est.)",B35)), SUMIFS(AT:AT, AQ:AQ, ">="&DATE("20"&RIGHT(LEFT(B35,4),2)-1,7,1), AQ:AQ, "<="&DATE("20"&RIGHT(LEFT(B35,4),2),6,30)), ""), "") | AA35: =IF($A35<>"", MIN(AB35,$P$3), "") -> 3450000 | AB35: =IF($A35<>"", AC35+AD35, "") -> 3450000 | AC35: =IF(A35<>"", AC34+D35+F35-G35, "") -> 515390.06 | AD35: =IF(A35<>"", AD34+C35-F35+G35, "") -> 2934609.9 | AE35: =IF(A36<>"", A36-A35, IF(A35<>"",IF(AC35<>0,TODAY()-A35,0), "")) -> 3 | AG35: =IF($A35<>"", I35+J35+E35-F35-H35, "") -> 1900 | AH35: =IF(A35<>"", A35-A$3, "") -> 70 | AI35: =IF(A35<>"", AG35*(1+$X$3)^-(AH35/365), "") -> 1900 | AL35: =IF($A35<>"", AG35-IF(ISNUMBER(K35),K35*L35,0), "") -> 1900 | AM35: =IF(A35<>"", AL35*(1+$X$6/CompoundingRate)^-(AH35/(365/CompoundingRate)), "") -> 1900 | AQ35: =IF(AQ34<$AP$3,AQ34+1,"") -> 44383 | AR35: =IF($AQ35<>"", INDEX($AC$3:$AC$1055, MATCH($AQ35,$A$3:$A$1055,1)), "") -> 172500 | AS35: =IF($AQ35<>"", INDEX(Inputs!$B$3:$B$101, MATCH($AQ35,Inputs!$A$3:$A$101,1)), "") -> 0.001 | AT35: =IF($AQ35<>"", AR35*AS35/365, "") -> 0.47260274 | AU35: =IF($AQ35<>"", SUMIFS($AL$3:$AL$1054, $A$3:$A$1054,$AQ35) + SUMIFS($M$3:$M$1054, $A$3:$A$1054,$AQ35)*IFERROR(AVERAGEIFS($L$3:$L$1054, $A$3:$A$1054,$AQ35, $M$3:$M$1054,">0"),0) - AT35, "") -> -0.47260274 | AV35: =IF(AQ35<>"", AU35*(1+$X$9/CompoundingRate)^-((AQ35-AQ$3)/(365/CompoundingRate)), "") -> -0.47260274
A36: 44424 | B36: NAB #3063 - Repayment | F36: 9818.51 | M36: =IF($A36<>"", IF(ISNUMBER(SEARCH("Debt Cost (est.)",B36)), SUMIFS(AT:AT, AQ:AQ, ">="&DATE("20"&RIGHT(LEFT(B36,4),2)-1,7,1), AQ:AQ, "<="&DATE("20"&RIGHT(LEFT(B36,4),2),6,30)), ""), "") | AA36: =IF($A36<>"", MIN(AB36,$P$3), "") -> 3450000 | AB36: =IF($A36<>"", AC36+AD36, "") -> 3450000 | AC36: =IF(A36<>"", AC35+D36+F36-G36, "") -> 525208.57 | AD36: =IF(A36<>"", AD35+C36-F36+G36, "") -> 2924791.4 | AE36: =IF(A37<>"", A37-A36, IF(A36<>"",IF(AC36<>0,TODAY()-A36,0), "")) -> 0 | AG36: =IF($A36<>"", I36+J36+E36-F36-H36, "") -> -9818.51 | AH36: =IF(A36<>"", A36-A$3, "") -> 73 | AI36: =IF(A36<>"", AG36*(1+$X$3)^-(AH36/365), "") -> -9818.51 | AL36: =IF($A36<>"", AG36-IF(ISNUMBER(K36),K36*L36,0), "") -> -9818.51 | AM36: =IF(A36<>"", AL36*(1+$X$6/CompoundingRate)^-(AH36/(365/CompoundingRate)), "") -> -9818.51 | AQ36: =IF(AQ35<$AP$3,AQ35+1,"") -> 44384 | AR36: =IF($AQ36<>"", INDEX($AC$3:$AC$1055, MATCH($AQ36,$A$3:$A$1055,1)), "") -> 172500 | AS36: =IF($AQ36<>"", INDEX(Inputs!$B$3:$B$101, MATCH($AQ36,Inputs!$A$3:$A$101,1)), "") -> 0.001 | AT36: =IF($AQ36<>"", AR36*AS36/365, "") -> 0.47260274 | AU36: =IF($AQ36<>"", SUMIFS($AL$3:$AL$1054, $A$3:$A$1054,$AQ36) + SUMIFS($M$3:$M$1054, $A$3:$A$1054,$AQ36)*IFERROR(AVERAGEIFS($L$3:$L$1054, $A$3:$A$1054,$AQ36, $M$3:$M$1054,">0"),0) - AT36, "") -> -0.47260274 | AV36: =IF(AQ36<>"", AU36*(1+$X$9/CompoundingRate)^-((AQ36-AQ$3)/(365/CompoundingRate)), "") -> -0.47260274
A37: 44424 | B37: NAB #2157 - Repayment | F37: 2232.44 | M37: =IF($A37<>"", IF(ISNUMBER(SEARCH("Debt Cost (est.)",B37)), SUMIFS(AT:AT, AQ:AQ, ">="&DATE("20"&RIGHT(LEFT(B37,4),2)-1,7,1), AQ:AQ, "<="&DATE("20"&RIGHT(LEFT(B37,4),2),6,30)), ""), "") | AA37: =IF($A37<>"", MIN(AB37,$P$3), "") -> 3450000 | AB37: =IF($A37<>"", AC37+AD37, "") -> 3450000 | AC37: =IF(A37<>"", AC36+D37+F37-G37, "") -> 527441.01 | AD37: =IF(A37<>"", AD36+C37-F37+G37, "") -> 2922559 | AE37: =IF(A38<>"", A38-A37, IF(A37<>"",IF(AC37<>0,TODAY()-A37,0), "")) -> 3 | AG37: =IF($A37<>"", I37+J37+E37-F37-H37, "") -> -2232.44 | AH37: =IF(A37<>"", A37-A$3, "") -> 73 | AI37: =IF(A37<>"", AG37*(1+$X$3)^-(AH37/365), "") -> -2232.44 | AL37: =IF($A37<>"", AG37-IF(ISNUMBER(K37),K37*L37,0), "") -> -2232.44 | AM37: =IF(A37<>"", AL37*(1+$X$6/CompoundingRate)^-(AH37/(365/CompoundingRate)), "") -> -2232.44 | AQ37: =IF(AQ36<$AP$3,AQ36+1,"") -> 44385 | AR37: =IF($AQ37<>"", INDEX($AC$3:$AC$1055, MATCH($AQ37,$A$3:$A$1055,1)), "") -> 172500 | AS37: =IF($AQ37<>"", INDEX(Inputs!$B$3:$B$101, MATCH($AQ37,Inputs!$A$3:$A$101,1)), "") -> 0.001 | AT37: =IF($AQ37<>"", AR37*AS37/365, "") -> 0.47260274 | AU37: =IF($AQ37<>"", SUMIFS($AL$3:$AL$1054, $A$3:$A$1054,$AQ37) + SUMIFS($M$3:$M$1054, $A$3:$A$1054,$AQ37)*IFERROR(AVERAGEIFS($L$3:$L$1054, $A$3:$A$1054,$AQ37, $M$3:$M$1054,">0"),0) - AT37, "") -> -0.47260274 | AV37: =IF(AQ37<>"", AU37*(1+$X$9/CompoundingRate)^-((AQ37-AQ$3)/(365/CompoundingRate)), "") -> -0.47260274
A38: 44427 | B38: Lawyer Fees Return | H38: -335.05 | M38: =IF($A38<>"", IF(ISNUMBER(SEARCH("Debt Cost (est.)",B38)), SUMIFS(AT:AT, AQ:AQ, ">="&DATE("20"&RIGHT(LEFT(B38,4),2)-1,7,1), AQ:AQ, "<="&DATE("20"&RIGHT(LEFT(B38,4),2),6,30)), ""), "") | AA38: =IF($A38<>"", MIN(AB38,$P$3), "") -> 3450000 | AB38: =IF($A38<>"", AC38+AD38, "") -> 3450000 | AC38: =IF(A38<>"", AC37+D38+F38-G38, "") -> 527441.01 | AD38: =IF(A38<>"", AD37+C38-F38+G38, "") -> 2922559 | AE38: =IF(A39<>"", A39-A38, IF(A38<>"",IF(AC38<>0,TODAY()-A38,0), "")) -> 1 | AG38: =IF($A38<>"", I38+J38+E38-F38-H38, "") -> 335.05 | AH38: =IF(A38<>"", A38-A$3, "") -> 76 | AI38: =IF(A38<>"", AG38*(1+$X$3)^-(AH38/365), "") -> 335.05 | AL38: =IF($A38<>"", AG38-IF(ISNUMBER(K38),K38*L38,0), "") -> 335.05 | AM38: =IF(A38<>"", AL38*(1+$X$6/CompoundingRate)^-(AH38/(365/CompoundingRate)), "") -> 335.05 | AQ38: =IF(AQ37<$AP$3,AQ37+1,"") -> 44386 | AR38: =IF($AQ38<>"", INDEX($AC$3:$AC$1055, MATCH($AQ38,$A$3:$A$1055,1)), "") -> 172500 | AS38: =IF($AQ38<>"", INDEX(Inputs!$B$3:$B$101, MATCH($AQ38,Inputs!$A$3:$A$101,1)), "") -> 0.001 | AT38: =IF($AQ38<>"", AR38*AS38/365, "") -> 0.47260274 | AU38: =IF($AQ38<>"", SUMIFS($AL$3:$AL$1054, $A$3:$A$1054,$AQ38) + SUMIFS($M$3:$M$1054, $A$3:$A$1054,$AQ38)*IFERROR(AVERAGEIFS($L$3:$L$1054, $A$3:$A$1054,$AQ38, $M$3:$M$1054,">0"),0) - AT38, "") -> -0.47260274 | AV38: =IF(AQ38<>"", AU38*(1+$X$9/CompoundingRate)^-((AQ38-AQ$3)/(365/CompoundingRate)), "") -> -0.47260274
A39: 44428 | B39: Rent - Andre | I39: 1900 | M39: =IF($A39<>"", IF(ISNUMBER(SEARCH("Debt Cost (est.)",B39)), SUMIFS(AT:AT, AQ:AQ, ">="&DATE("20"&RIGHT(LEFT(B39,4),2)-1,7,1), AQ:AQ, "<="&DATE("20"&RIGHT(LEFT(B39,4),2),6,30)), ""), "") | AA39: =IF($A39<>"", MIN(AB39,$P$3), "") -> 3450000 | AB39: =IF($A39<>"", AC39+AD39, "") -> 3450000 | AC39: =IF(A39<>"", AC38+D39+F39-G39, "") -> 527441.01 | AD39: =IF(A39<>"", AD38+C39-F39+G39, "") -> 2922559 | AE39: =IF(A40<>"", A40-A39, IF(A39<>"",IF(AC39<>0,TODAY()-A39,0), "")) -> 7 | AG39: =IF($A39<>"", I39+J39+E39-F39-H39, "") -> 1900 | AH39: =IF(A39<>"", A39-A$3, "") -> 77 | AI39: =IF(A39<>"", AG39*(1+$X$3)^-(AH39/365), "") -> 1900 | AL39: =IF($A39<>"", AG39-IF(ISNUMBER(K39),K39*L39,0), "") -> 1900 | AM39: =IF(A39<>"", AL39*(1+$X$6/CompoundingRate)^-(AH39/(365/CompoundingRate)), "") -> 1900 | AQ39: =IF(AQ38<$AP$3,AQ38+1,"") -> 44387 | AR39: =IF($AQ39<>"", INDEX($AC$3:$AC$1055, MATCH($AQ39,$A$3:$A$1055,1)), "") -> 172500 | AS39: =IF($AQ39<>"", INDEX(Inputs!$B$3:$B$101, MATCH($AQ39,Inputs!$A$3:$A$101,1)), "") -> 0.001 | AT39: =IF($AQ39<>"", AR39*AS39/365, "") -> 0.47260274 | AU39: =IF($AQ39<>"", SUMIFS($AL$3:$AL$1054, $A$3:$A$1054,$AQ39) + SUMIFS($M$3:$M$1054, $A$3:$A$1054,$AQ39)*IFERROR(AVERAGEIFS($L$3:$L$1054, $A$3:$A$1054,$AQ39, $M$3:$M$1054,">0"),0) - AT39, "") -> -0.47260274 | AV39: =IF(AQ39<>"", AU39*(1+$X$9/CompoundingRate)^-((AQ39-AQ$3)/(365/CompoundingRate)), "") -> -0.47260274
A40: 44435 | B40: Rent - Andre | I40: 1900 | M40: =IF($A40<>"", IF(ISNUMBER(SEARCH("Debt Cost (est.)",B40)), SUMIFS(AT:AT, AQ:AQ, ">="&DATE("20"&RIGHT(LEFT(B40,4),2)-1,7,1), AQ:AQ, "<="&DATE("20"&RIGHT(LEFT(B40,4),2),6,30)), ""), "") | AA40: =IF($A40<>"", MIN(AB40,$P$3), "") -> 3450000 | AB40: =IF($A40<>"", AC40+AD40, "") -> 3450000 | AC40: =IF(A40<>"", AC39+D40+F40-G40, "") -> 527441.01 | AD40: =IF(A40<>"", AD39+C40-F40+G40, "") -> 2922559 | AE40: =IF(A41<>"", A41-A40, IF(A40<>"",IF(AC40<>0,TODAY()-A40,0), "")) -> 4 | AG40: =IF($A40<>"", I40+J40+E40-F40-H40, "") -> 1900 | AH40: =IF(A40<>"", A40-A$3, "") -> 84 | AI40: =IF(A40<>"", AG40*(1+$X$3)^-(AH40/365), "") -> 1900 | AL40: =IF($A40<>"", AG40-IF(ISNUMBER(K40),K40*L40,0), "") -> 1900 | AM40: =IF(A40<>"", AL40*(1+$X$6/CompoundingRate)^-(AH40/(365/CompoundingRate)), "") -> 1900 | AQ40: =IF(AQ39<$AP$3,AQ39+1,"") -> 44388 | AR40: =IF($AQ40<>"", INDEX($AC$3:$AC$1055, MATCH($AQ40,$A$3:$A$1055,1)), "") -> 172500 | AS40: =IF($AQ40<>"", INDEX(Inputs!$B$3:$B$101, MATCH($AQ40,Inputs!$A$3:$A$101,1)), "") -> 0.001 | AT40: =IF($AQ40<>"", AR40*AS40/365, "") -> 0.47260274 | AU40: =IF($AQ40<>"", SUMIFS($AL$3:$AL$1054, $A$3:$A$1054,$AQ40) + SUMIFS($M$3:$M$1054, $A$3:$A$1054,$AQ40)*IFERROR(AVERAGEIFS($L$3:$L$1054, $A$3:$A$1054,$AQ40, $M$3:$M$1054,">0"),0) - AT40, "") -> -0.47260274 | AV40: =IF(AQ40<>"", AU40*(1+$X$9/CompoundingRate)^-((AQ40-AQ$3)/(365/CompoundingRate)), "") -> -0.47260274
A41: 44439 | B41: NAB #3063 - Interest | G41: 4430.96 | M41: =IF($A41<>"", IF(ISNUMBER(SEARCH("Debt Cost (est.)",B41)), SUMIFS(AT:AT, AQ:AQ, ">="&DATE("20"&RIGHT(LEFT(B41,4),2)-1,7,1), AQ:AQ, "<="&DATE("20"&RIGHT(LEFT(B41,4),2),6,30)), ""), "") | AA41: =IF($A41<>"", MIN(AB41,$P$3), "") -> 3450000 | AB41: =IF($A41<>"", AC41+AD41, "") -> 3450000 | AC41: =IF(A41<>"", AC40+D41+F41-G41, "") -> 523010.05 | AD41: =IF(A41<>"", AD40+C41-F41+G41, "") -> 2926990 | AE41: =IF(A42<>"", A42-A41, IF(A41<>"",IF(AC41<>0,TODAY()-A41,0), "")) -> 0 | AG41: =IF($A41<>"", I41+J41+E41-F41-H41, "") -> 0 | AH41: =IF(A41<>"", A41-A$3, "") -> 88 | AI41: =IF(A41<>"", AG41*(1+$X$3)^-(AH41/365), "") -> 0 | AL41: =IF($A41<>"", AG41-IF(ISNUMBER(K41),K41*L41,0), "") -> 0 | AM41: =IF(A41<>"", AL41*(1+$X$6/CompoundingRate)^-(AH41/(365/CompoundingRate)), "") -> 0 | AQ41: =IF(AQ40<$AP$3,AQ40+1,"") -> 44389 | AR41: =IF($AQ41<>"", INDEX($AC$3:$AC$1055, MATCH($AQ41,$A$3:$A$1055,1)), "") -> 172500 | AS41: =IF($AQ41<>"", INDEX(Inputs!$B$3:$B$101, MATCH($AQ41,Inputs!$A$3:$A$101,1)), "") -> 0.001 | AT41: =IF($AQ41<>"", AR41*AS41/365, "") -> 0.47260274 | AU41: =IF($AQ41<>"", SUMIFS($AL$3:$AL$1054, $A$3:$A$1054,$AQ41) + SUMIFS($M$3:$M$1054, $A$3:$A$1054,$AQ41)*IFERROR(AVERAGEIFS($L$3:$L$1054, $A$3:$A$1054,$AQ41, $M$3:$M$1054,">0"),0) - AT41, "") -> -0.47260274 | AV41: =IF(AQ41<>"", AU41*(1+$X$9/CompoundingRate)^-((AQ41-AQ$3)/(365/CompoundingRate)), "") -> -0.47260274
A42: 44439 | B42: NAB #2157 - Interest | G42: 331.9 | M42: =IF($A42<>"", IF(ISNUMBER(SEARCH("Debt Cost (est.)",B42)), SUMIFS(AT:AT, AQ:AQ, ">="&DATE("20"&RIGHT(LEFT(B42,4),2)-1,7,1), AQ:AQ, "<="&DATE("20"&RIGHT(LEFT(B42,4),2),6,30)), ""), "") | AA42: =IF($A42<>"", MIN(AB42,$P$3), "") -> 3450000 | AB42: =IF($A42<>"", AC42+AD42, "") -> 3450000 | AC42: =IF(A42<>"", AC41+D42+F42-G42, "") -> 522678.15 | AD42: =IF(A42<>"", AD41+C42-F42+G42, "") -> 2927321.9 | AE42: =IF(A43<>"", A43-A42, IF(A42<>"",IF(AC42<>0,TODAY()-A42,0), "")) -> 3 | AG42: =IF($A42<>"", I42+J42+E42-F42-H42, "") -> 0 | AH42: =IF(A42<>"", A42-A$3, "") -> 88 | AI42: =IF(A42<>"", AG42*(1+$X$3)^-(AH42/365), "") -> 0 | AL42: =IF($A42<>"", AG42-IF(ISNUMBER(K42),K42*L42,0), "") -> 0 | AM42: =IF(A42<>"", AL42*(1+$X$6/CompoundingRate)^-(AH42/(365/CompoundingRate)), "") -> 0 | AQ42: =IF(AQ41<$AP$3,AQ41+1,"") -> 44390 | AR42: =IF($AQ42<>"", INDEX($AC$3:$AC$1055, MATCH($AQ42,$A$3:$A$1055,1)), "") -> 172500 | AS42: =IF($AQ42<>"", INDEX(Inputs!$B$3:$B$101, MATCH($AQ42,Inputs!$A$3:$A$101,1)), "") -> 0.001 | AT42: =IF($AQ42<>"", AR42*AS42/365, "") -> 0.47260274 | AU42: =IF($AQ42<>"", SUMIFS($AL$3:$AL$1054, $A$3:$A$1054,$AQ42) + SUMIFS($M$3:$M$1054, $A$3:$A$1054,$AQ42)*IFERROR(AVERAGEIFS($L$3:$L$1054, $A$3:$A$1054,$AQ42, $M$3:$M$1054,">0"),0) - AT42, "") -> -0.47260274 | AV42: =IF(AQ42<>"", AU42*(1+$X$9/CompoundingRate)^-((AQ42-AQ$3)/(365/CompoundingRate)), "") -> -0.47260274
A43: 44442 | B43: Rent - Andre | I43: 1900 | M43: =IF($A43<>"", IF(ISNUMBER(SEARCH("Debt Cost (est.)",B43)), SUMIFS(AT:AT, AQ:AQ, ">="&DATE("20"&RIGHT(LEFT(B43,4),2)-1,7,1), AQ:AQ, "<="&DATE("20"&RIGHT(LEFT(B43,4),2),6,30)), ""), "") | AA43: =IF($A43<>"", MIN(AB43,$P$3), "") -> 3450000 | AB43: =IF($A43<>"", AC43+AD43, "") -> 3450000 | AC43: =IF(A43<>"", AC42+D43+F43-G43, "") -> 522678.15 | AD43: =IF(A43<>"", AD42+C43-F43+G43, "") -> 2927321.9 | AE43: =IF(A44<>"", A44-A43, IF(A43<>"",IF(AC43<>0,TODAY()-A43,0), "")) -> 7 | AG43: =IF($A43<>"", I43+J43+E43-F43-H43, "") -> 1900 | AH43: =IF(A43<>"", A43-A$3, "") -> 91 | AI43: =IF(A43<>"", AG43*(1+$X$3)^-(AH43/365), "") -> 1900 | AL43: =IF($A43<>"", AG43-IF(ISNUMBER(K43),K43*L43,0), "") -> 1900 | AM43: =IF(A43<>"", AL43*(1+$X$6/CompoundingRate)^-(AH43/(365/CompoundingRate)), "") -> 1900 | AQ43: =IF(AQ42<$AP$3,AQ42+1,"") -> 44391 | AR43: =IF($AQ43<>"", INDEX($AC$3:$AC$1055, MATCH($AQ43,$A$3:$A$1055,1)), "") -> 172500 | AS43: =IF($AQ43<>"", INDEX(Inputs!$B$3:$B$101, MATCH($AQ43,Inputs!$A$3:$A$101,1)), "") -> 0.001 | AT43: =IF($AQ43<>"", AR43*AS43/365, "") -> 0.47260274 | AU43: =IF($AQ43<>"", SUMIFS($AL$3:$AL$1054, $A$3:$A$1054,$AQ43) + SUMIFS($M$3:$M$1054, $A$3:$A$1054,$AQ43)*IFERROR(AVERAGEIFS($L$3:$L$1054, $A$3:$A$1054,$AQ43, $M$3:$M$1054,">0"),0) - AT43, "") -> -0.47260274 | AV43: =IF(AQ43<>"", AU43*(1+$X$9/CompoundingRate)^-((AQ43-AQ$3)/(365/CompoundingRate)), "") -> -0.47260274
A44: 44449 | B44: Rent - Andre | I44: 1900 | M44: =IF($A44<>"", IF(ISNUMBER(SEARCH("Debt Cost (est.)",B44)), SUMIFS(AT:AT, AQ:AQ, ">="&DATE("20"&RIGHT(LEFT(B44,4),2)-1,7,1), AQ:AQ, "<="&DATE("20"&RIGHT(LEFT(B44,4),2),6,30)), ""), "") | AA44: =IF($A44<>"", MIN(AB44,$P$3), "") -> 3450000 | AB44: =IF($A44<>"", AC44+AD44, "") -> 3450000 | AC44: =IF(A44<>"", AC43+D44+F44-G44, "") -> 522678.15 | AD44: =IF(A44<>"", AD43+C44-F44+G44, "") -> 2927321.9 | AE44: =IF(A45<>"", A45-A44, IF(A44<>"",IF(AC44<>0,TODAY()-A44,0), "")) -> 2 | AG44: =IF($A44<>"", I44+J44+E44-F44-H44, "") -> 1900 | AH44: =IF(A44<>"", A44-A$3, "") -> 98 | AI44: =IF(A44<>"", AG44*(1+$X$3)^-(AH44/365), "") -> 1900 | AL44: =IF($A44<>"", AG44-IF(ISNUMBER(K44),K44*L44,0), "") -> 1900 | AM44: =IF(A44<>"", AL44*(1+$X$6/CompoundingRate)^-(AH44/(365/CompoundingRate)), "") -> 1900 | AQ44: =IF(AQ43<$AP$3,AQ43+1,"") -> 44392 | AR44: =IF($AQ44<>"", INDEX($AC$3:$AC$1055, MATCH($AQ44,$A$3:$A$1055,1)), "") -> 517500 | AS44: =IF($AQ44<>"", INDEX(Inputs!$B$3:$B$101, MATCH($AQ44,Inputs!$A$3:$A$101,1)), "") -> 0.001 | AT44: =IF($AQ44<>"", AR44*AS44/365, "") -> 1.4178082 | AU44: =IF($AQ44<>"", SUMIFS($AL$3:$AL$1054, $A$3:$A$1054,$AQ44) + SUMIFS($M$3:$M$1054, $A$3:$A$1054,$AQ44)*IFERROR(AVERAGEIFS($L$3:$L$1054, $A$3:$A$1054,$AQ44, $M$3:$M$1054,">0"),0) - AT44, "") -> -536277.75 | AV44: =IF(AQ44<>"", AU44*(1+$X$9/CompoundingRate)^-((AQ44-AQ$3)/(365/CompoundingRate)), "") -> -536277.75
A45: 44451 | B45: Strata Levies | H45: 1896.96 | M45: =IF($A45<>"", IF(ISNUMBER(SEARCH("Debt Cost (est.)",B45)), SUMIFS(AT:AT, AQ:AQ, ">="&DATE("20"&RIGHT(LEFT(B45,4),2)-1,7,1), AQ:AQ, "<="&DATE("20"&RIGHT(LEFT(B45,4),2),6,30)), ""), "") | AA45: =IF($A45<>"", MIN(AB45,$P$3), "") -> 3450000 | AB45: =IF($A45<>"", AC45+AD45, "") -> 3450000 | AC45: =IF(A45<>"", AC44+D45+F45-G45, "") -> 522678.15 | AD45: =IF(A45<>"", AD44+C45-F45+G45, "") -> 2927321.9 | AE45: =IF(A46<>"", A46-A45, IF(A45<>"",IF(AC45<>0,TODAY()-A45,0), "")) -> 4 | AG45: =IF($A45<>"", I45+J45+E45-F45-H45, "") -> -1896.96 | AH45: =IF(A45<>"", A45-A$3, "") -> 100 | AI45: =IF(A45<>"", AG45*(1+$X$3)^-(AH45/365), "") -> -1896.96 | AL45: =IF($A45<>"", AG45-IF(ISNUMBER(K45),K45*L45,0), "") -> -1896.96 | AM45: =IF(A45<>"", AL45*(1+$X$6/CompoundingRate)^-(AH45/(365/CompoundingRate)), "") -> -1896.96 | AQ45: =IF(AQ44<$AP$3,AQ44+1,"") -> 44393 | AR45: =IF($AQ45<>"", INDEX($AC$3:$AC$1055, MATCH($AQ45,$A$3:$A$1055,1)), "") -> 517500 | AS45: =IF($AQ45<>"", INDEX(Inputs!$B$3:$B$101, MATCH($AQ45,Inputs!$A$3:$A$101,1)), "") -> 0.001 | AT45: =IF($AQ45<>"", AR45*AS45/365, "") -> 1.4178082 | AU45: =IF($AQ45<>"", SUMIFS($AL$3:$AL$1054, $A$3:$A$1054,$AQ45) + SUMIFS($M$3:$M$1054, $A$3:$A$1054,$AQ45)*IFERROR(AVERAGEIFS($L$3:$L$1054, $A$3:$A$1054,$AQ45, $M$3:$M$1054,">0"),0) - AT45, "") -> -12228.368 | AV45: =IF(AQ45<>"", AU45*(1+$X$9/CompoundingRate)^-((AQ45-AQ$3)/(365/CompoundingRate)), "") -> -12228.368
A46: 44455 | B46: NAB #3063 - Repayment | F46: 9818.51 | M46: =IF($A46<>"", IF(ISNUMBER(SEARCH("Debt Cost (est.)",B46)), SUMIFS(AT:AT, AQ:AQ, ">="&DATE("20"&RIGHT(LEFT(B46,4),2)-1,7,1), AQ:AQ, "<="&DATE("20"&RIGHT(LEFT(B46,4),2),6,30)), ""), "") | AA46: =IF($A46<>"", MIN(AB46,$P$3), "") -> 3450000 | AB46: =IF($A46<>"", AC46+AD46, "") -> 3450000 | AC46: =IF(A46<>"", AC45+D46+F46-G46, "") -> 532496.66 | AD46: =IF(A46<>"", AD45+C46-F46+G46, "") -> 2917503.3 | AE46: =IF(A47<>"", A47-A46, IF(A46<>"",IF(AC46<>0,TODAY()-A46,0), "")) -> 0 | AG46: =IF($A46<>"", I46+J46+E46-F46-H46, "") -> -9818.51 | AH46: =IF(A46<>"", A46-A$3, "") -> 104 | AI46: =IF(A46<>"", AG46*(1+$X$3)^-(AH46/365), "") -> -9818.51 | AL46: =IF($A46<>"", AG46-IF(ISNUMBER(K46),K46*L46,0), "") -> -9818.51 | AM46: =IF(A46<>"", AL46*(1+$X$6/CompoundingRate)^-(AH46/(365/CompoundingRate)), "") -> -9818.51 | AQ46: =IF(AQ45<$AP$3,AQ45+1,"") -> 44394 | AR46: =IF($AQ46<>"", INDEX($AC$3:$AC$1055, MATCH($AQ46,$A$3:$A$1055,1)), "") -> 517500 | AS46: =IF($AQ46<>"", INDEX(Inputs!$B$3:$B$101, MATCH($AQ46,Inputs!$A$3:$A$101,1)), "") -> 0.001 | AT46: =IF($AQ46<>"", AR46*AS46/365, "") -> 1.4178082 | AU46: =IF($AQ46<>"", SUMIFS($AL$3:$AL$1054, $A$3:$A$1054,$AQ46) + SUMIFS($M$3:$M$1054, $A$3:$A$1054,$AQ46)*IFERROR(AVERAGEIFS($L$3:$L$1054, $A$3:$A$1054,$AQ46, $M$3:$M$1054,">0"),0) - AT46, "") -> -1.4178082 | AV46: =IF(AQ46<>"", AU46*(1+$X$9/CompoundingRate)^-((AQ46-AQ$3)/(365/CompoundingRate)), "") -> -1.4178082
A47: 44455 | B47: NAB #2157 - Repayment | F47: 2232.44 | M47: =IF($A47<>"", IF(ISNUMBER(SEARCH("Debt Cost (est.)",B47)), SUMIFS(AT:AT, AQ:AQ, ">="&DATE("20"&RIGHT(LEFT(B47,4),2)-1,7,1), AQ:AQ, "<="&DATE("20"&RIGHT(LEFT(B47,4),2),6,30)), ""), "") | AA47: =IF($A47<>"", MIN(AB47,$P$3), "") -> 3450000 | AB47: =IF($A47<>"", AC47+AD47, "") -> 3450000 | AC47: =IF(A47<>"", AC46+D47+F47-G47, "") -> 534729.1 | AD47: =IF(A47<>"", AD46+C47-F47+G47, "") -> 2915270.9 | AE47: =IF(A48<>"", A48-A47, IF(A47<>"",IF(AC47<>0,TODAY()-A47,0), "")) -> 1 | AG47: =IF($A47<>"", I47+J47+E47-F47-H47, "") -> -2232.44 | AH47: =IF(A47<>"", A47-A$3, "") -> 104 | AI47: =IF(A47<>"", AG47*(1+$X$3)^-(AH47/365), "") -> -2232.44 | AL47: =IF($A47<>"", AG47-IF(ISNUMBER(K47),K47*L47,0), "") -> -2232.44 | AM47: =IF(A47<>"", AL47*(1+$X$6/CompoundingRate)^-(AH47/(365/CompoundingRate)), "") -> -2232.44 | AQ47: =IF(AQ46<$AP$3,AQ46+1,"") -> 44395 | AR47: =IF($AQ47<>"", INDEX($AC$3:$AC$1055, MATCH($AQ47,$A$3:$A$1055,1)), "") -> 517500 | AS47: =IF($AQ47<>"", INDEX(Inputs!$B$3:$B$101, MATCH($AQ47,Inputs!$A$3:$A$101,1)), "") -> 0.001 | AT47: =IF($AQ47<>"", AR47*AS47/365, "") -> 1.4178082 | AU47: =IF($AQ47<>"", SUMIFS($AL$3:$AL$1054, $A$3:$A$1054,$AQ47) + SUMIFS($M$3:$M$1054, $A$3:$A$1054,$AQ47)*IFERROR(AVERAGEIFS($L$3:$L$1054, $A$3:$A$1054,$AQ47, $M$3:$M$1054,">0"),0) - AT47, "") -> -1.4178082 | AV47: =IF(AQ47<>"", AU47*(1+$X$9/CompoundingRate)^-((AQ47-AQ$3)/(365/CompoundingRate)), "") -> -1.4178082
A48: 44456 | B48: Rent - Andre | I48: 1900 | M48: =IF($A48<>"", IF(ISNUMBER(SEARCH("Debt Cost (est.)",B48)), SUMIFS(AT:AT, AQ:AQ, ">="&DATE("20"&RIGHT(LEFT(B48,4),2)-1,7,1), AQ:AQ, "<="&DATE("20"&RIGHT(LEFT(B48,4),2),6,30)), ""), "") | AA48: =IF($A48<>"", MIN(AB48,$P$3), "") -> 3450000 | AB48: =IF($A48<>"", AC48+AD48, "") -> 3450000 | AC48: =IF(A48<>"", AC47+D48+F48-G48, "") -> 534729.1 | AD48: =IF(A48<>"", AD47+C48-F48+G48, "") -> 2915270.9 | AE48: =IF(A49<>"", A49-A48, IF(A48<>"",IF(AC48<>0,TODAY()-A48,0), "")) -> 7 | AG48: =IF($A48<>"", I48+J48+E48-F48-H48, "") -> 1900 | AH48: =IF(A48<>"", A48-A$3, "") -> 105 | AI48: =IF(A48<>"", AG48*(1+$X$3)^-(AH48/365), "") -> 1900 | AL48: =IF($A48<>"", AG48-IF(ISNUMBER(K48),K48*L48,0), "") -> 1900 | AM48: =IF(A48<>"", AL48*(1+$X$6/CompoundingRate)^-(AH48/(365/CompoundingRate)), "") -> 1900 | AQ48: =IF(AQ47<$AP$3,AQ47+1,"") -> 44396 | AR48: =IF($AQ48<>"", INDEX($AC$3:$AC$1055, MATCH($AQ48,$A$3:$A$1055,1)), "") -> 517500 | AS48: =IF($AQ48<>"", INDEX(Inputs!$B$3:$B$101, MATCH($AQ48,Inputs!$A$3:$A$101,1)), "") -> 0.001 | AT48: =IF($AQ48<>"", AR48*AS48/365, "") -> 1.4178082 | AU48: =IF($AQ48<>"", SUMIFS($AL$3:$AL$1054, $A$3:$A$1054,$AQ48) + SUMIFS($M$3:$M$1054, $A$3:$A$1054,$AQ48)*IFERROR(AVERAGEIFS($L$3:$L$1054, $A$3:$A$1054,$AQ48, $M$3:$M$1054,">0"),0) - AT48, "") -> -589.17781 | AV48: =IF(AQ48<>"", AU48*(1+$X$9/CompoundingRate)^-((AQ48-AQ$3)/(365/CompoundingRate)), "") -> -589.17781
A49: 44463 | B49: Rent - Andre | I49: 1900 | M49: =IF($A49<>"", IF(ISNUMBER(SEARCH("Debt Cost (est.)",B49)), SUMIFS(AT:AT, AQ:AQ, ">="&DATE("20"&RIGHT(LEFT(B49,4),2)-1,7,1), AQ:AQ, "<="&DATE("20"&RIGHT(LEFT(B49,4),2),6,30)), ""), "") | AA49: =IF($A49<>"", MIN(AB49,$P$3), "") -> 3450000 | AB49: =IF($A49<>"", AC49+AD49, "") -> 3450000 | AC49: =IF(A49<>"", AC48+D49+F49-G49, "") -> 534729.1 | AD49: =IF(A49<>"", AD48+C49-F49+G49, "") -> 2915270.9 | AE49: =IF(A50<>"", A50-A49, IF(A49<>"",IF(AC49<>0,TODAY()-A49,0), "")) -> 0 | AG49: =IF($A49<>"", I49+J49+E49-F49-H49, "") -> 1900 | AH49: =IF(A49<>"", A49-A$3, "") -> 112 | AI49: =IF(A49<>"", AG49*(1+$X$3)^-(AH49/365), "") -> 1900 | AL49: =IF($A49<>"", AG49-IF(ISNUMBER(K49),K49*L49,0), "") -> 1900 | AM49: =IF(A49<>"", AL49*(1+$X$6/CompoundingRate)^-(AH49/(365/CompoundingRate)), "") -> 1900 | AQ49: =IF(AQ48<$AP$3,AQ48+1,"") -> 44397 | AR49: =IF($AQ49<>"", INDEX($AC$3:$AC$1055, MATCH($AQ49,$A$3:$A$1055,1)), "") -> 517500 | AS49: =IF($AQ49<>"", INDEX(Inputs!$B$3:$B$101, MATCH($AQ49,Inputs!$A$3:$A$101,1)), "") -> 0.001 | AT49: =IF($AQ49<>"", AR49*AS49/365, "") -> 1.4178082 | AU49: =IF($AQ49<>"", SUMIFS($AL$3:$AL$1054, $A$3:$A$1054,$AQ49) + SUMIFS($M$3:$M$1054, $A$3:$A$1054,$AQ49)*IFERROR(AVERAGEIFS($L$3:$L$1054, $A$3:$A$1054,$AQ49, $M$3:$M$1054,">0"),0) - AT49, "") -> -1.4178082 | AV49: =IF(AQ49<>"", AU49*(1+$X$9/CompoundingRate)^-((AQ49-AQ$3)/(365/CompoundingRate)), "") -> -1.4178082
A50: 44463 | B50: Water Rates | H50: 61.67 | M50: =IF($A50<>"", IF(ISNUMBER(SEARCH("Debt Cost (est.)",B50)), SUMIFS(AT:AT, AQ:AQ, ">="&DATE("20"&RIGHT(LEFT(B50,4),2)-1,7,1), AQ:AQ, "<="&DATE("20"&RIGHT(LEFT(B50,4),2),6,30)), ""), "") | AA50: =IF($A50<>"", MIN(AB50,$P$3), "") -> 3450000 | AB50: =IF($A50<>"", AC50+AD50, "") -> 3450000 | AC50: =IF(A50<>"", AC49+D50+F50-G50, "") -> 534729.1 | AD50: =IF(A50<>"", AD49+C50-F50+G50, "") -> 2915270.9 | AE50: =IF(A51<>"", A51-A50, IF(A50<>"",IF(AC50<>0,TODAY()-A50,0), "")) -> 6 | AG50: =IF($A50<>"", I50+J50+E50-F50-H50, "") -> -61.67 | AH50: =IF(A50<>"", A50-A$3, "") -> 112 | AI50: =IF(A50<>"", AG50*(1+$X$3)^-(AH50/365), "") -> -61.67 | AL50: =IF($A50<>"", AG50-IF(ISNUMBER(K50),K50*L50,0), "") -> -61.67 | AM50: =IF(A50<>"", AL50*(1+$X$6/CompoundingRate)^-(AH50/(365/CompoundingRate)), "") -> -61.67 | AQ50: =IF(AQ49<$AP$3,AQ49+1,"") -> 44398 | AR50: =IF($AQ50<>"", INDEX($AC$3:$AC$1055, MATCH($AQ50,$A$3:$A$1055,1)), "") -> 517500 | AS50: =IF($AQ50<>"", INDEX(Inputs!$B$3:$B$101, MATCH($AQ50,Inputs!$A$3:$A$101,1)), "") -> 0.001 | AT50: =IF($AQ50<>"", AR50*AS50/365, "") -> 1.4178082 | AU50: =IF($AQ50<>"", SUMIFS($AL$3:$AL$1054, $A$3:$A$1054,$AQ50) + SUMIFS($M$3:$M$1054, $A$3:$A$1054,$AQ50)*IFERROR(AVERAGEIFS($L$3:$L$1054, $A$3:$A$1054,$AQ50, $M$3:$M$1054,">0"),0) - AT50, "") -> -1.4178082 | AV50: =IF(AQ50<>"", AU50*(1+$X$9/CompoundingRate)^-((AQ50-AQ$3)/(365/CompoundingRate)), "") -> -1.4178082
A51: 44469 | B51: NAB #3063 - Interest | G51: 4144.85 | M51: =IF($A51<>"", IF(ISNUMBER(SEARCH("Debt Cost (est.)",B51)), SUMIFS(AT:AT, AQ:AQ, ">="&DATE("20"&RIGHT(LEFT(B51,4),2)-1,7,1), AQ:AQ, "<="&DATE("20"&RIGHT(LEFT(B51,4),2),6,30)), ""), "") | AA51: =IF($A51<>"", MIN(AB51,$P$3), "") -> 3450000 | AB51: =IF($A51<>"", AC51+AD51, "") -> 3450000 | AC51: =IF(A51<>"", AC50+D51+F51-G51, "") -> 530584.25 | AD51: =IF(A51<>"", AD50+C51-F51+G51, "") -> 2919415.8 | AE51: =IF(A52<>"", A52-A51, IF(A51<>"",IF(AC51<>0,TODAY()-A51,0), "")) -> 0 | AG51: =IF($A51<>"", I51+J51+E51-F51-H51, "") -> 0 | AH51: =IF(A51<>"", A51-A$3, "") -> 118 | AI51: =IF(A51<>"", AG51*(1+$X$3)^-(AH51/365), "") -> 0 | AL51: =IF($A51<>"", AG51-IF(ISNUMBER(K51),K51*L51,0), "") -> 0 | AM51: =IF(A51<>"", AL51*(1+$X$6/CompoundingRate)^-(AH51/(365/CompoundingRate)), "") -> 0 | AQ51: =IF(AQ50<$AP$3,AQ50+1,"") -> 44399 | AR51: =IF($AQ51<>"", INDEX($AC$3:$AC$1055, MATCH($AQ51,$A$3:$A$1055,1)), "") -> 517500 | AS51: =IF($AQ51<>"", INDEX(Inputs!$B$3:$B$101, MATCH($AQ51,Inputs!$A$3:$A$101,1)), "") -> 0.001 | AT51: =IF($AQ51<>"", AR51*AS51/365, "") -> 1.4178082 | AU51: =IF($AQ51<>"", SUMIFS($AL$3:$AL$1054, $A$3:$A$1054,$AQ51) + SUMIFS($M$3:$M$1054, $A$3:$A$1054,$AQ51)*IFERROR(AVERAGEIFS($L$3:$L$1054, $A$3:$A$1054,$AQ51, $M$3:$M$1054,">0"),0) - AT51, "") -> -1.4178082 | AV51: =IF(AQ51<>"", AU51*(1+$X$9/CompoundingRate)^-((AQ51-AQ$3)/(365/CompoundingRate)), "") -> -1.4178082
A52: 44469 | B52: NAB #2157 - Interest | G52: 546.99 | M52: =IF($A52<>"", IF(ISNUMBER(SEARCH("Debt Cost (est.)",B52)), SUMIFS(AT:AT, AQ:AQ, ">="&DATE("20"&RIGHT(LEFT(B52,4),2)-1,7,1), AQ:AQ, "<="&DATE("20"&RIGHT(LEFT(B52,4),2),6,30)), ""), "") | AA52: =IF($A52<>"", MIN(AB52,$P$3), "") -> 3450000 | AB52: =IF($A52<>"", AC52+AD52, "") -> 3450000 | AC52: =IF(A52<>"", AC51+D52+F52-G52, "") -> 530037.26 | AD52: =IF(A52<>"", AD51+C52-F52+G52, "") -> 2919962.7 | AE52: =IF(A53<>"", A53-A52, IF(A52<>"",IF(AC52<>0,TODAY()-A52,0), "")) -> 1 | AG52: =IF($A52<>"", I52+J52+E52-F52-H52, "") -> 0 | AH52: =IF(A52<>"", A52-A$3, "") -> 118 | AI52: =IF(A52<>"", AG52*(1+$X$3)^-(AH52/365), "") -> 0 | AL52: =IF($A52<>"", AG52-IF(ISNUMBER(K52),K52*L52,0), "") -> 0 | AM52: =IF(A52<>"", AL52*(1+$X$6/CompoundingRate)^-(AH52/(365/CompoundingRate)), "") -> 0 | AQ52: =IF(AQ51<$AP$3,AQ51+1,"") -> 44400 | AR52: =IF($AQ52<>"", INDEX($AC$3:$AC$1055, MATCH($AQ52,$A$3:$A$1055,1)), "") -> 517500 | AS52: =IF($AQ52<>"", INDEX(Inputs!$B$3:$B$101, MATCH($AQ52,Inputs!$A$3:$A$101,1)), "") -> 0.001 | AT52: =IF($AQ52<>"", AR52*AS52/365, "") -> 1.4178082 | AU52: =IF($AQ52<>"", SUMIFS($AL$3:$AL$1054, $A$3:$A$1054,$AQ52) + SUMIFS($M$3:$M$1054, $A$3:$A$1054,$AQ52)*IFERROR(AVERAGEIFS($L$3:$L$1054, $A$3:$A$1054,$AQ52, $M$3:$M$1054,">0"),0) - AT52, "") -> 1898.5822 | AV52: =IF(AQ52<>"", AU52*(1+$X$9/CompoundingRate)^-((AQ52-AQ$3)/(365/CompoundingRate)), "") -> 1898.5822
A53: 44470 | B53: Rent - Andre | I53: 1900 | M53: =IF($A53<>"", IF(ISNUMBER(SEARCH("Debt Cost (est.)",B53)), SUMIFS(AT:AT, AQ:AQ, ">="&DATE("20"&RIGHT(LEFT(B53,4),2)-1,7,1), AQ:AQ, "<="&DATE("20"&RIGHT(LEFT(B53,4),2),6,30)), ""), "") | AA53: =IF($A53<>"", MIN(AB53,$P$3), "") -> 3450000 | AB53: =IF($A53<>"", AC53+AD53, "") -> 3450000 | AC53: =IF(A53<>"", AC52+D53+F53-G53, "") -> 530037.26 | AD53: =IF(A53<>"", AD52+C53-F53+G53, "") -> 2919962.7 | AE53: =IF(A54<>"", A54-A53, IF(A53<>"",IF(AC53<>0,TODAY()-A53,0), "")) -> 7 | AG53: =IF($A53<>"", I53+J53+E53-F53-H53, "") -> 1900 | AH53: =IF(A53<>"", A53-A$3, "") -> 119 | AI53: =IF(A53<>"", AG53*(1+$X$3)^-(AH53/365), "") -> 1900 | AL53: =IF($A53<>"", AG53-IF(ISNUMBER(K53),K53*L53,0), "") -> 1900 | AM53: =IF(A53<>"", AL53*(1+$X$6/CompoundingRate)^-(AH53/(365/CompoundingRate)), "") -> 1900 | AQ53: =IF(AQ52<$AP$3,AQ52+1,"") -> 44401 | AR53: =IF($AQ53<>"", INDEX($AC$3:$AC$1055, MATCH($AQ53,$A$3:$A$1055,1)), "") -> 517500 | AS53: =IF($AQ53<>"", INDEX(Inputs!$B$3:$B$101, MATCH($AQ53,Inputs!$A$3:$A$101,1)), "") -> 0.001 | AT53: =IF($AQ53<>"", AR53*AS53/365, "") -> 1.4178082 | AU53: =IF($AQ53<>"", SUMIFS($AL$3:$AL$1054, $A$3:$A$1054,$AQ53) + SUMIFS($M$3:$M$1054, $A$3:$A$1054,$AQ53)*IFERROR(AVERAGEIFS($L$3:$L$1054, $A$3:$A$1054,$AQ53, $M$3:$M$1054,">0"),0) - AT53, "") -> -1.4178082 | AV53: =IF(AQ53<>"", AU53*(1+$X$9/CompoundingRate)^-((AQ53-AQ$3)/(365/CompoundingRate)), "") -> -1.4178082
A54: 44477 | B54: Rent - Andre | I54: 1900 | M54: =IF($A54<>"", IF(ISNUMBER(SEARCH("Debt Cost (est.)",B54)), SUMIFS(AT:AT, AQ:AQ, ">="&DATE("20"&RIGHT(LEFT(B54,4),2)-1,7,1), AQ:AQ, "<="&DATE("20"&RIGHT(LEFT(B54,4),2),6,30)), ""), "") | AA54: =IF($A54<>"", MIN(AB54,$P$3), "") -> 3450000 | AB54: =IF($A54<>"", AC54+AD54, "") -> 3450000 | AC54: =IF(A54<>"", AC53+D54+F54-G54, "") -> 530037.26 | AD54: =IF(A54<>"", AD53+C54-F54+G54, "") -> 2919962.7 | AE54: =IF(A55<>"", A55-A54, IF(A54<>"",IF(AC54<>0,TODAY()-A54,0), "")) -> 7 | AG54: =IF($A54<>"", I54+J54+E54-F54-H54, "") -> 1900 | AH54: =IF(A54<>"", A54-A$3, "") -> 126 | AI54: =IF(A54<>"", AG54*(1+$X$3)^-(AH54/365), "") -> 1900 | AL54: =IF($A54<>"", AG54-IF(ISNUMBER(K54),K54*L54,0), "") -> 1900 | AM54: =IF(A54<>"", AL54*(1+$X$6/CompoundingRate)^-(AH54/(365/CompoundingRate)), "") -> 1900 | AQ54: =IF(AQ53<$AP$3,AQ53+1,"") -> 44402 | AR54: =IF($AQ54<>"", INDEX($AC$3:$AC$1055, MATCH($AQ54,$A$3:$A$1055,1)), "") -> 517500 | AS54: =IF($AQ54<>"", INDEX(Inputs!$B$3:$B$101, MATCH($AQ54,Inputs!$A$3:$A$101,1)), "") -> 0.001 | AT54: =IF($AQ54<>"", AR54*AS54/365, "") -> 1.4178082 | AU54: =IF($AQ54<>"", SUMIFS($AL$3:$AL$1054, $A$3:$A$1054,$AQ54) + SUMIFS($M$3:$M$1054, $A$3:$A$1054,$AQ54)*IFERROR(AVERAGEIFS($L$3:$L$1054, $A$3:$A$1054,$AQ54, $M$3:$M$1054,">0"),0) - AT54, "") -> -1.4178082 | AV54: =IF(AQ54<>"", AU54*(1+$X$9/CompoundingRate)^-((AQ54-AQ$3)/(365/CompoundingRate)), "") -> -1.4178082
A55: 44484 | B55: Rent - Andre | I55: 1900 | M55: =IF($A55<>"", IF(ISNUMBER(SEARCH("Debt Cost (est.)",B55)), SUMIFS(AT:AT, AQ:AQ, ">="&DATE("20"&RIGHT(LEFT(B55,4),2)-1,7,1), AQ:AQ, "<="&DATE("20"&RIGHT(LEFT(B55,4),2),6,30)), ""), "") | AA55: =IF($A55<>"", MIN(AB55,$P$3), "") -> 3450000 | AB55: =IF($A55<>"", AC55+AD55, "") -> 3450000 | AC55: =IF(A55<>"", AC54+D55+F55-G55, "") -> 530037.26 | AD55: =IF(A55<>"", AD54+C55-F55+G55, "") -> 2919962.7 | AE55: =IF(A56<>"", A56-A55, IF(A55<>"",IF(AC55<>0,TODAY()-A55,0), "")) -> 3 | AG55: =IF($A55<>"", I55+J55+E55-F55-H55, "") -> 1900 | AH55: =IF(A55<>"", A55-A$3, "") -> 133 | AI55: =IF(A55<>"", AG55*(1+$X$3)^-(AH55/365), "") -> 1900 | AL55: =IF($A55<>"", AG55-IF(ISNUMBER(K55),K55*L55,0), "") -> 1900 | AM55: =IF(A55<>"", AL55*(1+$X$6/CompoundingRate)^-(AH55/(365/CompoundingRate)), "") -> 1900 | AQ55: =IF(AQ54<$AP$3,AQ54+1,"") -> 44403 | AR55: =IF($AQ55<>"", INDEX($AC$3:$AC$1055, MATCH($AQ55,$A$3:$A$1055,1)), "") -> 517500 | AS55: =IF($AQ55<>"", INDEX(Inputs!$B$3:$B$101, MATCH($AQ55,Inputs!$A$3:$A$101,1)), "") -> 0.001 | AT55: =IF($AQ55<>"", AR55*AS55/365, "") -> 1.4178082 | AU55: =IF($AQ55<>"", SUMIFS($AL$3:$AL$1054, $A$3:$A$1054,$AQ55) + SUMIFS($M$3:$M$1054, $A$3:$A$1054,$AQ55)*IFERROR(AVERAGEIFS($L$3:$L$1054, $A$3:$A$1054,$AQ55, $M$3:$M$1054,">0"),0) - AT55, "") -> -1.4178082 | AV55: =IF(AQ55<>"", AU55*(1+$X$9/CompoundingRate)^-((AQ55-AQ$3)/(365/CompoundingRate)), "") -> -1.4178082
A56: 44487 | B56: NAB #3063 - Repayment | F56: 9818.51 | M56: =IF($A56<>"", IF(ISNUMBER(SEARCH("Debt Cost (est.)",B56)), SUMIFS(AT:AT, AQ:AQ, ">="&DATE("20"&RIGHT(LEFT(B56,4),2)-1,7,1), AQ:AQ, "<="&DATE("20"&RIGHT(LEFT(B56,4),2),6,30)), ""), "") | AA56: =IF($A56<>"", MIN(AB56,$P$3), "") -> 3450000 | AB56: =IF($A56<>"", AC56+AD56, "") -> 3450000 | AC56: =IF(A56<>"", AC55+D56+F56-G56, "") -> 539855.77 | AD56: =IF(A56<>"", AD55+C56-F56+G56, "") -> 2910144.2 | AE56: =IF(A57<>"", A57-A56, IF(A56<>"",IF(AC56<>0,TODAY()-A56,0), "")) -> 0 | AG56: =IF($A56<>"", I56+J56+E56-F56-H56, "") -> -9818.51 | AH56: =IF(A56<>"", A56-A$3, "") -> 136 | AI56: =IF(A56<>"", AG56*(1+$X$3)^-(AH56/365), "") -> -9818.51 | AL56: =IF($A56<>"", AG56-IF(ISNUMBER(K56),K56*L56,0), "") -> -9818.51 | AM56: =IF(A56<>"", AL56*(1+$X$6/CompoundingRate)^-(AH56/(365/CompoundingRate)), "") -> -9818.51 | AQ56: =IF(AQ55<$AP$3,AQ55+1,"") -> 44404 | AR56: =IF($AQ56<>"", INDEX($AC$3:$AC$1055, MATCH($AQ56,$A$3:$A$1055,1)), "") -> 517500 | AS56: =IF($AQ56<>"", INDEX(Inputs!$B$3:$B$101, MATCH($AQ56,Inputs!$A$3:$A$101,1)), "") -> 0.001 | AT56: =IF($AQ56<>"", AR56*AS56/365, "") -> 1.4178082 | AU56: =IF($AQ56<>"", SUMIFS($AL$3:$AL$1054, $A$3:$A$1054,$AQ56) + SUMIFS($M$3:$M$1054, $A$3:$A$1054,$AQ56)*IFERROR(AVERAGEIFS($L$3:$L$1054, $A$3:$A$1054,$AQ56, $M$3:$M$1054,">0"),0) - AT56, "") -> -1.4178082 | AV56: =IF(AQ56<>"", AU56*(1+$X$9/CompoundingRate)^-((AQ56-AQ$3)/(365/CompoundingRate)), "") -> -1.4178082
A57: 44487 | B57: NAB #2157 - Repayment | F57: 2232.44 | M57: =IF($A57<>"", IF(ISNUMBER(SEARCH("Debt Cost (est.)",B57)), SUMIFS(AT:AT, AQ:AQ, ">="&DATE("20"&RIGHT(LEFT(B57,4),2)-1,7,1), AQ:AQ, "<="&DATE("20"&RIGHT(LEFT(B57,4),2),6,30)), ""), "") | AA57: =IF($A57<>"", MIN(AB57,$P$3), "") -> 3450000 | AB57: =IF($A57<>"", AC57+AD57, "") -> 3450000 | AC57: =IF(A57<>"", AC56+D57+F57-G57, "") -> 542088.21 | AD57: =IF(A57<>"", AD56+C57-F57+G57, "") -> 2907911.8 | AE57: =IF(A58<>"", A58-A57, IF(A57<>"",IF(AC57<>0,TODAY()-A57,0), "")) -> 4 | AG57: =IF($A57<>"", I57+J57+E57-F57-H57, "") -> -2232.44 | AH57: =IF(A57<>"", A57-A$3, "") -> 136 | AI57: =IF(A57<>"", AG57*(1+$X$3)^-(AH57/365), "") -> -2232.44 | AL57: =IF($A57<>"", AG57-IF(ISNUMBER(K57),K57*L57,0), "") -> -2232.44 | AM57: =IF(A57<>"", AL57*(1+$X$6/CompoundingRate)^-(AH57/(365/CompoundingRate)), "") -> -2232.44 | AQ57: =IF(AQ56<$AP$3,AQ56+1,"") -> 44405 | AR57: =IF($AQ57<>"", INDEX($AC$3:$AC$1055, MATCH($AQ57,$A$3:$A$1055,1)), "") -> 517500 | AS57: =IF($AQ57<>"", INDEX(Inputs!$B$3:$B$101, MATCH($AQ57,Inputs!$A$3:$A$101,1)), "") -> 0.001 | AT57: =IF($AQ57<>"", AR57*AS57/365, "") -> 1.4178082 | AU57: =IF($AQ57<>"", SUMIFS($AL$3:$AL$1054, $A$3:$A$1054,$AQ57) + SUMIFS($M$3:$M$1054, $A$3:$A$1054,$AQ57)*IFERROR(AVERAGEIFS($L$3:$L$1054, $A$3:$A$1054,$AQ57, $M$3:$M$1054,">0"),0) - AT57, "") -> -1.4178082 | AV57: =IF(AQ57<>"", AU57*(1+$X$9/CompoundingRate)^-((AQ57-AQ$3)/(365/CompoundingRate)), "") -> -1.4178082
A58: 44491 | B58: Rent - Andre | I58: 1900 | M58: =IF($A58<>"", IF(ISNUMBER(SEARCH("Debt Cost (est.)",B58)), SUMIFS(AT:AT, AQ:AQ, ">="&DATE("20"&RIGHT(LEFT(B58,4),2)-1,7,1), AQ:AQ, "<="&DATE("20"&RIGHT(LEFT(B58,4),2),6,30)), ""), "") | AA58: =IF($A58<>"", MIN(AB58,$P$3), "") -> 3450000 | AB58: =IF($A58<>"", AC58+AD58, "") -> 3450000 | AC58: =IF(A58<>"", AC57+D58+F58-G58, "") -> 542088.21 | AD58: =IF(A58<>"", AD57+C58-F58+G58, "") -> 2907911.8 | AE58: =IF(A59<>"", A59-A58, IF(A58<>"",IF(AC58<>0,TODAY()-A58,0), "")) -> 7 | AG58: =IF($A58<>"", I58+J58+E58-F58-H58, "") -> 1900 | AH58: =IF(A58<>"", A58-A$3, "") -> 140 | AI58: =IF(A58<>"", AG58*(1+$X$3)^-(AH58/365), "") -> 1900 | AL58: =IF($A58<>"", AG58-IF(ISNUMBER(K58),K58*L58,0), "") -> 1900 | AM58: =IF(A58<>"", AL58*(1+$X$6/CompoundingRate)^-(AH58/(365/CompoundingRate)), "") -> 1900 | AQ58: =IF(AQ57<$AP$3,AQ57+1,"") -> 44406 | AR58: =IF($AQ58<>"", INDEX($AC$3:$AC$1055, MATCH($AQ58,$A$3:$A$1055,1)), "") -> 517500 | AS58: =IF($AQ58<>"", INDEX(Inputs!$B$3:$B$101, MATCH($AQ58,Inputs!$A$3:$A$101,1)), "") -> 0.001 | AT58: =IF($AQ58<>"", AR58*AS58/365, "") -> 1.4178082 | AU58: =IF($AQ58<>"", SUMIFS($AL$3:$AL$1054, $A$3:$A$1054,$AQ58) + SUMIFS($M$3:$M$1054, $A$3:$A$1054,$AQ58)*IFERROR(AVERAGEIFS($L$3:$L$1054, $A$3:$A$1054,$AQ58, $M$3:$M$1054,">0"),0) - AT58, "") -> -1.4178082 | AV58: =IF(AQ58<>"", AU58*(1+$X$9/CompoundingRate)^-((AQ58-AQ$3)/(365/CompoundingRate)), "") -> -1.4178082
A59: 44498 | B59: Rent - Andre | I59: 1900 | M59: =IF($A59<>"", IF(ISNUMBER(SEARCH("Debt Cost (est.)",B59)), SUMIFS(AT:AT, AQ:AQ, ">="&DATE("20"&RIGHT(LEFT(B59,4),2)-1,7,1), AQ:AQ, "<="&DATE("20"&RIGHT(LEFT(B59,4),2),6,30)), ""), "") | AA59: =IF($A59<>"", MIN(AB59,$P$3), "") -> 3450000 | AB59: =IF($A59<>"", AC59+AD59, "") -> 3450000 | AC59: =IF(A59<>"", AC58+D59+F59-G59, "") -> 542088.21 | AD59: =IF(A59<>"", AD58+C59-F59+G59, "") -> 2907911.8 | AE59: =IF(A60<>"", A60-A59, IF(A59<>"",IF(AC59<>0,TODAY()-A59,0), "")) -> 0 | AG59: =IF($A59<>"", I59+J59+E59-F59-H59, "") -> 1900 | AH59: =IF(A59<>"", A59-A$3, "") -> 147 | AI59: =IF(A59<>"", AG59*(1+$X$3)^-(AH59/365), "") -> 1900 | AL59: =IF($A59<>"", AG59-IF(ISNUMBER(K59),K59*L59,0), "") -> 1900 | AM59: =IF(A59<>"", AL59*(1+$X$6/CompoundingRate)^-(AH59/(365/CompoundingRate)), "") -> 1900 | AQ59: =IF(AQ58<$AP$3,AQ58+1,"") -> 44407 | AR59: =IF($AQ59<>"", INDEX($AC$3:$AC$1055, MATCH($AQ59,$A$3:$A$1055,1)), "") -> 515390.06 | AS59: =IF($AQ59<>"", INDEX(Inputs!$B$3:$B$101, MATCH($AQ59,Inputs!$A$3:$A$101,1)), "") -> 0.001 | AT59: =IF($AQ59<>"", AR59*AS59/365, "") -> 1.4120276 | AU59: =IF($AQ59<>"", SUMIFS($AL$3:$AL$1054, $A$3:$A$1054,$AQ59) + SUMIFS($M$3:$M$1054, $A$3:$A$1054,$AQ59)*IFERROR(AVERAGEIFS($L$3:$L$1054, $A$3:$A$1054,$AQ59, $M$3:$M$1054,">0"),0) - AT59, "") -> 1898.588 | AV59: =IF(AQ59<>"", AU59*(1+$X$9/CompoundingRate)^-((AQ59-AQ$3)/(365/CompoundingRate)), "") -> 1898.588
A60: 44498 | B60: NAB #3063 - Interest | G60: 3998.73 | M60: =IF($A60<>"", IF(ISNUMBER(SEARCH("Debt Cost (est.)",B60)), SUMIFS(AT:AT, AQ:AQ, ">="&DATE("20"&RIGHT(LEFT(B60,4),2)-1,7,1), AQ:AQ, "<="&DATE("20"&RIGHT(LEFT(B60,4),2),6,30)), ""), "") | AA60: =IF($A60<>"", MIN(AB60,$P$3), "") -> 3450000 | AB60: =IF($A60<>"", AC60+AD60, "") -> 3450000 | AC60: =IF(A60<>"", AC59+D60+F60-G60, "") -> 538089.48 | AD60: =IF(A60<>"", AD59+C60-F60+G60, "") -> 2911910.5 | AE60: =IF(A61<>"", A61-A60, IF(A60<>"",IF(AC60<>0,TODAY()-A60,0), "")) -> 0 | AG60: =IF($A60<>"", I60+J60+E60-F60-H60, "") -> 0 | AH60: =IF(A60<>"", A60-A$3, "") -> 147 | AI60: =IF(A60<>"", AG60*(1+$X$3)^-(AH60/365), "") -> 0 | AL60: =IF($A60<>"", AG60-IF(ISNUMBER(K60),K60*L60,0), "") -> 0 | AM60: =IF(A60<>"", AL60*(1+$X$6/CompoundingRate)^-(AH60/(365/CompoundingRate)), "") -> 0 | AQ60: =IF(AQ59<$AP$3,AQ59+1,"") -> 44408 | AR60: =IF($AQ60<>"", INDEX($AC$3:$AC$1055, MATCH($AQ60,$A$3:$A$1055,1)), "") -> 515390.06 | AS60: =IF($AQ60<>"", INDEX(Inputs!$B$3:$B$101, MATCH($AQ60,Inputs!$A$3:$A$101,1)), "") -> 0.001 | AT60: =IF($AQ60<>"", AR60*AS60/365, "") -> 1.4120276 | AU60: =IF($AQ60<>"", SUMIFS($AL$3:$AL$1054, $A$3:$A$1054,$AQ60) + SUMIFS($M$3:$M$1054, $A$3:$A$1054,$AQ60)*IFERROR(AVERAGEIFS($L$3:$L$1054, $A$3:$A$1054,$AQ60, $M$3:$M$1054,">0"),0) - AT60, "") -> -1.4120276 | AV60: =IF(AQ60<>"", AU60*(1+$X$9/CompoundingRate)^-((AQ60-AQ$3)/(365/CompoundingRate)), "") -> -1.4120276
A61: 44498 | B61: NAB #2157 - Interest | G61: 627.85 | M61: =IF($A61<>"", IF(ISNUMBER(SEARCH("Debt Cost (est.)",B61)), SUMIFS(AT:AT, AQ:AQ, ">="&DATE("20"&RIGHT(LEFT(B61,4),2)-1,7,1), AQ:AQ, "<="&DATE("20"&RIGHT(LEFT(B61,4),2),6,30)), ""), "") | AA61: =IF($A61<>"", MIN(AB61,$P$3), "") -> 3450000 | AB61: =IF($A61<>"", AC61+AD61, "") -> 3450000 | AC61: =IF(A61<>"", AC60+D61+F61-G61, "") -> 537461.63 | AD61: =IF(A61<>"", AD60+C61-F61+G61, "") -> 2912538.4 | AE61: =IF(A62<>"", A62-A61, IF(A61<>"",IF(AC61<>0,TODAY()-A61,0), "")) -> 7 | AG61: =IF($A61<>"", I61+J61+E61-F61-H61, "") -> 0 | AH61: =IF(A61<>"", A61-A$3, "") -> 147 | AI61: =IF(A61<>"", AG61*(1+$X$3)^-(AH61/365), "") -> 0 | AL61: =IF($A61<>"", AG61-IF(ISNUMBER(K61),K61*L61,0), "") -> 0 | AM61: =IF(A61<>"", AL61*(1+$X$6/CompoundingRate)^-(AH61/(365/CompoundingRate)), "") -> 0 | AQ61: =IF(AQ60<$AP$3,AQ60+1,"") -> 44409 | AR61: =IF($AQ61<>"", INDEX($AC$3:$AC$1055, MATCH($AQ61,$A$3:$A$1055,1)), "") -> 515390.06 | AS61: =IF($AQ61<>"", INDEX(Inputs!$B$3:$B$101, MATCH($AQ61,Inputs!$A$3:$A$101,1)), "") -> 0.001 | AT61: =IF($AQ61<>"", AR61*AS61/365, "") -> 1.4120276 | AU61: =IF($AQ61<>"", SUMIFS($AL$3:$AL$1054, $A$3:$A$1054,$AQ61) + SUMIFS($M$3:$M$1054, $A$3:$A$1054,$AQ61)*IFERROR(AVERAGEIFS($L$3:$L$1054, $A$3:$A$1054,$AQ61, $M$3:$M$1054,">0"),0) - AT61, "") -> -1.4120276 | AV61: =IF(AQ61<>"", AU61*(1+$X$9/CompoundingRate)^-((AQ61-AQ$3)/(365/CompoundingRate)), "") -> -1.4120276
A62: 44505 | B62: Rent - Andre | I62: 1900 | M62: =IF($A62<>"", IF(ISNUMBER(SEARCH("Debt Cost (est.)",B62)), SUMIFS(AT:AT, AQ:AQ, ">="&DATE("20"&RIGHT(LEFT(B62,4),2)-1,7,1), AQ:AQ, "<="&DATE("20"&RIGHT(LEFT(B62,4),2),6,30)), ""), "") | AA62: =IF($A62<>"", MIN(AB62,$P$3), "") -> 3450000 | AB62: =IF($A62<>"", AC62+AD62, "") -> 3450000 | AC62: =IF(A62<>"", AC61+D62+F62-G62, "") -> 537461.63 | AD62: =IF(A62<>"", AD61+C62-F62+G62, "") -> 2912538.4 | AE62: =IF(A63<>"", A63-A62, IF(A62<>"",IF(AC62<>0,TODAY()-A62,0), "")) -> 7 | AG62: =IF($A62<>"", I62+J62+E62-F62-H62, "") -> 1900 | AH62: =IF(A62<>"", A62-A$3, "") -> 154 | AI62: =IF(A62<>"", AG62*(1+$X$3)^-(AH62/365), "") -> 1900 | AL62: =IF($A62<>"", AG62-IF(ISNUMBER(K62),K62*L62,0), "") -> 1900 | AM62: =IF(A62<>"", AL62*(1+$X$6/CompoundingRate)^-(AH62/(365/CompoundingRate)), "") -> 1900 | AQ62: =IF(AQ61<$AP$3,AQ61+1,"") -> 44410 | AR62: =IF($AQ62<>"", INDEX($AC$3:$AC$1055, MATCH($AQ62,$A$3:$A$1055,1)), "") -> 515390.06 | AS62: =IF($AQ62<>"", INDEX(Inputs!$B$3:$B$101, MATCH($AQ62,Inputs!$A$3:$A$101,1)), "") -> 0.001 | AT62: =IF($AQ62<>"", AR62*AS62/365, "") -> 1.4120276 | AU62: =IF($AQ62<>"", SUMIFS($AL$3:$AL$1054, $A$3:$A$1054,$AQ62) + SUMIFS($M$3:$M$1054, $A$3:$A$1054,$AQ62)*IFERROR(AVERAGEIFS($L$3:$L$1054, $A$3:$A$1054,$AQ62, $M$3:$M$1054,">0"),0) - AT62, "") -> -1.4120276 | AV62: =IF(AQ62<>"", AU62*(1+$X$9/CompoundingRate)^-((AQ62-AQ$3)/(365/CompoundingRate)), "") -> -1.4120276
A63: 44512 | B63: Rent - Andre | I63: 1900 | M63: =IF($A63<>"", IF(ISNUMBER(SEARCH("Debt Cost (est.)",B63)), SUMIFS(AT:AT, AQ:AQ, ">="&DATE("20"&RIGHT(LEFT(B63,4),2)-1,7,1), AQ:AQ, "<="&DATE("20"&RIGHT(LEFT(B63,4),2),6,30)), ""), "") | AA63: =IF($A63<>"", MIN(AB63,$P$3), "") -> 3450000 | AB63: =IF($A63<>"", AC63+AD63, "") -> 3450000 | AC63: =IF(A63<>"", AC62+D63+F63-G63, "") -> 537461.63 | AD63: =IF(A63<>"", AD62+C63-F63+G63, "") -> 2912538.4 | AE63: =IF(A64<>"", A64-A63, IF(A63<>"",IF(AC63<>0,TODAY()-A63,0), "")) -> 4 | AG63: =IF($A63<>"", I63+J63+E63-F63-H63, "") -> 1900 | AH63: =IF(A63<>"", A63-A$3, "") -> 161 | AI63: =IF(A63<>"", AG63*(1+$X$3)^-(AH63/365), "") -> 1900 | AL63: =IF($A63<>"", AG63-IF(ISNUMBER(K63),K63*L63,0), "") -> 1900 | AM63: =IF(A63<>"", AL63*(1+$X$6/CompoundingRate)^-(AH63/(365/CompoundingRate)), "") -> 1900 | AQ63: =IF(AQ62<$AP$3,AQ62+1,"") -> 44411 | AR63: =IF($AQ63<>"", INDEX($AC$3:$AC$1055, MATCH($AQ63,$A$3:$A$1055,1)), "") -> 515390.06 | AS63: =IF($AQ63<>"", INDEX(Inputs!$B$3:$B$101, MATCH($AQ63,Inputs!$A$3:$A$101,1)), "") -> 0.001 | AT63: =IF($AQ63<>"", AR63*AS63/365, "") -> 1.4120276 | AU63: =IF($AQ63<>"", SUMIFS($AL$3:$AL$1054, $A$3:$A$1054,$AQ63) + SUMIFS($M$3:$M$1054, $A$3:$A$1054,$AQ63)*IFERROR(AVERAGEIFS($L$3:$L$1054, $A$3:$A$1054,$AQ63, $M$3:$M$1054,">0"),0) - AT63, "") -> -1.4120276 | AV63: =IF(AQ63<>"", AU63*(1+$X$9/CompoundingRate)^-((AQ63-AQ$3)/(365/CompoundingRate)), "") -> -1.4120276
A64: 44516 | B64: NAB #3063 - Repayment | F64: 9818.51 | M64: =IF($A64<>"", IF(ISNUMBER(SEARCH("Debt Cost (est.)",B64)), SUMIFS(AT:AT, AQ:AQ, ">="&DATE("20"&RIGHT(LEFT(B64,4),2)-1,7,1), AQ:AQ, "<="&DATE("20"&RIGHT(LEFT(B64,4),2),6,30)), ""), "") | AA64: =IF($A64<>"", MIN(AB64,$P$3), "") -> 3450000 | AB64: =IF($A64<>"", AC64+AD64, "") -> 3450000 | AC64: =IF(A64<>"", AC63+D64+F64-G64, "") -> 547280.14 | AD64: =IF(A64<>"", AD63+C64-F64+G64, "") -> 2902719.9 | AE64: =IF(A65<>"", A65-A64, IF(A64<>"",IF(AC64<>0,TODAY()-A64,0), "")) -> 0 | AG64: =IF($A64<>"", I64+J64+E64-F64-H64, "") -> -9818.51 | AH64: =IF(A64<>"", A64-A$3, "") -> 165 | AI64: =IF(A64<>"", AG64*(1+$X$3)^-(AH64/365), "") -> -9818.51 | AL64: =IF($A64<>"", AG64-IF(ISNUMBER(K64),K64*L64,0), "") -> -9818.51 | AM64: =IF(A64<>"", AL64*(1+$X$6/CompoundingRate)^-(AH64/(365/CompoundingRate)), "") -> -9818.51 | AQ64: =IF(AQ63<$AP$3,AQ63+1,"") -> 44412 | AR64: =IF($AQ64<>"", INDEX($AC$3:$AC$1055, MATCH($AQ64,$A$3:$A$1055,1)), "") -> 515390.06 | AS64: =IF($AQ64<>"", INDEX(Inputs!$B$3:$B$101, MATCH($AQ64,Inputs!$A$3:$A$101,1)), "") -> 0.001 | AT64: =IF($AQ64<>"", AR64*AS64/365, "") -> 1.4120276 | AU64: =IF($AQ64<>"", SUMIFS($AL$3:$AL$1054, $A$3:$A$1054,$AQ64) + SUMIFS($M$3:$M$1054, $A$3:$A$1054,$AQ64)*IFERROR(AVERAGEIFS($L$3:$L$1054, $A$3:$A$1054,$AQ64, $M$3:$M$1054,">0"),0) - AT64, "") -> -1.4120276 | AV64: =IF(AQ64<>"", AU64*(1+$X$9/CompoundingRate)^-((AQ64-AQ$3)/(365/CompoundingRate)), "") -> -1.4120276
A65: 44516 | B65: NAB #2157 - Repayment | F65: 2232.44 | M65: =IF($A65<>"", IF(ISNUMBER(SEARCH("Debt Cost (est.)",B65)), SUMIFS(AT:AT, AQ:AQ, ">="&DATE("20"&RIGHT(LEFT(B65,4),2)-1,7,1), AQ:AQ, "<="&DATE("20"&RIGHT(LEFT(B65,4),2),6,30)), ""), "") | AA65: =IF($A65<>"", MIN(AB65,$P$3), "") -> 3450000 | AB65: =IF($A65<>"", AC65+AD65, "") -> 3450000 | AC65: =IF(A65<>"", AC64+D65+F65-G65, "") -> 549512.58 | AD65: =IF(A65<>"", AD64+C65-F65+G65, "") -> 2900487.4 | AE65: =IF(A66<>"", A66-A65, IF(A65<>"",IF(AC65<>0,TODAY()-A65,0), "")) -> 3 | AG65: =IF($A65<>"", I65+J65+E65-F65-H65, "") -> -2232.44 | AH65: =IF(A65<>"", A65-A$3, "") -> 165 | AI65: =IF(A65<>"", AG65*(1+$X$3)^-(AH65/365), "") -> -2232.44 | AL65: =IF($A65<>"", AG65-IF(ISNUMBER(K65),K65*L65,0), "") -> -2232.44 | AM65: =IF(A65<>"", AL65*(1+$X$6/CompoundingRate)^-(AH65/(365/CompoundingRate)), "") -> -2232.44 | AQ65: =IF(AQ64<$AP$3,AQ64+1,"") -> 44413 | AR65: =IF($AQ65<>"", INDEX($AC$3:$AC$1055, MATCH($AQ65,$A$3:$A$1055,1)), "") -> 515390.06 | AS65: =IF($AQ65<>"", INDEX(Inputs!$B$3:$B$101, MATCH($AQ65,Inputs!$A$3:$A$101,1)), "") -> 0.001 | AT65: =IF($AQ65<>"", AR65*AS65/365, "") -> 1.4120276 | AU65: =IF($AQ65<>"", SUMIFS($AL$3:$AL$1054, $A$3:$A$1054,$AQ65) + SUMIFS($M$3:$M$1054, $A$3:$A$1054,$AQ65)*IFERROR(AVERAGEIFS($L$3:$L$1054, $A$3:$A$1054,$AQ65, $M$3:$M$1054,">0"),0) - AT65, "") -> -1.4120276 | AV65: =IF(AQ65<>"", AU65*(1+$X$9/CompoundingRate)^-((AQ65-AQ$3)/(365/CompoundingRate)), "") -> -1.4120276
A66: 44519 | B66: Rent - Andre | I66: 1900 | M66: =IF($A66<>"", IF(ISNUMBER(SEARCH("Debt Cost (est.)",B66)), SUMIFS(AT:AT, AQ:AQ, ">="&DATE("20"&RIGHT(LEFT(B66,4),2)-1,7,1), AQ:AQ, "<="&DATE("20"&RIGHT(LEFT(B66,4),2),6,30)), ""), "") | AA66: =IF($A66<>"", MIN(AB66,$P$3), "") -> 3450000 | AB66: =IF($A66<>"", AC66+AD66, "") -> 3450000 | AC66: =IF(A66<>"", AC65+D66+F66-G66, "") -> 549512.58 | AD66: =IF(A66<>"", AD65+C66-F66+G66, "") -> 2900487.4 | AE66: =IF(A67<>"", A67-A66, IF(A66<>"",IF(AC66<>0,TODAY()-A66,0), "")) -> 7 | AG66: =IF($A66<>"", I66+J66+E66-F66-H66, "") -> 1900 | AH66: =IF(A66<>"", A66-A$3, "") -> 168 | AI66: =IF(A66<>"", AG66*(1+$X$3)^-(AH66/365), "") -> 1900 | AL66: =IF($A66<>"", AG66-IF(ISNUMBER(K66),K66*L66,0), "") -> 1900 | AM66: =IF(A66<>"", AL66*(1+$X$6/CompoundingRate)^-(AH66/(365/CompoundingRate)), "") -> 1900 | AQ66: =IF(AQ65<$AP$3,AQ65+1,"") -> 44414 | AR66: =IF($AQ66<>"", INDEX($AC$3:$AC$1055, MATCH($AQ66,$A$3:$A$1055,1)), "") -> 515390.06 | AS66: =IF($AQ66<>"", INDEX(Inputs!$B$3:$B$101, MATCH($AQ66,Inputs!$A$3:$A$101,1)), "") -> 0.001 | AT66: =IF($AQ66<>"", AR66*AS66/365, "") -> 1.4120276 | AU66: =IF($AQ66<>"", SUMIFS($AL$3:$AL$1054, $A$3:$A$1054,$AQ66) + SUMIFS($M$3:$M$1054, $A$3:$A$1054,$AQ66)*IFERROR(AVERAGEIFS($L$3:$L$1054, $A$3:$A$1054,$AQ66, $M$3:$M$1054,">0"),0) - AT66, "") -> 1898.588 | AV66: =IF(AQ66<>"", AU66*(1+$X$9/CompoundingRate)^-((AQ66-AQ$3)/(365/CompoundingRate)), "") -> 1898.588
A67: 44526 | B67: Rent - Andre | I67: 1900 | M67: =IF($A67<>"", IF(ISNUMBER(SEARCH("Debt Cost (est.)",B67)), SUMIFS(AT:AT, AQ:AQ, ">="&DATE("20"&RIGHT(LEFT(B67,4),2)-1,7,1), AQ:AQ, "<="&DATE("20"&RIGHT(LEFT(B67,4),2),6,30)), ""), "") | AA67: =IF($A67<>"", MIN(AB67,$P$3), "") -> 3450000 | AB67: =IF($A67<>"", AC67+AD67, "") -> 3450000 | AC67: =IF(A67<>"", AC66+D67+F67-G67, "") -> 549512.58 | AD67: =IF(A67<>"", AD66+C67-F67+G67, "") -> 2900487.4 | AE67: =IF(A68<>"", A68-A67, IF(A67<>"",IF(AC67<>0,TODAY()-A67,0), "")) -> 4 | AG67: =IF($A67<>"", I67+J67+E67-F67-H67, "") -> 1900 | AH67: =IF(A67<>"", A67-A$3, "") -> 175 | AI67: =IF(A67<>"", AG67*(1+$X$3)^-(AH67/365), "") -> 1900 | AL67: =IF($A67<>"", AG67-IF(ISNUMBER(K67),K67*L67,0), "") -> 1900 | AM67: =IF(A67<>"", AL67*(1+$X$6/CompoundingRate)^-(AH67/(365/CompoundingRate)), "") -> 1900 | AQ67: =IF(AQ66<$AP$3,AQ66+1,"") -> 44415 | AR67: =IF($AQ67<>"", INDEX($AC$3:$AC$1055, MATCH($AQ67,$A$3:$A$1055,1)), "") -> 515390.06 | AS67: =IF($AQ67<>"", INDEX(Inputs!$B$3:$B$101, MATCH($AQ67,Inputs!$A$3:$A$101,1)), "") -> 0.001 | AT67: =IF($AQ67<>"", AR67*AS67/365, "") -> 1.4120276 | AU67: =IF($AQ67<>"", SUMIFS($AL$3:$AL$1054, $A$3:$A$1054,$AQ67) + SUMIFS($M$3:$M$1054, $A$3:$A$1054,$AQ67)*IFERROR(AVERAGEIFS($L$3:$L$1054, $A$3:$A$1054,$AQ67, $M$3:$M$1054,">0"),0) - AT67, "") -> -1.4120276 | AV67: =IF(AQ67<>"", AU67*(1+$X$9/CompoundingRate)^-((AQ67-AQ$3)/(365/CompoundingRate)), "") -> -1.4120276
A68: 44530 | B68: NAB #3063 - Interest | G68: 4400.73 | M68: =IF($A68<>"", IF(ISNUMBER(SEARCH("Debt Cost (est.)",B68)), SUMIFS(AT:AT, AQ:AQ, ">="&DATE("20"&RIGHT(LEFT(B68,4),2)-1,7,1), AQ:AQ, "<="&DATE("20"&RIGHT(LEFT(B68,4),2),6,30)), ""), "") | AA68: =IF($A68<>"", MIN(AB68,$P$3), "") -> 3450000 | AB68: =IF($A68<>"", AC68+AD68, "") -> 3450000 | AC68: =IF(A68<>"", AC67+D68+F68-G68, "") -> 545111.85 | AD68: =IF(A68<>"", AD67+C68-F68+G68, "") -> 2904888.2 | AE68: =IF(A69<>"", A69-A68, IF(A68<>"",IF(AC68<>0,TODAY()-A68,0), "")) -> 0 | AG68: =IF($A68<>"", I68+J68+E68-F68-H68, "") -> 0 | AH68: =IF(A68<>"", A68-A$3, "") -> 179 | AI68: =IF(A68<>"", AG68*(1+$X$3)^-(AH68/365), "") -> 0 | AL68: =IF($A68<>"", AG68-IF(ISNUMBER(K68),K68*L68,0), "") -> 0 | AM68: =IF(A68<>"", AL68*(1+$X$6/CompoundingRate)^-(AH68/(365/CompoundingRate)), "") -> 0 | AQ68: =IF(AQ67<$AP$3,AQ67+1,"") -> 44416 | AR68: =IF($AQ68<>"", INDEX($AC$3:$AC$1055, MATCH($AQ68,$A$3:$A$1055,1)), "") -> 515390.06 | AS68: =IF($AQ68<>"", INDEX(Inputs!$B$3:$B$101, MATCH($AQ68,Inputs!$A$3:$A$101,1)), "") -> 0.001 | AT68: =IF($AQ68<>"", AR68*AS68/365, "") -> 1.4120276 | AU68: =IF($AQ68<>"", SUMIFS($AL$3:$AL$1054, $A$3:$A$1054,$AQ68) + SUMIFS($M$3:$M$1054, $A$3:$A$1054,$AQ68)*IFERROR(AVERAGEIFS($L$3:$L$1054, $A$3:$A$1054,$AQ68, $M$3:$M$1054,">0"),0) - AT68, "") -> -1.4120276 | AV68: =IF(AQ68<>"", AU68*(1+$X$9/CompoundingRate)^-((AQ68-AQ$3)/(365/CompoundingRate)), "") -> -1.4120276
A69: 44530 | B69: NAB #2157 - Interest | G69: 582.62 | M69: =IF($A69<>"", IF(ISNUMBER(SEARCH("Debt Cost (est.)",B69)), SUMIFS(AT:AT, AQ:AQ, ">="&DATE("20"&RIGHT(LEFT(B69,4),2)-1,7,1), AQ:AQ, "<="&DATE("20"&RIGHT(LEFT(B69,4),2),6,30)), ""), "") | AA69: =IF($A69<>"", MIN(AB69,$P$3), "") -> 3450000 | AB69: =IF($A69<>"", AC69+AD69, "") -> 3450000 | AC69: =IF(A69<>"", AC68+D69+F69-G69, "") -> 544529.23 | AD69: =IF(A69<>"", AD68+C69-F69+G69, "") -> 2905470.8 | AE69: =IF(A70<>"", A70-A69, IF(A69<>"",IF(AC69<>0,TODAY()-A69,0), "")) -> 3 | AG69: =IF($A69<>"", I69+J69+E69-F69-H69, "") -> 0 | AH69: =IF(A69<>"", A69-A$3, "") -> 179 | AI69: =IF(A69<>"", AG69*(1+$X$3)^-(AH69/365), "") -> 0 | AL69: =IF($A69<>"", AG69-IF(ISNUMBER(K69),K69*L69,0), "") -> 0 | AM69: =IF(A69<>"", AL69*(1+$X$6/CompoundingRate)^-(AH69/(365/CompoundingRate)), "") -> 0 | AQ69: =IF(AQ68<$AP$3,AQ68+1,"") -> 44417 | AR69: =IF($AQ69<>"", INDEX($AC$3:$AC$1055, MATCH($AQ69,$A$3:$A$1055,1)), "") -> 515390.06 | AS69: =IF($AQ69<>"", INDEX(Inputs!$B$3:$B$101, MATCH($AQ69,Inputs!$A$3:$A$101,1)), "") -> 0.001 | AT69: =IF($AQ69<>"", AR69*AS69/365, "") -> 1.4120276 | AU69: =IF($AQ69<>"", SUMIFS($AL$3:$AL$1054, $A$3:$A$1054,$AQ69) + SUMIFS($M$3:$M$1054, $A$3:$A$1054,$AQ69)*IFERROR(AVERAGEIFS($L$3:$L$1054, $A$3:$A$1054,$AQ69, $M$3:$M$1054,">0"),0) - AT69, "") -> -1.4120276 | AV69: =IF(AQ69<>"", AU69*(1+$X$9/CompoundingRate)^-((AQ69-AQ$3)/(365/CompoundingRate)), "") -> -1.4120276
A70: 44533 | B70: Rent - Andre | I70: 1900 | M70: =IF($A70<>"", IF(ISNUMBER(SEARCH("Debt Cost (est.)",B70)), SUMIFS(AT:AT, AQ:AQ, ">="&DATE("20"&RIGHT(LEFT(B70,4),2)-1,7,1), AQ:AQ, "<="&DATE("20"&RIGHT(LEFT(B70,4),2),6,30)), ""), "") | AA70: =IF($A70<>"", MIN(AB70,$P$3), "") -> 3450000 | AB70: =IF($A70<>"", AC70+AD70, "") -> 3450000 | AC70: =IF(A70<>"", AC69+D70+F70-G70, "") -> 544529.23 | AD70: =IF(A70<>"", AD69+C70-F70+G70, "") -> 2905470.8 | AE70: =IF(A71<>"", A71-A70, IF(A70<>"",IF(AC70<>0,TODAY()-A70,0), "")) -> 7 | AG70: =IF($A70<>"", I70+J70+E70-F70-H70, "") -> 1900 | AH70: =IF(A70<>"", A70-A$3, "") -> 182 | AI70: =IF(A70<>"", AG70*(1+$X$3)^-(AH70/365), "") -> 1900 | AL70: =IF($A70<>"", AG70-IF(ISNUMBER(K70),K70*L70,0), "") -> 1900 | AM70: =IF(A70<>"", AL70*(1+$X$6/CompoundingRate)^-(AH70/(365/CompoundingRate)), "") -> 1900 | AQ70: =IF(AQ69<$AP$3,AQ69+1,"") -> 44418 | AR70: =IF($AQ70<>"", INDEX($AC$3:$AC$1055, MATCH($AQ70,$A$3:$A$1055,1)), "") -> 515390.06 | AS70: =IF($AQ70<>"", INDEX(Inputs!$B$3:$B$101, MATCH($AQ70,Inputs!$A$3:$A$101,1)), "") -> 0.001 | AT70: =IF($AQ70<>"", AR70*AS70/365, "") -> 1.4120276 | AU70: =IF($AQ70<>"", SUMIFS($AL$3:$AL$1054, $A$3:$A$1054,$AQ70) + SUMIFS($M$3:$M$1054, $A$3:$A$1054,$AQ70)*IFERROR(AVERAGEIFS($L$3:$L$1054, $A$3:$A$1054,$AQ70, $M$3:$M$1054,">0"),0) - AT70, "") -> -1.4120276 | AV70: =IF(AQ70<>"", AU70*(1+$X$9/CompoundingRate)^-((AQ70-AQ$3)/(365/CompoundingRate)), "") -> -1.4120276
A71: 44540 | B71: Rent - Andre | I71: 1900 | M71: =IF($A71<>"", IF(ISNUMBER(SEARCH("Debt Cost (est.)",B71)), SUMIFS(AT:AT, AQ:AQ, ">="&DATE("20"&RIGHT(LEFT(B71,4),2)-1,7,1), AQ:AQ, "<="&DATE("20"&RIGHT(LEFT(B71,4),2),6,30)), ""), "") | AA71: =IF($A71<>"", MIN(AB71,$P$3), "") -> 3450000 | AB71: =IF($A71<>"", AC71+AD71, "") -> 3450000 | AC71: =IF(A71<>"", AC70+D71+F71-G71, "") -> 544529.23 | AD71: =IF(A71<>"", AD70+C71-F71+G71, "") -> 2905470.8 | AE71: =IF(A72<>"", A72-A71, IF(A71<>"",IF(AC71<>0,TODAY()-A71,0), "")) -> 6 | AG71: =IF($A71<>"", I71+J71+E71-F71-H71, "") -> 1900 | AH71: =IF(A71<>"", A71-A$3, "") -> 189 | AI71: =IF(A71<>"", AG71*(1+$X$3)^-(AH71/365), "") -> 1900 | AL71: =IF($A71<>"", AG71-IF(ISNUMBER(K71),K71*L71,0), "") -> 1900 | AM71: =IF(A71<>"", AL71*(1+$X$6/CompoundingRate)^-(AH71/(365/CompoundingRate)), "") -> 1900 | AQ71: =IF(AQ70<$AP$3,AQ70+1,"") -> 44419 | AR71: =IF($AQ71<>"", INDEX($AC$3:$AC$1055, MATCH($AQ71,$A$3:$A$1055,1)), "") -> 515390.06 | AS71: =IF($AQ71<>"", INDEX(Inputs!$B$3:$B$101, MATCH($AQ71,Inputs!$A$3:$A$101,1)), "") -> 0.001 | AT71: =IF($AQ71<>"", AR71*AS71/365, "") -> 1.4120276 | AU71: =IF($AQ71<>"", SUMIFS($AL$3:$AL$1054, $A$3:$A$1054,$AQ71) + SUMIFS($M$3:$M$1054, $A$3:$A$1054,$AQ71)*IFERROR(AVERAGEIFS($L$3:$L$1054, $A$3:$A$1054,$AQ71, $M$3:$M$1054,">0"),0) - AT71, "") -> -1.4120276 | AV71: =IF(AQ71<>"", AU71*(1+$X$9/CompoundingRate)^-((AQ71-AQ$3)/(365/CompoundingRate)), "") -> -1.4120276
A72: 44546 | B72: NAB #3063 - Repayment | F72: 9818.51 | M72: =IF($A72<>"", IF(ISNUMBER(SEARCH("Debt Cost (est.)",B72)), SUMIFS(AT:AT, AQ:AQ, ">="&DATE("20"&RIGHT(LEFT(B72,4),2)-1,7,1), AQ:AQ, "<="&DATE("20"&RIGHT(LEFT(B72,4),2),6,30)), ""), "") | AA72: =IF($A72<>"", MIN(AB72,$P$3), "") -> 3450000 | AB72: =IF($A72<>"", AC72+AD72, "") -> 3450000 | AC72: =IF(A72<>"", AC71+D72+F72-G72, "") -> 554347.74 | AD72: =IF(A72<>"", AD71+C72-F72+G72, "") -> 2895652.3 | AE72: =IF(A73<>"", A73-A72, IF(A72<>"",IF(AC72<>0,TODAY()-A72,0), "")) -> 0 | AG72: =IF($A72<>"", I72+J72+E72-F72-H72, "") -> -9818.51 | AH72: =IF(A72<>"", A72-A$3, "") -> 195 | AI72: =IF(A72<>"", AG72*(1+$X$3)^-(AH72/365), "") -> -9818.51 | AL72: =IF($A72<>"", AG72-IF(ISNUMBER(K72),K72*L72,0), "") -> -9818.51 | AM72: =IF(A72<>"", AL72*(1+$X$6/CompoundingRate)^-(AH72/(365/CompoundingRate)), "") -> -9818.51 | AQ72: =IF(AQ71<$AP$3,AQ71+1,"") -> 44420 | AR72: =IF($AQ72<>"", INDEX($AC$3:$AC$1055, MATCH($AQ72,$A$3:$A$1055,1)), "") -> 515390.06 | AS72: =IF($AQ72<>"", INDEX(Inputs!$B$3:$B$101, MATCH($AQ72,Inputs!$A$3:$A$101,1)), "") -> 0.001 | AT72: =IF($AQ72<>"", AR72*AS72/365, "") -> 1.4120276 | AU72: =IF($AQ72<>"", SUMIFS($AL$3:$AL$1054, $A$3:$A$1054,$AQ72) + SUMIFS($M$3:$M$1054, $A$3:$A$1054,$AQ72)*IFERROR(AVERAGEIFS($L$3:$L$1054, $A$3:$A$1054,$AQ72, $M$3:$M$1054,">0"),0) - AT72, "") -> -1.4120276 | AV72: =IF(AQ72<>"", AU72*(1+$X$9/CompoundingRate)^-((AQ72-AQ$3)/(365/CompoundingRate)), "") -> -1.4120276
A73: 44546 | B73: NAB #2157 - Repayment | F73: 2232.44 | M73: =IF($A73<>"", IF(ISNUMBER(SEARCH("Debt Cost (est.)",B73)), SUMIFS(AT:AT, AQ:AQ, ">="&DATE("20"&RIGHT(LEFT(B73,4),2)-1,7,1), AQ:AQ, "<="&DATE("20"&RIGHT(LEFT(B73,4),2),6,30)), ""), "") | AA73: =IF($A73<>"", MIN(AB73,$P$3), "") -> 3450000 | AB73: =IF($A73<>"", AC73+AD73, "") -> 3450000 | AC73: =IF(A73<>"", AC72+D73+F73-G73, "") -> 556580.18 | AD73: =IF(A73<>"", AD72+C73-F73+G73, "") -> 2893419.8 | AE73: =IF(A74<>"", A74-A73, IF(A73<>"",IF(AC73<>0,TODAY()-A73,0), "")) -> 0 | AG73: =IF($A73<>"", I73+J73+E73-F73-H73, "") -> -2232.44 | AH73: =IF(A73<>"", A73-A$3, "") -> 195 | AI73: =IF(A73<>"", AG73*(1+$X$3)^-(AH73/365), "") -> -2232.44 | AL73: =IF($A73<>"", AG73-IF(ISNUMBER(K73),K73*L73,0), "") -> -2232.44 | AM73: =IF(A73<>"", AL73*(1+$X$6/CompoundingRate)^-(AH73/(365/CompoundingRate)), "") -> -2232.44 | AQ73: =IF(AQ72<$AP$3,AQ72+1,"") -> 44421 | AR73: =IF($AQ73<>"", INDEX($AC$3:$AC$1055, MATCH($AQ73,$A$3:$A$1055,1)), "") -> 515390.06 | AS73: =IF($AQ73<>"", INDEX(Inputs!$B$3:$B$101, MATCH($AQ73,Inputs!$A$3:$A$101,1)), "") -> 0.001 | AT73: =IF($AQ73<>"", AR73*AS73/365, "") -> 1.4120276 | AU73: =IF($AQ73<>"", SUMIFS($AL$3:$AL$1054, $A$3:$A$1054,$AQ73) + SUMIFS($M$3:$M$1054, $A$3:$A$1054,$AQ73)*IFERROR(AVERAGEIFS($L$3:$L$1054, $A$3:$A$1054,$AQ73, $M$3:$M$1054,">0"),0) - AT73, "") -> 1898.588 | AV73: =IF(AQ73<>"", AU73*(1+$X$9/CompoundingRate)^-((AQ73-AQ$3)/(365/CompoundingRate)), "") -> 1898.588
A74: 44546 | B74: Strata Levies | H74: 3126.64 | M74: =IF($A74<>"", IF(ISNUMBER(SEARCH("Debt Cost (est.)",B74)), SUMIFS(AT:AT, AQ:AQ, ">="&DATE("20"&RIGHT(LEFT(B74,4),2)-1,7,1), AQ:AQ, "<="&DATE("20"&RIGHT(LEFT(B74,4),2),6,30)), ""), "") | AA74: =IF($A74<>"", MIN(AB74,$P$3), "") -> 3450000 | AB74: =IF($A74<>"", AC74+AD74, "") -> 3450000 | AC74: =IF(A74<>"", AC73+D74+F74-G74, "") -> 556580.18 | AD74: =IF(A74<>"", AD73+C74-F74+G74, "") -> 2893419.8 | AE74: =IF(A75<>"", A75-A74, IF(A74<>"",IF(AC74<>0,TODAY()-A74,0), "")) -> 1 | AG74: =IF($A74<>"", I74+J74+E74-F74-H74, "") -> -3126.64 | AH74: =IF(A74<>"", A74-A$3, "") -> 195 | AI74: =IF(A74<>"", AG74*(1+$X$3)^-(AH74/365), "") -> -3126.64 | AL74: =IF($A74<>"", AG74-IF(ISNUMBER(K74),K74*L74,0), "") -> -3126.64 | AM74: =IF(A74<>"", AL74*(1+$X$6/CompoundingRate)^-(AH74/(365/CompoundingRate)), "") -> -3126.64 | AQ74: =IF(AQ73<$AP$3,AQ73+1,"") -> 44422 | AR74: =IF($AQ74<>"", INDEX($AC$3:$AC$1055, MATCH($AQ74,$A$3:$A$1055,1)), "") -> 515390.06 | AS74: =IF($AQ74<>"", INDEX(Inputs!$B$3:$B$101, MATCH($AQ74,Inputs!$A$3:$A$101,1)), "") -> 0.001 | AT74: =IF($AQ74<>"", AR74*AS74/365, "") -> 1.4120276 | AU74: =IF($AQ74<>"", SUMIFS($AL$3:$AL$1054, $A$3:$A$1054,$AQ74) + SUMIFS($M$3:$M$1054, $A$3:$A$1054,$AQ74)*IFERROR(AVERAGEIFS($L$3:$L$1054, $A$3:$A$1054,$AQ74, $M$3:$M$1054,">0"),0) - AT74, "") -> -1.4120276 | AV74: =IF(AQ74<>"", AU74*(1+$X$9/CompoundingRate)^-((AQ74-AQ$3)/(365/CompoundingRate)), "") -> -1.4120276
A75: 44547 | B75: Rent - Andre | I75: 1900 | M75: =IF($A75<>"", IF(ISNUMBER(SEARCH("Debt Cost (est.)",B75)), SUMIFS(AT:AT, AQ:AQ, ">="&DATE("20"&RIGHT(LEFT(B75,4),2)-1,7,1), AQ:AQ, "<="&DATE("20"&RIGHT(LEFT(B75,4),2),6,30)), ""), "") | AA75: =IF($A75<>"", MIN(AB75,$P$3), "") -> 3450000 | AB75: =IF($A75<>"", AC75+AD75, "") -> 3450000 | AC75: =IF(A75<>"", AC74+D75+F75-G75, "") -> 556580.18 | AD75: =IF(A75<>"", AD74+C75-F75+G75, "") -> 2893419.8 | AE75: =IF(A76<>"", A76-A75, IF(A75<>"",IF(AC75<>0,TODAY()-A75,0), "")) -> 7 | AG75: =IF($A75<>"", I75+J75+E75-F75-H75, "") -> 1900 | AH75: =IF(A75<>"", A75-A$3, "") -> 196 | AI75: =IF(A75<>"", AG75*(1+$X$3)^-(AH75/365), "") -> 1900 | AL75: =IF($A75<>"", AG75-IF(ISNUMBER(K75),K75*L75,0), "") -> 1900 | AM75: =IF(A75<>"", AL75*(1+$X$6/CompoundingRate)^-(AH75/(365/CompoundingRate)), "") -> 1900 | AQ75: =IF(AQ74<$AP$3,AQ74+1,"") -> 44423 | AR75: =IF($AQ75<>"", INDEX($AC$3:$AC$1055, MATCH($AQ75,$A$3:$A$1055,1)), "") -> 515390.06 | AS75: =IF($AQ75<>"", INDEX(Inputs!$B$3:$B$101, MATCH($AQ75,Inputs!$A$3:$A$101,1)), "") -> 0.001 | AT75: =IF($AQ75<>"", AR75*AS75/365, "") -> 1.4120276 | AU75: =IF($AQ75<>"", SUMIFS($AL$3:$AL$1054, $A$3:$A$1054,$AQ75) + SUMIFS($M$3:$M$1054, $A$3:$A$1054,$AQ75)*IFERROR(AVERAGEIFS($L$3:$L$1054, $A$3:$A$1054,$AQ75, $M$3:$M$1054,">0"),0) - AT75, "") -> -1.4120276 | AV75: =IF(AQ75<>"", AU75*(1+$X$9/CompoundingRate)^-((AQ75-AQ$3)/(365/CompoundingRate)), "") -> -1.4120276
A76: 44554 | B76: Rent - Andre | I76: 1900 | M76: =IF($A76<>"", IF(ISNUMBER(SEARCH("Debt Cost (est.)",B76)), SUMIFS(AT:AT, AQ:AQ, ">="&DATE("20"&RIGHT(LEFT(B76,4),2)-1,7,1), AQ:AQ, "<="&DATE("20"&RIGHT(LEFT(B76,4),2),6,30)), ""), "") | AA76: =IF($A76<>"", MIN(AB76,$P$3), "") -> 3450000 | AB76: =IF($A76<>"", AC76+AD76, "") -> 3450000 | AC76: =IF(A76<>"", AC75+D76+F76-G76, "") -> 556580.18 | AD76: =IF(A76<>"", AD75+C76-F76+G76, "") -> 2893419.8 | AE76: =IF(A77<>"", A77-A76, IF(A76<>"",IF(AC76<>0,TODAY()-A76,0), "")) -> 5 | AG76: =IF($A76<>"", I76+J76+E76-F76-H76, "") -> 1900 | AH76: =IF(A76<>"", A76-A$3, "") -> 203 | AI76: =IF(A76<>"", AG76*(1+$X$3)^-(AH76/365), "") -> 1900 | AL76: =IF($A76<>"", AG76-IF(ISNUMBER(K76),K76*L76,0), "") -> 1900 | AM76: =IF(A76<>"", AL76*(1+$X$6/CompoundingRate)^-(AH76/(365/CompoundingRate)), "") -> 1900 | AQ76: =IF(AQ75<$AP$3,AQ75+1,"") -> 44424 | AR76: =IF($AQ76<>"", INDEX($AC$3:$AC$1055, MATCH($AQ76,$A$3:$A$1055,1)), "") -> 527441.01 | AS76: =IF($AQ76<>"", INDEX(Inputs!$B$3:$B$101, MATCH($AQ76,Inputs!$A$3:$A$101,1)), "") -> 0.001 | AT76: =IF($AQ76<>"", AR76*AS76/365, "") -> 1.4450439 | AU76: =IF($AQ76<>"", SUMIFS($AL$3:$AL$1054, $A$3:$A$1054,$AQ76) + SUMIFS($M$3:$M$1054, $A$3:$A$1054,$AQ76)*IFERROR(AVERAGEIFS($L$3:$L$1054, $A$3:$A$1054,$AQ76, $M$3:$M$1054,">0"),0) - AT76, "") -> -12052.395 | AV76: =IF(AQ76<>"", AU76*(1+$X$9/CompoundingRate)^-((AQ76-AQ$3)/(365/CompoundingRate)), "") -> -12052.395
A77: 44559 | B77: Water Rates | H77: 278.94 | M77: =IF($A77<>"", IF(ISNUMBER(SEARCH("Debt Cost (est.)",B77)), SUMIFS(AT:AT, AQ:AQ, ">="&DATE("20"&RIGHT(LEFT(B77,4),2)-1,7,1), AQ:AQ, "<="&DATE("20"&RIGHT(LEFT(B77,4),2),6,30)), ""), "") | AA77: =IF($A77<>"", MIN(AB77,$P$3), "") -> 3450000 | AB77: =IF($A77<>"", AC77+AD77, "") -> 3450000 | AC77: =IF(A77<>"", AC76+D77+F77-G77, "") -> 556580.18 | AD77: =IF(A77<>"", AD76+C77-F77+G77, "") -> 2893419.8 | AE77: =IF(A78<>"", A78-A77, IF(A77<>"",IF(AC77<>0,TODAY()-A77,0), "")) -> 2 | AG77: =IF($A77<>"", I77+J77+E77-F77-H77, "") -> -278.94 | AH77: =IF(A77<>"", A77-A$3, "") -> 208 | AI77: =IF(A77<>"", AG77*(1+$X$3)^-(AH77/365), "") -> -278.94 | AL77: =IF($A77<>"", AG77-IF(ISNUMBER(K77),K77*L77,0), "") -> -278.94 | AM77: =IF(A77<>"", AL77*(1+$X$6/CompoundingRate)^-(AH77/(365/CompoundingRate)), "") -> -278.94 | AQ77: =IF(AQ76<$AP$3,AQ76+1,"") -> 44425 | AR77: =IF($AQ77<>"", INDEX($AC$3:$AC$1055, MATCH($AQ77,$A$3:$A$1055,1)), "") -> 527441.01 | AS77: =IF($AQ77<>"", INDEX(Inputs!$B$3:$B$101, MATCH($AQ77,Inputs!$A$3:$A$101,1)), "") -> 0.001 | AT77: =IF($AQ77<>"", AR77*AS77/365, "") -> 1.4450439 | AU77: =IF($AQ77<>"", SUMIFS($AL$3:$AL$1054, $A$3:$A$1054,$AQ77) + SUMIFS($M$3:$M$1054, $A$3:$A$1054,$AQ77)*IFERROR(AVERAGEIFS($L$3:$L$1054, $A$3:$A$1054,$AQ77, $M$3:$M$1054,">0"),0) - AT77, "") -> -1.4450439 | AV77: =IF(AQ77<>"", AU77*(1+$X$9/CompoundingRate)^-((AQ77-AQ$3)/(365/CompoundingRate)), "") -> -1.4450439
A78: 44561 | B78: Rent - Andre | I78: 1900 | M78: =IF($A78<>"", IF(ISNUMBER(SEARCH("Debt Cost (est.)",B78)), SUMIFS(AT:AT, AQ:AQ, ">="&DATE("20"&RIGHT(LEFT(B78,4),2)-1,7,1), AQ:AQ, "<="&DATE("20"&RIGHT(LEFT(B78,4),2),6,30)), ""), "") | AA78: =IF($A78<>"", MIN(AB78,$P$3), "") -> 3450000 | AB78: =IF($A78<>"", AC78+AD78, "") -> 3450000 | AC78: =IF(A78<>"", AC77+D78+F78-G78, "") -> 556580.18 | AD78: =IF(A78<>"", AD77+C78-F78+G78, "") -> 2893419.8 | AE78: =IF(A79<>"", A79-A78, IF(A78<>"",IF(AC78<>0,TODAY()-A78,0), "")) -> 0 | AG78: =IF($A78<>"", I78+J78+E78-F78-H78, "") -> 1900 | AH78: =IF(A78<>"", A78-A$3, "") -> 210 | AI78: =IF(A78<>"", AG78*(1+$X$3)^-(AH78/365), "") -> 1900 | AL78: =IF($A78<>"", AG78-IF(ISNUMBER(K78),K78*L78,0), "") -> 1900 | AM78: =IF(A78<>"", AL78*(1+$X$6/CompoundingRate)^-(AH78/(365/CompoundingRate)), "") -> 1900 | AQ78: =IF(AQ77<$AP$3,AQ77+1,"") -> 44426 | AR78: =IF($AQ78<>"", INDEX($AC$3:$AC$1055, MATCH($AQ78,$A$3:$A$1055,1)), "") -> 527441.01 | AS78: =IF($AQ78<>"", INDEX(Inputs!$B$3:$B$101, MATCH($AQ78,Inputs!$A$3:$A$101,1)), "") -> 0.001 | AT78: =IF($AQ78<>"", AR78*AS78/365, "") -> 1.4450439 | AU78: =IF($AQ78<>"", SUMIFS($AL$3:$AL$1054, $A$3:$A$1054,$AQ78) + SUMIFS($M$3:$M$1054, $A$3:$A$1054,$AQ78)*IFERROR(AVERAGEIFS($L$3:$L$1054, $A$3:$A$1054,$AQ78, $M$3:$M$1054,">0"),0) - AT78, "") -> -1.4450439 | AV78: =IF(AQ78<>"", AU78*(1+$X$9/CompoundingRate)^-((AQ78-AQ$3)/(365/CompoundingRate)), "") -> -1.4450439
A79: 44561 | B79: NAB #3063 - Interest | G79: 4252.84 | M79: =IF($A79<>"", IF(ISNUMBER(SEARCH("Debt Cost (est.)",B79)), SUMIFS(AT:AT, AQ:AQ, ">="&DATE("20"&RIGHT(LEFT(B79,4),2)-1,7,1), AQ:AQ, "<="&DATE("20"&RIGHT(LEFT(B79,4),2),6,30)), ""), "") | AA79: =IF($A79<>"", MIN(AB79,$P$3), "") -> 3450000 | AB79: =IF($A79<>"", AC79+AD79, "") -> 3450000 | AC79: =IF(A79<>"", AC78+D79+F79-G79, "") -> 552327.34 | AD79: =IF(A79<>"", AD78+C79-F79+G79, "") -> 2897672.7 | AE79: =IF(A80<>"", A80-A79, IF(A79<>"",IF(AC79<>0,TODAY()-A79,0), "")) -> 0 | AG79: =IF($A79<>"", I79+J79+E79-F79-H79, "") -> 0 | AH79: =IF(A79<>"", A79-A$3, "") -> 210 | AI79: =IF(A79<>"", AG79*(1+$X$3)^-(AH79/365), "") -> 0 | AL79: =IF($A79<>"", AG79-IF(ISNUMBER(K79),K79*L79,0), "") -> 0 | AM79: =IF(A79<>"", AL79*(1+$X$6/CompoundingRate)^-(AH79/(365/CompoundingRate)), "") -> 0 | AQ79: =IF(AQ78<$AP$3,AQ78+1,"") -> 44427 | AR79: =IF($AQ79<>"", INDEX($AC$3:$AC$1055, MATCH($AQ79,$A$3:$A$1055,1)), "") -> 527441.01 | AS79: =IF($AQ79<>"", INDEX(Inputs!$B$3:$B$101, MATCH($AQ79,Inputs!$A$3:$A$101,1)), "") -> 0.001 | AT79: =IF($AQ79<>"", AR79*AS79/365, "") -> 1.4450439 | AU79: =IF($AQ79<>"", SUMIFS($AL$3:$AL$1054, $A$3:$A$1054,$AQ79) + SUMIFS($M$3:$M$1054, $A$3:$A$1054,$AQ79)*IFERROR(AVERAGEIFS($L$3:$L$1054, $A$3:$A$1054,$AQ79, $M$3:$M$1054,">0"),0) - AT79, "") -> 333.60496 | AV79: =IF(AQ79<>"", AU79*(1+$X$9/CompoundingRate)^-((AQ79-AQ$3)/(365/CompoundingRate)), "") -> 333.60496
A80: 44561 | B80: NAB #2157 - Interest | G80: 666.37 | M80: =IF($A80<>"", IF(ISNUMBER(SEARCH("Debt Cost (est.)",B80)), SUMIFS(AT:AT, AQ:AQ, ">="&DATE("20"&RIGHT(LEFT(B80,4),2)-1,7,1), AQ:AQ, "<="&DATE("20"&RIGHT(LEFT(B80,4),2),6,30)), ""), "") | AA80: =IF($A80<>"", MIN(AB80,$P$3), "") -> 3450000 | AB80: =IF($A80<>"", AC80+AD80, "") -> 3450000 | AC80: =IF(A80<>"", AC79+D80+F80-G80, "") -> 551660.97 | AD80: =IF(A80<>"", AD79+C80-F80+G80, "") -> 2898339 | AE80: =IF(A81<>"", A81-A80, IF(A80<>"",IF(AC80<>0,TODAY()-A80,0), "")) -> 7 | AG80: =IF($A80<>"", I80+J80+E80-F80-H80, "") -> 0 | AH80: =IF(A80<>"", A80-A$3, "") -> 210 | AI80: =IF(A80<>"", AG80*(1+$X$3)^-(AH80/365), "") -> 0 | AL80: =IF($A80<>"", AG80-IF(ISNUMBER(K80),K80*L80,0), "") -> 0 | AM80: =IF(A80<>"", AL80*(1+$X$6/CompoundingRate)^-(AH80/(365/CompoundingRate)), "") -> 0 | AQ80: =IF(AQ79<$AP$3,AQ79+1,"") -> 44428 | AR80: =IF($AQ80<>"", INDEX($AC$3:$AC$1055, MATCH($AQ80,$A$3:$A$1055,1)), "") -> 527441.01 | AS80: =IF($AQ80<>"", INDEX(Inputs!$B$3:$B$101, MATCH($AQ80,Inputs!$A$3:$A$101,1)), "") -> 0.001 | AT80: =IF($AQ80<>"", AR80*AS80/365, "") -> 1.4450439 | AU80: =IF($AQ80<>"", SUMIFS($AL$3:$AL$1054, $A$3:$A$1054,$AQ80) + SUMIFS($M$3:$M$1054, $A$3:$A$1054,$AQ80)*IFERROR(AVERAGEIFS($L$3:$L$1054, $A$3:$A$1054,$AQ80, $M$3:$M$1054,">0"),0) - AT80, "") -> 1898.555 | AV80: =IF(AQ80<>"", AU80*(1+$X$9/CompoundingRate)^-((AQ80-AQ$3)/(365/CompoundingRate)), "") -> 1898.555
A81: 44568 | B81: Rent - Andre | I81: 1900 | M81: =IF($A81<>"", IF(ISNUMBER(SEARCH("Debt Cost (est.)",B81)), SUMIFS(AT:AT, AQ:AQ, ">="&DATE("20"&RIGHT(LEFT(B81,4),2)-1,7,1), AQ:AQ, "<="&DATE("20"&RIGHT(LEFT(B81,4),2),6,30)), ""), "") | AA81: =IF($A81<>"", MIN(AB81,$P$3), "") -> 3450000 | AB81: =IF($A81<>"", AC81+AD81, "") -> 3450000 | AC81: =IF(A81<>"", AC80+D81+F81-G81, "") -> 551660.97 | AD81: =IF(A81<>"", AD80+C81-F81+G81, "") -> 2898339 | AE81: =IF(A82<>"", A82-A81, IF(A81<>"",IF(AC81<>0,TODAY()-A81,0), "")) -> 7 | AG81: =IF($A81<>"", I81+J81+E81-F81-H81, "") -> 1900 | AH81: =IF(A81<>"", A81-A$3, "") -> 217 | AI81: =IF(A81<>"", AG81*(1+$X$3)^-(AH81/365), "") -> 1900 | AL81: =IF($A81<>"", AG81-IF(ISNUMBER(K81),K81*L81,0), "") -> 1900 | AM81: =IF(A81<>"", AL81*(1+$X$6/CompoundingRate)^-(AH81/(365/CompoundingRate)), "") -> 1900 | AQ81: =IF(AQ80<$AP$3,AQ80+1,"") -> 44429 | AR81: =IF($AQ81<>"", INDEX($AC$3:$AC$1055, MATCH($AQ81,$A$3:$A$1055,1)), "") -> 527441.01 | AS81: =IF($AQ81<>"", INDEX(Inputs!$B$3:$B$101, MATCH($AQ81,Inputs!$A$3:$A$101,1)), "") -> 0.001 | AT81: =IF($AQ81<>"", AR81*AS81/365, "") -> 1.4450439 | AU81: =IF($AQ81<>"", SUMIFS($AL$3:$AL$1054, $A$3:$A$1054,$AQ81) + SUMIFS($M$3:$M$1054, $A$3:$A$1054,$AQ81)*IFERROR(AVERAGEIFS($L$3:$L$1054, $A$3:$A$1054,$AQ81, $M$3:$M$1054,">0"),0) - AT81, "") -> -1.4450439 | AV81: =IF(AQ81<>"", AU81*(1+$X$9/CompoundingRate)^-((AQ81-AQ$3)/(365/CompoundingRate)), "") -> -1.4450439
A82: 44575 | B82: Rent - Andre | I82: 1900 | M82: =IF($A82<>"", IF(ISNUMBER(SEARCH("Debt Cost (est.)",B82)), SUMIFS(AT:AT, AQ:AQ, ">="&DATE("20"&RIGHT(LEFT(B82,4),2)-1,7,1), AQ:AQ, "<="&DATE("20"&RIGHT(LEFT(B82,4),2),6,30)), ""), "") | AA82: =IF($A82<>"", MIN(AB82,$P$3), "") -> 3450000 | AB82: =IF($A82<>"", AC82+AD82, "") -> 3450000 | AC82: =IF(A82<>"", AC81+D82+F82-G82, "") -> 551660.97 | AD82: =IF(A82<>"", AD81+C82-F82+G82, "") -> 2898339 | AE82: =IF(A83<>"", A83-A82, IF(A82<>"",IF(AC82<>0,TODAY()-A82,0), "")) -> 3 | AG82: =IF($A82<>"", I82+J82+E82-F82-H82, "") -> 1900 | AH82: =IF(A82<>"", A82-A$3, "") -> 224 | AI82: =IF(A82<>"", AG82*(1+$X$3)^-(AH82/365), "") -> 1900 | AL82: =IF($A82<>"", AG82-IF(ISNUMBER(K82),K82*L82,0), "") -> 1900 | AM82: =IF(A82<>"", AL82*(1+$X$6/CompoundingRate)^-(AH82/(365/CompoundingRate)), "") -> 1900 | AQ82: =IF(AQ81<$AP$3,AQ81+1,"") -> 44430 | AR82: =IF($AQ82<>"", INDEX($AC$3:$AC$1055, MATCH($AQ82,$A$3:$A$1055,1)), "") -> 527441.01 | AS82: =IF($AQ82<>"", INDEX(Inputs!$B$3:$B$101, MATCH($AQ82,Inputs!$A$3:$A$101,1)), "") -> 0.001 | AT82: =IF($AQ82<>"", AR82*AS82/365, "") -> 1.4450439 | AU82: =IF($AQ82<>"", SUMIFS($AL$3:$AL$1054, $A$3:$A$1054,$AQ82) + SUMIFS($M$3:$M$1054, $A$3:$A$1054,$AQ82)*IFERROR(AVERAGEIFS($L$3:$L$1054, $A$3:$A$1054,$AQ82, $M$3:$M$1054,">0"),0) - AT82, "") -> -1.4450439 | AV82: =IF(AQ82<>"", AU82*(1+$X$9/CompoundingRate)^-((AQ82-AQ$3)/(365/CompoundingRate)), "") -> -1.4450439
A83: 44578 | B83: NAB #3063 - Repayment | F83: 9818.51 | M83: =IF($A83<>"", IF(ISNUMBER(SEARCH("Debt Cost (est.)",B83)), SUMIFS(AT:AT, AQ:AQ, ">="&DATE("20"&RIGHT(LEFT(B83,4),2)-1,7,1), AQ:AQ, "<="&DATE("20"&RIGHT(LEFT(B83,4),2),6,30)), ""), "") | AA83: =IF($A83<>"", MIN(AB83,$P$3), "") -> 3450000 | AB83: =IF($A83<>"", AC83+AD83, "") -> 3450000 | AC83: =IF(A83<>"", AC82+D83+F83-G83, "") -> 561479.48 | AD83: =IF(A83<>"", AD82+C83-F83+G83, "") -> 2888520.5 | AE83: =IF(A84<>"", A84-A83, IF(A83<>"",IF(AC83<>0,TODAY()-A83,0), "")) -> 0 | AG83: =IF($A83<>"", I83+J83+E83-F83-H83, "") -> -9818.51 | AH83: =IF(A83<>"", A83-A$3, "") -> 227 | AI83: =IF(A83<>"", AG83*(1+$X$3)^-(AH83/365), "") -> -9818.51 | AL83: =IF($A83<>"", AG83-IF(ISNUMBER(K83),K83*L83,0), "") -> -9818.51 | AM83: =IF(A83<>"", AL83*(1+$X$6/CompoundingRate)^-(AH83/(365/CompoundingRate)), "") -> -9818.51 | AQ83: =IF(AQ82<$AP$3,AQ82+1,"") -> 44431 | AR83: =IF($AQ83<>"", INDEX($AC$3:$AC$1055, MATCH($AQ83,$A$3:$A$1055,1)), "") -> 527441.01 | AS83: =IF($AQ83<>"", INDEX(Inputs!$B$3:$B$101, MATCH($AQ83,Inputs!$A$3:$A$101,1)), "") -> 0.001 | AT83: =IF($AQ83<>"", AR83*AS83/365, "") -> 1.4450439 | AU83: =IF($AQ83<>"", SUMIFS($AL$3:$AL$1054, $A$3:$A$1054,$AQ83) + SUMIFS($M$3:$M$1054, $A$3:$A$1054,$AQ83)*IFERROR(AVERAGEIFS($L$3:$L$1054, $A$3:$A$1054,$AQ83, $M$3:$M$1054,">0"),0) - AT83, "") -> -1.4450439 | AV83: =IF(AQ83<>"", AU83*(1+$X$9/CompoundingRate)^-((AQ83-AQ$3)/(365/CompoundingRate)), "") -> -1.4450439
A84: 44578 | B84: NAB #2157 - Repayment | F84: 2232.44 | M84: =IF($A84<>"", IF(ISNUMBER(SEARCH("Debt Cost (est.)",B84)), SUMIFS(AT:AT, AQ:AQ, ">="&DATE("20"&RIGHT(LEFT(B84,4),2)-1,7,1), AQ:AQ, "<="&DATE("20"&RIGHT(LEFT(B84,4),2),6,30)), ""), "") | AA84: =IF($A84<>"", MIN(AB84,$P$3), "") -> 3450000 | AB84: =IF($A84<>"", AC84+AD84, "") -> 3450000 | AC84: =IF(A84<>"", AC83+D84+F84-G84, "") -> 563711.92 | AD84: =IF(A84<>"", AD83+C84-F84+G84, "") -> 2886288.1 | AE84: =IF(A85<>"", A85-A84, IF(A84<>"",IF(AC84<>0,TODAY()-A84,0), "")) -> 4 | AG84: =IF($A84<>"", I84+J84+E84-F84-H84, "") -> -2232.44 | AH84: =IF(A84<>"", A84-A$3, "") -> 227 | AI84: =IF(A84<>"", AG84*(1+$X$3)^-(AH84/365), "") -> -2232.44 | AL84: =IF($A84<>"", AG84-IF(ISNUMBER(K84),K84*L84,0), "") -> -2232.44 | AM84: =IF(A84<>"", AL84*(1+$X$6/CompoundingRate)^-(AH84/(365/CompoundingRate)), "") -> -2232.44 | AQ84: =IF(AQ83<$AP$3,AQ83+1,"") -> 44432 | AR84: =IF($AQ84<>"", INDEX($AC$3:$AC$1055, MATCH($AQ84,$A$3:$A$1055,1)), "") -> 527441.01 | AS84: =IF($AQ84<>"", INDEX(Inputs!$B$3:$B$101, MATCH($AQ84,Inputs!$A$3:$A$101,1)), "") -> 0.001 | AT84: =IF($AQ84<>"", AR84*AS84/365, "") -> 1.4450439 | AU84: =IF($AQ84<>"", SUMIFS($AL$3:$AL$1054, $A$3:$A$1054,$AQ84) + SUMIFS($M$3:$M$1054, $A$3:$A$1054,$AQ84)*IFERROR(AVERAGEIFS($L$3:$L$1054, $A$3:$A$1054,$AQ84, $M$3:$M$1054,">0"),0) - AT84, "") -> -1.4450439 | AV84: =IF(AQ84<>"", AU84*(1+$X$9/CompoundingRate)^-((AQ84-AQ$3)/(365/CompoundingRate)), "") -> -1.4450439
A85: 44582 | B85: Rent - Andre | I85: 1900 | M85: =IF($A85<>"", IF(ISNUMBER(SEARCH("Debt Cost (est.)",B85)), SUMIFS(AT:AT, AQ:AQ, ">="&DATE("20"&RIGHT(LEFT(B85,4),2)-1,7,1), AQ:AQ, "<="&DATE("20"&RIGHT(LEFT(B85,4),2),6,30)), ""), "") | AA85: =IF($A85<>"", MIN(AB85,$P$3), "") -> 3450000 | AB85: =IF($A85<>"", AC85+AD85, "") -> 3450000 | AC85: =IF(A85<>"", AC84+D85+F85-G85, "") -> 563711.92 | AD85: =IF(A85<>"", AD84+C85-F85+G85, "") -> 2886288.1 | AE85: =IF(A86<>"", A86-A85, IF(A85<>"",IF(AC85<>0,TODAY()-A85,0), "")) -> 7 | AG85: =IF($A85<>"", I85+J85+E85-F85-H85, "") -> 1900 | AH85: =IF(A85<>"", A85-A$3, "") -> 231 | AI85: =IF(A85<>"", AG85*(1+$X$3)^-(AH85/365), "") -> 1900 | AL85: =IF($A85<>"", AG85-IF(ISNUMBER(K85),K85*L85,0), "") -> 1900 | AM85: =IF(A85<>"", AL85*(1+$X$6/CompoundingRate)^-(AH85/(365/CompoundingRate)), "") -> 1900 | AQ85: =IF(AQ84<$AP$3,AQ84+1,"") -> 44433 | AR85: =IF($AQ85<>"", INDEX($AC$3:$AC$1055, MATCH($AQ85,$A$3:$A$1055,1)), "") -> 527441.01 | AS85: =IF($AQ85<>"", INDEX(Inputs!$B$3:$B$101, MATCH($AQ85,Inputs!$A$3:$A$101,1)), "") -> 0.001 | AT85: =IF($AQ85<>"", AR85*AS85/365, "") -> 1.4450439 | AU85: =IF($AQ85<>"", SUMIFS($AL$3:$AL$1054, $A$3:$A$1054,$AQ85) + SUMIFS($M$3:$M$1054, $A$3:$A$1054,$AQ85)*IFERROR(AVERAGEIFS($L$3:$L$1054, $A$3:$A$1054,$AQ85, $M$3:$M$1054,">0"),0) - AT85, "") -> -1.4450439 | AV85: =IF(AQ85<>"", AU85*(1+$X$9/CompoundingRate)^-((AQ85-AQ$3)/(365/CompoundingRate)), "") -> -1.4450439
A86: 44589 | B86: Rent - Andre | I86: 1900 | M86: =IF($A86<>"", IF(ISNUMBER(SEARCH("Debt Cost (est.)",B86)), SUMIFS(AT:AT, AQ:AQ, ">="&DATE("20"&RIGHT(LEFT(B86,4),2)-1,7,1), AQ:AQ, "<="&DATE("20"&RIGHT(LEFT(B86,4),2),6,30)), ""), "") | AA86: =IF($A86<>"", MIN(AB86,$P$3), "") -> 3450000 | AB86: =IF($A86<>"", AC86+AD86, "") -> 3450000 | AC86: =IF(A86<>"", AC85+D86+F86-G86, "") -> 563711.92 | AD86: =IF(A86<>"", AD85+C86-F86+G86, "") -> 2886288.1 | AE86: =IF(A87<>"", A87-A86, IF(A86<>"",IF(AC86<>0,TODAY()-A86,0), "")) -> 3 | AG86: =IF($A86<>"", I86+J86+E86-F86-H86, "") -> 1900 | AH86: =IF(A86<>"", A86-A$3, "") -> 238 | AI86: =IF(A86<>"", AG86*(1+$X$3)^-(AH86/365), "") -> 1900 | AL86: =IF($A86<>"", AG86-IF(ISNUMBER(K86),K86*L86,0), "") -> 1900 | AM86: =IF(A86<>"", AL86*(1+$X$6/CompoundingRate)^-(AH86/(365/CompoundingRate)), "") -> 1900 | AQ86: =IF(AQ85<$AP$3,AQ85+1,"") -> 44434 | AR86: =IF($AQ86<>"", INDEX($AC$3:$AC$1055, MATCH($AQ86,$A$3:$A$1055,1)), "") -> 527441.01 | AS86: =IF($AQ86<>"", INDEX(Inputs!$B$3:$B$101, MATCH($AQ86,Inputs!$A$3:$A$101,1)), "") -> 0.001 | AT86: =IF($AQ86<>"", AR86*AS86/365, "") -> 1.4450439 | AU86: =IF($AQ86<>"", SUMIFS($AL$3:$AL$1054, $A$3:$A$1054,$AQ86) + SUMIFS($M$3:$M$1054, $A$3:$A$1054,$AQ86)*IFERROR(AVERAGEIFS($L$3:$L$1054, $A$3:$A$1054,$AQ86, $M$3:$M$1054,">0"),0) - AT86, "") -> -1.4450439 | AV86: =IF(AQ86<>"", AU86*(1+$X$9/CompoundingRate)^-((AQ86-AQ$3)/(365/CompoundingRate)), "") -> -1.4450439
A87: 44592 | B87: NAB #3063 - Interest | G87: 4243.56 | M87: =IF($A87<>"", IF(ISNUMBER(SEARCH("Debt Cost (est.)",B87)), SUMIFS(AT:AT, AQ:AQ, ">="&DATE("20"&RIGHT(LEFT(B87,4),2)-1,7,1), AQ:AQ, "<="&DATE("20"&RIGHT(LEFT(B87,4),2),6,30)), ""), "") | AA87: =IF($A87<>"", MIN(AB87,$P$3), "") -> 3450000 | AB87: =IF($A87<>"", AC87+AD87, "") -> 3450000 | AC87: =IF(A87<>"", AC86+D87+F87-G87, "") -> 559468.36 | AD87: =IF(A87<>"", AD86+C87-F87+G87, "") -> 2890531.6 | AE87: =IF(A88<>"", A88-A87, IF(A87<>"",IF(AC87<>0,TODAY()-A87,0), "")) -> 0 | AG87: =IF($A87<>"", I87+J87+E87-F87-H87, "") -> 0 | AH87: =IF(A87<>"", A87-A$3, "") -> 241 | AI87: =IF(A87<>"", AG87*(1+$X$3)^-(AH87/365), "") -> 0 | AL87: =IF($A87<>"", AG87-IF(ISNUMBER(K87),K87*L87,0), "") -> 0 | AM87: =IF(A87<>"", AL87*(1+$X$6/CompoundingRate)^-(AH87/(365/CompoundingRate)), "") -> 0 | AQ87: =IF(AQ86<$AP$3,AQ86+1,"") -> 44435 | AR87: =IF($AQ87<>"", INDEX($AC$3:$AC$1055, MATCH($AQ87,$A$3:$A$1055,1)), "") -> 527441.01 | AS87: =IF($AQ87<>"", INDEX(Inputs!$B$3:$B$101, MATCH($AQ87,Inputs!$A$3:$A$101,1)), "") -> 0.001 | AT87: =IF($AQ87<>"", AR87*AS87/365, "") -> 1.4450439 | AU87: =IF($AQ87<>"", SUMIFS($AL$3:$AL$1054, $A$3:$A$1054,$AQ87) + SUMIFS($M$3:$M$1054, $A$3:$A$1054,$AQ87)*IFERROR(AVERAGEIFS($L$3:$L$1054, $A$3:$A$1054,$AQ87, $M$3:$M$1054,">0"),0) - AT87, "") -> 1898.555 | AV87: =IF(AQ87<>"", AU87*(1+$X$9/CompoundingRate)^-((AQ87-AQ$3)/(365/CompoundingRate)), "") -> 1898.555
A88: 44592 | B88: NAB #2157 - Interest | G88: 786.83 | M88: =IF($A88<>"", IF(ISNUMBER(SEARCH("Debt Cost (est.)",B88)), SUMIFS(AT:AT, AQ:AQ, ">="&DATE("20"&RIGHT(LEFT(B88,4),2)-1,7,1), AQ:AQ, "<="&DATE("20"&RIGHT(LEFT(B88,4),2),6,30)), ""), "") | AA88: =IF($A88<>"", MIN(AB88,$P$3), "") -> 3450000 | AB88: =IF($A88<>"", AC88+AD88, "") -> 3450000 | AC88: =IF(A88<>"", AC87+D88+F88-G88, "") -> 558681.53 | AD88: =IF(A88<>"", AD87+C88-F88+G88, "") -> 2891318.5 | AE88: =IF(A89<>"", A89-A88, IF(A88<>"",IF(AC88<>0,TODAY()-A88,0), "")) -> 0 | AG88: =IF($A88<>"", I88+J88+E88-F88-H88, "") -> 0 | AH88: =IF(A88<>"", A88-A$3, "") -> 241 | AI88: =IF(A88<>"", AG88*(1+$X$3)^-(AH88/365), "") -> 0 | AL88: =IF($A88<>"", AG88-IF(ISNUMBER(K88),K88*L88,0), "") -> 0 | AM88: =IF(A88<>"", AL88*(1+$X$6/CompoundingRate)^-(AH88/(365/CompoundingRate)), "") -> 0 | AQ88: =IF(AQ87<$AP$3,AQ87+1,"") -> 44436 | AR88: =IF($AQ88<>"", INDEX($AC$3:$AC$1055, MATCH($AQ88,$A$3:$A$1055,1)), "") -> 527441.01 | AS88: =IF($AQ88<>"", INDEX(Inputs!$B$3:$B$101, MATCH($AQ88,Inputs!$A$3:$A$101,1)), "") -> 0.001 | AT88: =IF($AQ88<>"", AR88*AS88/365, "") -> 1.4450439 | AU88: =IF($AQ88<>"", SUMIFS($AL$3:$AL$1054, $A$3:$A$1054,$AQ88) + SUMIFS($M$3:$M$1054, $A$3:$A$1054,$AQ88)*IFERROR(AVERAGEIFS($L$3:$L$1054, $A$3:$A$1054,$AQ88, $M$3:$M$1054,">0"),0) - AT88, "") -> -1.4450439 | AV88: =IF(AQ88<>"", AU88*(1+$X$9/CompoundingRate)^-((AQ88-AQ$3)/(365/CompoundingRate)), "") -> -1.4450439
A89: 44592 | B89: Strata Levies | H89: 3124 | M89: =IF($A89<>"", IF(ISNUMBER(SEARCH("Debt Cost (est.)",B89)), SUMIFS(AT:AT, AQ:AQ, ">="&DATE("20"&RIGHT(LEFT(B89,4),2)-1,7,1), AQ:AQ, "<="&DATE("20"&RIGHT(LEFT(B89,4),2),6,30)), ""), "") | AA89: =IF($A89<>"", MIN(AB89,$P$3), "") -> 3450000 | AB89: =IF($A89<>"", AC89+AD89, "") -> 3450000 | AC89: =IF(A89<>"", AC88+D89+F89-G89, "") -> 558681.53 | AD89: =IF(A89<>"", AD88+C89-F89+G89, "") -> 2891318.5 | AE89: =IF(A90<>"", A90-A89, IF(A89<>"",IF(AC89<>0,TODAY()-A89,0), "")) -> 4 | AG89: =IF($A89<>"", I89+J89+E89-F89-H89, "") -> -3124 | AH89: =IF(A89<>"", A89-A$3, "") -> 241 | AI89: =IF(A89<>"", AG89*(1+$X$3)^-(AH89/365), "") -> -3124 | AL89: =IF($A89<>"", AG89-IF(ISNUMBER(K89),K89*L89,0), "") -> -3124 | AM89: =IF(A89<>"", AL89*(1+$X$6/CompoundingRate)^-(AH89/(365/CompoundingRate)), "") -> -3124 | AQ89: =IF(AQ88<$AP$3,AQ88+1,"") -> 44437 | AR89: =IF($AQ89<>"", INDEX($AC$3:$AC$1055, MATCH($AQ89,$A$3:$A$1055,1)), "") -> 527441.01 | AS89: =IF($AQ89<>"", INDEX(Inputs!$B$3:$B$101, MATCH($AQ89,Inputs!$A$3:$A$101,1)), "") -> 0.001 | AT89: =IF($AQ89<>"", AR89*AS89/365, "") -> 1.4450439 | AU89: =IF($AQ89<>"", SUMIFS($AL$3:$AL$1054, $A$3:$A$1054,$AQ89) + SUMIFS($M$3:$M$1054, $A$3:$A$1054,$AQ89)*IFERROR(AVERAGEIFS($L$3:$L$1054, $A$3:$A$1054,$AQ89, $M$3:$M$1054,">0"),0) - AT89, "") -> -1.4450439 | AV89: =IF(AQ89<>"", AU89*(1+$X$9/CompoundingRate)^-((AQ89-AQ$3)/(365/CompoundingRate)), "") -> -1.4450439
A90: 44596 | B90: Rent - Andre | I90: 1900 | M90: =IF($A90<>"", IF(ISNUMBER(SEARCH("Debt Cost (est.)",B90)), SUMIFS(AT:AT, AQ:AQ, ">="&DATE("20"&RIGHT(LEFT(B90,4),2)-1,7,1), AQ:AQ, "<="&DATE("20"&RIGHT(LEFT(B90,4),2),6,30)), ""), "") | AA90: =IF($A90<>"", MIN(AB90,$P$3), "") -> 3450000 | AB90: =IF($A90<>"", AC90+AD90, "") -> 3450000 | AC90: =IF(A90<>"", AC89+D90+F90-G90, "") -> 558681.53 | AD90: =IF(A90<>"", AD89+C90-F90+G90, "") -> 2891318.5 | AE90: =IF(A91<>"", A91-A90, IF(A90<>"",IF(AC90<>0,TODAY()-A90,0), "")) -> 7 | AG90: =IF($A90<>"", I90+J90+E90-F90-H90, "") -> 1900 | AH90: =IF(A90<>"", A90-A$3, "") -> 245 | AI90: =IF(A90<>"", AG90*(1+$X$3)^-(AH90/365), "") -> 1900 | AL90: =IF($A90<>"", AG90-IF(ISNUMBER(K90),K90*L90,0), "") -> 1900 | AM90: =IF(A90<>"", AL90*(1+$X$6/CompoundingRate)^-(AH90/(365/CompoundingRate)), "") -> 1900 | AQ90: =IF(AQ89<$AP$3,AQ89+1,"") -> 44438 | AR90: =IF($AQ90<>"", INDEX($AC$3:$AC$1055, MATCH($AQ90,$A$3:$A$1055,1)), "") -> 527441.01 | AS90: =IF($AQ90<>"", INDEX(Inputs!$B$3:$B$101, MATCH($AQ90,Inputs!$A$3:$A$101,1)), "") -> 0.001 | AT90: =IF($AQ90<>"", AR90*AS90/365, "") -> 1.4450439 | AU90: =IF($AQ90<>"", SUMIFS($AL$3:$AL$1054, $A$3:$A$1054,$AQ90) + SUMIFS($M$3:$M$1054, $A$3:$A$1054,$AQ90)*IFERROR(AVERAGEIFS($L$3:$L$1054, $A$3:$A$1054,$AQ90, $M$3:$M$1054,">0"),0) - AT90, "") -> -1.4450439 | AV90: =IF(AQ90<>"", AU90*(1+$X$9/CompoundingRate)^-((AQ90-AQ$3)/(365/CompoundingRate)), "") -> -1.4450439
A91: 44603 | B91: Rent - Andre | I91: 1900 | M91: =IF($A91<>"", IF(ISNUMBER(SEARCH("Debt Cost (est.)",B91)), SUMIFS(AT:AT, AQ:AQ, ">="&DATE("20"&RIGHT(LEFT(B91,4),2)-1,7,1), AQ:AQ, "<="&DATE("20"&RIGHT(LEFT(B91,4),2),6,30)), ""), "") | AA91: =IF($A91<>"", MIN(AB91,$P$3), "") -> 3450000 | AB91: =IF($A91<>"", AC91+AD91, "") -> 3450000 | AC91: =IF(A91<>"", AC90+D91+F91-G91, "") -> 558681.53 | AD91: =IF(A91<>"", AD90+C91-F91+G91, "") -> 2891318.5 | AE91: =IF(A92<>"", A92-A91, IF(A91<>"",IF(AC91<>0,TODAY()-A91,0), "")) -> 5 | AG91: =IF($A91<>"", I91+J91+E91-F91-H91, "") -> 1900 | AH91: =IF(A91<>"", A91-A$3, "") -> 252 | AI91: =IF(A91<>"", AG91*(1+$X$3)^-(AH91/365), "") -> 1900 | AL91: =IF($A91<>"", AG91-IF(ISNUMBER(K91),K91*L91,0), "") -> 1900 | AM91: =IF(A91<>"", AL91*(1+$X$6/CompoundingRate)^-(AH91/(365/CompoundingRate)), "") -> 1900 | AQ91: =IF(AQ90<$AP$3,AQ90+1,"") -> 44439 | AR91: =IF($AQ91<>"", INDEX($AC$3:$AC$1055, MATCH($AQ91,$A$3:$A$1055,1)), "") -> 522678.15 | AS91: =IF($AQ91<>"", INDEX(Inputs!$B$3:$B$101, MATCH($AQ91,Inputs!$A$3:$A$101,1)), "") -> 0.001 | AT91: =IF($AQ91<>"", AR91*AS91/365, "") -> 1.4319949 | AU91: =IF($AQ91<>"", SUMIFS($AL$3:$AL$1054, $A$3:$A$1054,$AQ91) + SUMIFS($M$3:$M$1054, $A$3:$A$1054,$AQ91)*IFERROR(AVERAGEIFS($L$3:$L$1054, $A$3:$A$1054,$AQ91, $M$3:$M$1054,">0"),0) - AT91, "") -> -1.4319949 | AV91: =IF(AQ91<>"", AU91*(1+$X$9/CompoundingRate)^-((AQ91-AQ$3)/(365/CompoundingRate)), "") -> -1.4319949
A92: 44608 | B92: NAB #3063 - Repayment | F92: 9818.51 | M92: =IF($A92<>"", IF(ISNUMBER(SEARCH("Debt Cost (est.)",B92)), SUMIFS(AT:AT, AQ:AQ, ">="&DATE("20"&RIGHT(LEFT(B92,4),2)-1,7,1), AQ:AQ, "<="&DATE("20"&RIGHT(LEFT(B92,4),2),6,30)), ""), "") | AA92: =IF($A92<>"", MIN(AB92,$P$3), "") -> 3450000 | AB92: =IF($A92<>"", AC92+AD92, "") -> 3450000 | AC92: =IF(A92<>"", AC91+D92+F92-G92, "") -> 568500.04 | AD92: =IF(A92<>"", AD91+C92-F92+G92, "") -> 2881500 | AE92: =IF(A93<>"", A93-A92, IF(A92<>"",IF(AC92<>0,TODAY()-A92,0), "")) -> 0 | AG92: =IF($A92<>"", I92+J92+E92-F92-H92, "") -> -9818.51 | AH92: =IF(A92<>"", A92-A$3, "") -> 257 | AI92: =IF(A92<>"", AG92*(1+$X$3)^-(AH92/365), "") -> -9818.51 | AL92: =IF($A92<>"", AG92-IF(ISNUMBER(K92),K92*L92,0), "") -> -9818.51 | AM92: =IF(A92<>"", AL92*(1+$X$6/CompoundingRate)^-(AH92/(365/CompoundingRate)), "") -> -9818.51 | AQ92: =IF(AQ91<$AP$3,AQ91+1,"") -> 44440 | AR92: =IF($AQ92<>"", INDEX($AC$3:$AC$1055, MATCH($AQ92,$A$3:$A$1055,1)), "") -> 522678.15 | AS92: =IF($AQ92<>"", INDEX(Inputs!$B$3:$B$101, MATCH($AQ92,Inputs!$A$3:$A$101,1)), "") -> 0.001 | AT92: =IF($AQ92<>"", AR92*AS92/365, "") -> 1.4319949 | AU92: =IF($AQ92<>"", SUMIFS($AL$3:$AL$1054, $A$3:$A$1054,$AQ92) + SUMIFS($M$3:$M$1054, $A$3:$A$1054,$AQ92)*IFERROR(AVERAGEIFS($L$3:$L$1054, $A$3:$A$1054,$AQ92, $M$3:$M$1054,">0"),0) - AT92, "") -> -1.4319949 | AV92: =IF(AQ92<>"", AU92*(1+$X$9/CompoundingRate)^-((AQ92-AQ$3)/(365/CompoundingRate)), "") -> -1.4319949
A93: 44608 | B93: NAB #2157 - Repayment | F93: 2232.44 | M93: =IF($A93<>"", IF(ISNUMBER(SEARCH("Debt Cost (est.)",B93)), SUMIFS(AT:AT, AQ:AQ, ">="&DATE("20"&RIGHT(LEFT(B93,4),2)-1,7,1), AQ:AQ, "<="&DATE("20"&RIGHT(LEFT(B93,4),2),6,30)), ""), "") | AA93: =IF($A93<>"", MIN(AB93,$P$3), "") -> 3450000 | AB93: =IF($A93<>"", AC93+AD93, "") -> 3450000 | AC93: =IF(A93<>"", AC92+D93+F93-G93, "") -> 570732.48 | AD93: =IF(A93<>"", AD92+C93-F93+G93, "") -> 2879267.5 | AE93: =IF(A94<>"", A94-A93, IF(A93<>"",IF(AC93<>0,TODAY()-A93,0), "")) -> 2 | AG93: =IF($A93<>"", I93+J93+E93-F93-H93, "") -> -2232.44 | AH93: =IF(A93<>"", A93-A$3, "") -> 257 | AI93: =IF(A93<>"", AG93*(1+$X$3)^-(AH93/365), "") -> -2232.44 | AL93: =IF($A93<>"", AG93-IF(ISNUMBER(K93),K93*L93,0), "") -> -2232.44 | AM93: =IF(A93<>"", AL93*(1+$X$6/CompoundingRate)^-(AH93/(365/CompoundingRate)), "") -> -2232.44 | AQ93: =IF(AQ92<$AP$3,AQ92+1,"") -> 44441 | AR93: =IF($AQ93<>"", INDEX($AC$3:$AC$1055, MATCH($AQ93,$A$3:$A$1055,1)), "") -> 522678.15 | AS93: =IF($AQ93<>"", INDEX(Inputs!$B$3:$B$101, MATCH($AQ93,Inputs!$A$3:$A$101,1)), "") -> 0.001 | AT93: =IF($AQ93<>"", AR93*AS93/365, "") -> 1.4319949 | AU93: =IF($AQ93<>"", SUMIFS($AL$3:$AL$1054, $A$3:$A$1054,$AQ93) + SUMIFS($M$3:$M$1054, $A$3:$A$1054,$AQ93)*IFERROR(AVERAGEIFS($L$3:$L$1054, $A$3:$A$1054,$AQ93, $M$3:$M$1054,">0"),0) - AT93, "") -> -1.4319949 | AV93: =IF(AQ93<>"", AU93*(1+$X$9/CompoundingRate)^-((AQ93-AQ$3)/(365/CompoundingRate)), "") -> -1.4319949
A94: 44610 | B94: Rent - Andre | I94: 1900 | M94: =IF($A94<>"", IF(ISNUMBER(SEARCH("Debt Cost (est.)",B94)), SUMIFS(AT:AT, AQ:AQ, ">="&DATE("20"&RIGHT(LEFT(B94,4),2)-1,7,1), AQ:AQ, "<="&DATE("20"&RIGHT(LEFT(B94,4),2),6,30)), ""), "") | AA94: =IF($A94<>"", MIN(AB94,$P$3), "") -> 3450000 | AB94: =IF($A94<>"", AC94+AD94, "") -> 3450000 | AC94: =IF(A94<>"", AC93+D94+F94-G94, "") -> 570732.48 | AD94: =IF(A94<>"", AD93+C94-F94+G94, "") -> 2879267.5 | AE94: =IF(A95<>"", A95-A94, IF(A94<>"",IF(AC94<>0,TODAY()-A94,0), "")) -> 7 | AG94: =IF($A94<>"", I94+J94+E94-F94-H94, "") -> 1900 | AH94: =IF(A94<>"", A94-A$3, "") -> 259 | AI94: =IF(A94<>"", AG94*(1+$X$3)^-(AH94/365), "") -> 1900 | AL94: =IF($A94<>"", AG94-IF(ISNUMBER(K94),K94*L94,0), "") -> 1900 | AM94: =IF(A94<>"", AL94*(1+$X$6/CompoundingRate)^-(AH94/(365/CompoundingRate)), "") -> 1900 | AQ94: =IF(AQ93<$AP$3,AQ93+1,"") -> 44442 | AR94: =IF($AQ94<>"", INDEX($AC$3:$AC$1055, MATCH($AQ94,$A$3:$A$1055,1)), "") -> 522678.15 | AS94: =IF($AQ94<>"", INDEX(Inputs!$B$3:$B$101, MATCH($AQ94,Inputs!$A$3:$A$101,1)), "") -> 0.001 | AT94: =IF($AQ94<>"", AR94*AS94/365, "") -> 1.4319949 | AU94: =IF($AQ94<>"", SUMIFS($AL$3:$AL$1054, $A$3:$A$1054,$AQ94) + SUMIFS($M$3:$M$1054, $A$3:$A$1054,$AQ94)*IFERROR(AVERAGEIFS($L$3:$L$1054, $A$3:$A$1054,$AQ94, $M$3:$M$1054,">0"),0) - AT94, "") -> 1898.568 | AV94: =IF(AQ94<>"", AU94*(1+$X$9/CompoundingRate)^-((AQ94-AQ$3)/(365/CompoundingRate)), "") -> 1898.568
A95: 44617 | B95: Rent - Andre | I95: 1900 | M95: =IF($A95<>"", IF(ISNUMBER(SEARCH("Debt Cost (est.)",B95)), SUMIFS(AT:AT, AQ:AQ, ">="&DATE("20"&RIGHT(LEFT(B95,4),2)-1,7,1), AQ:AQ, "<="&DATE("20"&RIGHT(LEFT(B95,4),2),6,30)), ""), "") | AA95: =IF($A95<>"", MIN(AB95,$P$3), "") -> 3450000 | AB95: =IF($A95<>"", AC95+AD95, "") -> 3450000 | AC95: =IF(A95<>"", AC94+D95+F95-G95, "") -> 570732.48 | AD95: =IF(A95<>"", AD94+C95-F95+G95, "") -> 2879267.5 | AE95: =IF(A96<>"", A96-A95, IF(A95<>"",IF(AC95<>0,TODAY()-A95,0), "")) -> 3 | AG95: =IF($A95<>"", I95+J95+E95-F95-H95, "") -> 1900 | AH95: =IF(A95<>"", A95-A$3, "") -> 266 | AI95: =IF(A95<>"", AG95*(1+$X$3)^-(AH95/365), "") -> 1900 | AL95: =IF($A95<>"", AG95-IF(ISNUMBER(K95),K95*L95,0), "") -> 1900 | AM95: =IF(A95<>"", AL95*(1+$X$6/CompoundingRate)^-(AH95/(365/CompoundingRate)), "") -> 1900 | AQ95: =IF(AQ94<$AP$3,AQ94+1,"") -> 44443 | AR95: =IF($AQ95<>"", INDEX($AC$3:$AC$1055, MATCH($AQ95,$A$3:$A$1055,1)), "") -> 522678.15 | AS95: =IF($AQ95<>"", INDEX(Inputs!$B$3:$B$101, MATCH($AQ95,Inputs!$A$3:$A$101,1)), "") -> 0.001 | AT95: =IF($AQ95<>"", AR95*AS95/365, "") -> 1.4319949 | AU95: =IF($AQ95<>"", SUMIFS($AL$3:$AL$1054, $A$3:$A$1054,$AQ95) + SUMIFS($M$3:$M$1054, $A$3:$A$1054,$AQ95)*IFERROR(AVERAGEIFS($L$3:$L$1054, $A$3:$A$1054,$AQ95, $M$3:$M$1054,">0"),0) - AT95, "") -> -1.4319949 | AV95: =IF(AQ95<>"", AU95*(1+$X$9/CompoundingRate)^-((AQ95-AQ$3)/(365/CompoundingRate)), "") -> -1.4319949
A96: 44620 | B96: NAB #3063 - Interest | G96: 3824.36 | M96: =IF($A96<>"", IF(ISNUMBER(SEARCH("Debt Cost (est.)",B96)), SUMIFS(AT:AT, AQ:AQ, ">="&DATE("20"&RIGHT(LEFT(B96,4),2)-1,7,1), AQ:AQ, "<="&DATE("20"&RIGHT(LEFT(B96,4),2),6,30)), ""), "") | AA96: =IF($A96<>"", MIN(AB96,$P$3), "") -> 3450000 | AB96: =IF($A96<>"", AC96+AD96, "") -> 3450000 | AC96: =IF(A96<>"", AC95+D96+F96-G96, "") -> 566908.12 | AD96: =IF(A96<>"", AD95+C96-F96+G96, "") -> 2883091.9 | AE96: =IF(A97<>"", A97-A96, IF(A96<>"",IF(AC96<>0,TODAY()-A96,0), "")) -> 0 | AG96: =IF($A96<>"", I96+J96+E96-F96-H96, "") -> 0 | AH96: =IF(A96<>"", A96-A$3, "") -> 269 | AI96: =IF(A96<>"", AG96*(1+$X$3)^-(AH96/365), "") -> 0 | AL96: =IF($A96<>"", AG96-IF(ISNUMBER(K96),K96*L96,0), "") -> 0 | AM96: =IF(A96<>"", AL96*(1+$X$6/CompoundingRate)^-(AH96/(365/CompoundingRate)), "") -> 0 | AQ96: =IF(AQ95<$AP$3,AQ95+1,"") -> 44444 | AR96: =IF($AQ96<>"", INDEX($AC$3:$AC$1055, MATCH($AQ96,$A$3:$A$1055,1)), "") -> 522678.15 | AS96: =IF($AQ96<>"", INDEX(Inputs!$B$3:$B$101, MATCH($AQ96,Inputs!$A$3:$A$101,1)), "") -> 0.001 | AT96: =IF($AQ96<>"", AR96*AS96/365, "") -> 1.4319949 | AU96: =IF($AQ96<>"", SUMIFS($AL$3:$AL$1054, $A$3:$A$1054,$AQ96) + SUMIFS($M$3:$M$1054, $A$3:$A$1054,$AQ96)*IFERROR(AVERAGEIFS($L$3:$L$1054, $A$3:$A$1054,$AQ96, $M$3:$M$1054,">0"),0) - AT96, "") -> -1.4319949 | AV96: =IF(AQ96<>"", AU96*(1+$X$9/CompoundingRate)^-((AQ96-AQ$3)/(365/CompoundingRate)), "") -> -1.4319949
A97: 44620 | B97: NAB #2157 - Interest | G97: 906.37 | M97: =IF($A97<>"", IF(ISNUMBER(SEARCH("Debt Cost (est.)",B97)), SUMIFS(AT:AT, AQ:AQ, ">="&DATE("20"&RIGHT(LEFT(B97,4),2)-1,7,1), AQ:AQ, "<="&DATE("20"&RIGHT(LEFT(B97,4),2),6,30)), ""), "") | AA97: =IF($A97<>"", MIN(AB97,$P$3), "") -> 3450000 | AB97: =IF($A97<>"", AC97+AD97, "") -> 3450000 | AC97: =IF(A97<>"", AC96+D97+F97-G97, "") -> 566001.75 | AD97: =IF(A97<>"", AD96+C97-F97+G97, "") -> 2883998.3 | AE97: =IF(A98<>"", A98-A97, IF(A97<>"",IF(AC97<>0,TODAY()-A97,0), "")) -> 4 | AG97: =IF($A97<>"", I97+J97+E97-F97-H97, "") -> 0 | AH97: =IF(A97<>"", A97-A$3, "") -> 269 | AI97: =IF(A97<>"", AG97*(1+$X$3)^-(AH97/365), "") -> 0 | AL97: =IF($A97<>"", AG97-IF(ISNUMBER(K97),K97*L97,0), "") -> 0 | AM97: =IF(A97<>"", AL97*(1+$X$6/CompoundingRate)^-(AH97/(365/CompoundingRate)), "") -> 0 | AQ97: =IF(AQ96<$AP$3,AQ96+1,"") -> 44445 | AR97: =IF($AQ97<>"", INDEX($AC$3:$AC$1055, MATCH($AQ97,$A$3:$A$1055,1)), "") -> 522678.15 | AS97: =IF($AQ97<>"", INDEX(Inputs!$B$3:$B$101, MATCH($AQ97,Inputs!$A$3:$A$101,1)), "") -> 0.001 | AT97: =IF($AQ97<>"", AR97*AS97/365, "") -> 1.4319949 | AU97: =IF($AQ97<>"", SUMIFS($AL$3:$AL$1054, $A$3:$A$1054,$AQ97) + SUMIFS($M$3:$M$1054, $A$3:$A$1054,$AQ97)*IFERROR(AVERAGEIFS($L$3:$L$1054, $A$3:$A$1054,$AQ97, $M$3:$M$1054,">0"),0) - AT97, "") -> -1.4319949 | AV97: =IF(AQ97<>"", AU97*(1+$X$9/CompoundingRate)^-((AQ97-AQ$3)/(365/CompoundingRate)), "") -> -1.4319949
A98: 44624 | B98: Rent - Andre | I98: 1900 | M98: =IF($A98<>"", IF(ISNUMBER(SEARCH("Debt Cost (est.)",B98)), SUMIFS(AT:AT, AQ:AQ, ">="&DATE("20"&RIGHT(LEFT(B98,4),2)-1,7,1), AQ:AQ, "<="&DATE("20"&RIGHT(LEFT(B98,4),2),6,30)), ""), "") | AA98: =IF($A98<>"", MIN(AB98,$P$3), "") -> 3450000 | AB98: =IF($A98<>"", AC98+AD98, "") -> 3450000 | AC98: =IF(A98<>"", AC97+D98+F98-G98, "") -> 566001.75 | AD98: =IF(A98<>"", AD97+C98-F98+G98, "") -> 2883998.3 | AE98: =IF(A99<>"", A99-A98, IF(A98<>"",IF(AC98<>0,TODAY()-A98,0), "")) -> 7 | AG98: =IF($A98<>"", I98+J98+E98-F98-H98, "") -> 1900 | AH98: =IF(A98<>"", A98-A$3, "") -> 273 | AI98: =IF(A98<>"", AG98*(1+$X$3)^-(AH98/365), "") -> 1900 | AL98: =IF($A98<>"", AG98-IF(ISNUMBER(K98),K98*L98,0), "") -> 1900 | AM98: =IF(A98<>"", AL98*(1+$X$6/CompoundingRate)^-(AH98/(365/CompoundingRate)), "") -> 1900 | AQ98: =IF(AQ97<$AP$3,AQ97+1,"") -> 44446 | AR98: =IF($AQ98<>"", INDEX($AC$3:$AC$1055, MATCH($AQ98,$A$3:$A$1055,1)), "") -> 522678.15 | AS98: =IF($AQ98<>"", INDEX(Inputs!$B$3:$B$101, MATCH($AQ98,Inputs!$A$3:$A$101,1)), "") -> 0.001 | AT98: =IF($AQ98<>"", AR98*AS98/365, "") -> 1.4319949 | AU98: =IF($AQ98<>"", SUMIFS($AL$3:$AL$1054, $A$3:$A$1054,$AQ98) + SUMIFS($M$3:$M$1054, $A$3:$A$1054,$AQ98)*IFERROR(AVERAGEIFS($L$3:$L$1054, $A$3:$A$1054,$AQ98, $M$3:$M$1054,">0"),0) - AT98, "") -> -1.4319949 | AV98: =IF(AQ98<>"", AU98*(1+$X$9/CompoundingRate)^-((AQ98-AQ$3)/(365/CompoundingRate)), "") -> -1.4319949
A99: 44631 | B99: Rent - Andre | I99: 1900 | M99: =IF($A99<>"", IF(ISNUMBER(SEARCH("Debt Cost (est.)",B99)), SUMIFS(AT:AT, AQ:AQ, ">="&DATE("20"&RIGHT(LEFT(B99,4),2)-1,7,1), AQ:AQ, "<="&DATE("20"&RIGHT(LEFT(B99,4),2),6,30)), ""), "") | AA99: =IF($A99<>"", MIN(AB99,$P$3), "") -> 3450000 | AB99: =IF($A99<>"", AC99+AD99, "") -> 3450000 | AC99: =IF(A99<>"", AC98+D99+F99-G99, "") -> 566001.75 | AD99: =IF(A99<>"", AD98+C99-F99+G99, "") -> 2883998.3 | AE99: =IF(A100<>"", A100-A99, IF(A99<>"",IF(AC99<>0,TODAY()-A99,0), "")) -> 5 | AG99: =IF($A99<>"", I99+J99+E99-F99-H99, "") -> 1900 | AH99: =IF(A99<>"", A99-A$3, "") -> 280 | AI99: =IF(A99<>"", AG99*(1+$X$3)^-(AH99/365), "") -> 1900 | AL99: =IF($A99<>"", AG99-IF(ISNUMBER(K99),K99*L99,0), "") -> 1900 | AM99: =IF(A99<>"", AL99*(1+$X$6/CompoundingRate)^-(AH99/(365/CompoundingRate)), "") -> 1900 | AQ99: =IF(AQ98<$AP$3,AQ98+1,"") -> 44447 | AR99: =IF($AQ99<>"", INDEX($AC$3:$AC$1055, MATCH($AQ99,$A$3:$A$1055,1)), "") -> 522678.15 | AS99: =IF($AQ99<>"", INDEX(Inputs!$B$3:$B$101, MATCH($AQ99,Inputs!$A$3:$A$101,1)), "") -> 0.001 | AT99: =IF($AQ99<>"", AR99*AS99/365, "") -> 1.4319949 | AU99: =IF($AQ99<>"", SUMIFS($AL$3:$AL$1054, $A$3:$A$1054,$AQ99) + SUMIFS($M$3:$M$1054, $A$3:$A$1054,$AQ99)*IFERROR(AVERAGEIFS($L$3:$L$1054, $A$3:$A$1054,$AQ99, $M$3:$M$1054,">0"),0) - AT99, "") -> -1.4319949 | AV99: =IF(AQ99<>"", AU99*(1+$X$9/CompoundingRate)^-((AQ99-AQ$3)/(365/CompoundingRate)), "") -> -1.4319949
A100: 44636 | B100: NAB #3063 - Repayment | F100: 9818.51 | M100: =IF($A100<>"", IF(ISNUMBER(SEARCH("Debt Cost (est.)",B100)), SUMIFS(AT:AT, AQ:AQ, ">="&DATE("20"&RIGHT(LEFT(B100,4),2)-1,7,1), AQ:AQ, "<="&DATE("20"&RIGHT(LEFT(B100,4),2),6,30)), ""), "") | AA100: =IF($A100<>"", MIN(AB100,$P$3), "") -> 3450000 | AB100: =IF($A100<>"", AC100+AD100, "") -> 3450000 | AC100: =IF(A100<>"", AC99+D100+F100-G100, "") -> 575820.26 | AD100: =IF(A100<>"", AD99+C100-F100+G100, "") -> 2874179.7 | AE100: =IF(A101<>"", A101-A100, IF(A100<>"",IF(AC100<>0,TODAY()-A100,0), "")) -> 0 | AG100: =IF($A100<>"", I100+J100+E100-F100-H100, "") -> -9818.51 | AH100: =IF(A100<>"", A100-A$3, "") -> 285 | AI100: =IF(A100<>"", AG100*(1+$X$3)^-(AH100/365), "") -> -9818.51 | AL100: =IF($A100<>"", AG100-IF(ISNUMBER(K100),K100*L100,0), "") -> -9818.51 | AM100: =IF(A100<>"", AL100*(1+$X$6/CompoundingRate)^-(AH100/(365/CompoundingRate)), "") -> -9818.51 | AQ100: =IF(AQ99<$AP$3,AQ99+1,"") -> 44448 | AR100: =IF($AQ100<>"", INDEX($AC$3:$AC$1055, MATCH($AQ100,$A$3:$A$1055,1)), "") -> 522678.15 | AS100: =IF($AQ100<>"", INDEX(Inputs!$B$3:$B$101, MATCH($AQ100,Inputs!$A$3:$A$101,1)), "") -> 0.001 | AT100: =IF($AQ100<>"", AR100*AS100/365, "") -> 1.4319949 | AU100: =IF($AQ100<>"", SUMIFS($AL$3:$AL$1054, $A$3:$A$1054,$AQ100) + SUMIFS($M$3:$M$1054, $A$3:$A$1054,$AQ100)*IFERROR(AVERAGEIFS($L$3:$L$1054, $A$3:$A$1054,$AQ100, $M$3:$M$1054,">0"),0) - AT100, "") -> -1.4319949 | AV100: =IF(AQ100<>"", AU100*(1+$X$9/CompoundingRate)^-((AQ100-AQ$3)/(365/CompoundingRate)), "") -> -1.4319949
...

Sheet Inputs
A1: RBA Cash Rate | D1: Compounding Rate | F1: FX
A2: =[1]RBA!A1 -> AUD Date | B2: =[1]RBA!B1 -> AUD Rate | D2: =[1]CompoundingRate!$A$2 -> 12 | F2: =[1]FX!A1 -> Date | G2: =[1]FX!B1 -> AUD | H2: =[1]FX!C1 -> USD | I2: =[1]FX!D1 -> EUR | J2: =[1]FX!E1 -> CNY | K2: =[1]FX!F1 -> SGD | L2: =[1]FX!G1 -> GBP
A3: =IF([1]RBA!A2>1, [1]RBA!A2, "") -> 40849 | B3: =IF($A3<>"", [1]RBA!B2, "") -> 0.045 | F3: =IF([1]FX!A2>1, [1]FX!A2, "") -> 40209 | G3: =IF($F3<>"", [1]FX!B2, "") -> 1 | H3: =IF($F3<>"", [1]FX!C2, "") -> 0.88433 | I3: =IF($F3<>"", [1]FX!D2, "") -> 0.63731 | J3: =IF($F3<>"", [1]FX!E2, "") -> 6.0228 | K3: =IF($F3<>"", [1]FX!F2, "") -> 1.2435 | L3: =IF($F3<>"", [1]FX!G2, "") -> 0.55267
A4: =IF([1]RBA!A3>1, [1]RBA!A3, "") -> 40884 | B4: =IF($A4<>"", [1]RBA!B3, "") -> 0.0425 | F4: =IF([1]FX!A3>1, [1]FX!A3, "") -> 40237 | G4: =IF($F4<>"", [1]FX!B3, "") -> 1 | H4: =IF($F4<>"", [1]FX!C3, "") -> 0.895897 | I4: =IF($F4<>"", [1]FX!D3, "") -> 0.65707 | J4: =IF($F4<>"", [1]FX!E3, "") -> 6.1165 | K4: =IF($F4<>"", [1]FX!F3, "") -> 1.2585 | L4: =IF($F4<>"", [1]FX!G3, "") -> 0.58623
A5: =IF([1]RBA!A4>1, [1]RBA!A4, "") -> 41031 | B5: =IF($A5<>"", [1]RBA!B4, "") -> 0.0375 | F5: =IF([1]FX!A4>1, [1]FX!A4, "") -> 40268 | G5: =IF($F5<>"", [1]FX!B4, "") -> 1 | H5: =IF($F5<>"", [1]FX!C4, "") -> 0.915583 | I5: =IF($F5<>"", [1]FX!D4, "") -> 0.67746 | J5: =IF($F5<>"", [1]FX!E4, "") -> 6.2434 | K5: =IF($F5<>"", [1]FX!F4, "") -> 1.2807 | L5: =IF($F5<>"", [1]FX!G4, "") -> 0.6027
A6: =IF([1]RBA!A5>1, [1]RBA!A5, "") -> 41066 | B6: =IF($A6<>"", [1]RBA!B5, "") -> 0.035 | F6: =IF([1]FX!A5>1, [1]FX!A5, "") -> 40298 | G6: =IF($F6<>"", [1]FX!B5, "") -> 1 | H6: =IF($F6<>"", [1]FX!C5, "") -> 0.924813 | I6: =IF($F6<>"", [1]FX!D5, "") -> 0.69527 | J6: =IF($F6<>"", [1]FX!E5, "") -> 6.3002 | K6: =IF($F6<>"", [1]FX!F5, "") -> 1.2649 | L6: =IF($F6<>"", [1]FX!G5, "") -> 0.60425
A7: =IF([1]RBA!A6>1, [1]RBA!A6, "") -> 41185 | B7: =IF($A7<>"", [1]RBA!B6, "") -> 0.0325 | F7: =IF([1]FX!A6>1, [1]FX!A6, "") -> 40329 | G7: =IF($F7<>"", [1]FX!B6, "") -> 1 | H7: =IF($F7<>"", [1]FX!C6, "") -> 0.846597 | I7: =IF($F7<>"", [1]FX!D6, "") -> 0.6886 | J7: =IF($F7<>"", [1]FX!E6, "") -> 5.7632 | K7: =IF($F7<>"", [1]FX!F6, "") -> 1.1843 | L7: =IF($F7<>"", [1]FX!G6, "") -> 0.5826
A8: =IF([1]RBA!A7>1, [1]RBA!A7, "") -> 41248 | B8: =IF($A8<>"", [1]RBA!B7, "") -> 0.03 | F8: =IF([1]FX!A7>1, [1]FX!A7, "") -> 40359 | G8: =IF($F8<>"", [1]FX!B7, "") -> 1 | H8: =IF($F8<>"", [1]FX!C7, "") -> 0.841326 | I8: =IF($F8<>"", [1]FX!D7, "") -> 0.68763 | J8: =IF($F8<>"", [1]FX!E7, "") -> 5.7188 | K8: =IF($F8<>"", [1]FX!F7, "") -> 1.1771 | L8: =IF($F8<>"", [1]FX!G7, "") -> 0.5626
A9: =IF([1]RBA!A8>1, [1]RBA!A8, "") -> 41402 | B9: =IF($A9<>"", [1]RBA!B8, "") -> 0.0275 | F9: =IF([1]FX!A8>1, [1]FX!A8, "") -> 40390 | G9: =IF($F9<>"", [1]FX!B8, "") -> 1 | H9: =IF($F9<>"", [1]FX!C8, "") -> 0.904404 | I9: =IF($F9<>"", [1]FX!D8, "") -> 0.69343 | J9: =IF($F9<>"", [1]FX!E8, "") -> 6.1241 | K9: =IF($F9<>"", [1]FX!F8, "") -> 1.2308 | L9: =IF($F9<>"", [1]FX!G8, "") -> 0.57689
A10: =IF([1]RBA!A9>1, [1]RBA!A9, "") -> 41493 | B10: =IF($A10<>"", [1]RBA!B9, "") -> 0.025 | F10: =IF([1]FX!A9>1, [1]FX!A9, "") -> 40421 | G10: =IF($F10<>"", [1]FX!B9, "") -> 1 | H10: =IF($F10<>"", [1]FX!C9, "") -> 0.891822 | I10: =IF($F10<>"", [1]FX!D9, "") -> 0.7038 | J10: =IF($F10<>"", [1]FX!E9, "") -> 6.0618 | K10: =IF($F10<>"", [1]FX!F9, "") -> 1.2081 | L10: =IF($F10<>"", [1]FX!G9, "") -> 0.5763
A11: =IF([1]RBA!A10>1, [1]RBA!A10, "") -> 42039 | B11: =IF($A11<>"", [1]RBA!B10, "") -> 0.0225 | F11: =IF([1]FX!A10>1, [1]FX!A10, "") -> 40451 | G11: =IF($F11<>"", [1]FX!B10, "") -> 1 | H11: =IF($F11<>"", [1]FX!C10, "") -> 0.969368 | I11: =IF($F11<>"", [1]FX!D10, "") -> 0.7111 | J11: =IF($F11<>"", [1]FX!E10, "") -> 6.4691 | K11: =IF($F11<>"", [1]FX!F10, "") -> 1.277 | L11: =IF($F11<>"", [1]FX!G10, "") -> 0.61338
A12: =IF([1]RBA!A11>1, [1]RBA!A11, "") -> 42130 | B12: =IF($A12<>"", [1]RBA!B11, "") -> 0.02 | F12: =IF([1]FX!A11>1, [1]FX!A11, "") -> 40482 | G12: =IF($F12<>"", [1]FX!B11, "") -> 1 | H12: =IF($F12<>"", [1]FX!C11, "") -> 0.972763 | I12: =IF($F12<>"", [1]FX!D11, "") -> 0.7059 | J12: =IF($F12<>"", [1]FX!E11, "") -> 6.4884 | K12: =IF($F12<>"", [1]FX!F11, "") -> 1.2685 | L12: =IF($F12<>"", [1]FX!G11, "") -> 0.6163
A13: =IF([1]RBA!A12>1, [1]RBA!A12, "") -> 42494 | B13: =IF($A13<>"", [1]RBA!B12, "") -> 0.0175 | F13: =IF([1]FX!A12>1, [1]FX!A12, "") -> 40512 | G13: =IF($F13<>"", [1]FX!B12, "") -> 1 | H13: =IF($F13<>"", [1]FX!C12, "") -> 0.960707 | I13: =IF($F13<>"", [1]FX!D12, "") -> 0.7332 | J13: =IF($F13<>"", [1]FX!E12, "") -> 6.382 | K13: =IF($F13<>"", [1]FX!F12, "") -> 1.269 | L13: =IF($F13<>"", [1]FX!G12, "") -> 0.6178
A14: =IF([1]RBA!A13>1, [1]RBA!A13, "") -> 42585 | B14: =IF($A14<>"", [1]RBA!B13, "") -> 0.015 | F14: =IF([1]FX!A13>1, [1]FX!A13, "") -> 40543 | G14: =IF($F14<>"", [1]FX!B13, "") -> 1 | H14: =IF($F14<>"", [1]FX!C13, "") -> 1.015775 | I14: =IF($F14<>"", [1]FX!D13, "") -> 0.7632 | J14: =IF($F14<>"", [1]FX!E13, "") -> 6.6737 | K14: =IF($F14<>"", [1]FX!F13, "") -> 1.307 | L14: =IF($F14<>"", [1]FX!G13, "") -> 0.6579
... A101: =IF([1]RBA!A100>1, [1]RBA!A100, "") | B101: =IF($A101<>"", [1]RBA!B100, "") | F101: =IF([1]FX!A100>1, [1]FX!A100, "") -> 43190 | G101: =IF($F101<>"", [1]FX!B100, "") -> 1 | H101: =IF($F101<>"", [1]FX!C100, "") -> 0.76858 | I101: =IF($F101<>"", [1]FX!D100, "") -> 0.6245 | J101: =IF($F101<>"", [1]FX!E100, "") -> 4.8269 | K101: =IF($F101<>"", [1]FX!F100, "") -> 1.00747 | L101: =IF($F101<>"", [1]FX!G100, "") -> 0.54765
F102: =IF([1]FX!A101>1, [1]FX!A101, "") -> 43220 | G102: =IF($F102<>"", [1]FX!B101, "") -> 1 | H102: =IF($F102<>"", [1]FX!C101, "") -> 0.757518 | I102: =IF($F102<>"", [1]FX!D101, "") -> 0.6247 | J102: =IF($F102<>"", [1]FX!E101, "") -> 4.7946 | K102: =IF($F102<>"", [1]FX!F101, "") -> 1.0018 | L102: =IF($F102<>"", [1]FX!G101, "") -> 0.54993
F103: =IF([1]FX!A102>1, [1]FX!A102, "") -> 43251 | G103: =IF($F103<>"", [1]FX!B102, "") -> 1 | H103: =IF($F103<>"", [1]FX!C102, "") -> 0.757117 | I103: =IF($F103<>"", [1]FX!D102, "") -> 0.64898 | J103: =IF($F103<>"", [1]FX!E102, "") -> 4.8543 | K103: =IF($F103<>"", [1]FX!F102, "") -> 1.01367 | L103: =IF($F103<>"", [1]FX!G102, "") -> 0.56991
F104: =IF([1]FX!A103>1, [1]FX!A103, "") -> 43281 | G104: =IF($F104<>"", [1]FX!B103, "") -> 1 | H104: =IF($F104<>"", [1]FX!C103, "") -> 0.734646 | I104: =IF($F104<>"", [1]FX!D103, "") -> 0.63529 | J104: =IF($F104<>"", [1]FX!E103, "") -> 4.8629 | K104: =IF($F104<>"", [1]FX!F103, "") -> 1.00511 | L104: =IF($F104<>"", [1]FX!G103, "") -> 0.56182
F105: =IF([1]FX!A104>1, [1]FX!A104, "") -> 43312 | G105: =IF($F105<>"", [1]FX!B104, "") -> 1 | H105: =IF($F105<>"", [1]FX!C104, "") -> 0.74073 | I105: =IF($F105<>"", [1]FX!D104, "") -> 0.63261 | J105: =IF($F105<>"", [1]FX!E104, "") -> 5.0429 | K105: =IF($F105<>"", [1]FX!F104, "") -> 1.00808 | L105: =IF($F105<>"", [1]FX!G104, "") -> 0.56386
F106: =IF([1]FX!A105>1, [1]FX!A105, "") -> 43343 | G106: =IF($F106<>"", [1]FX!B105, "") -> 1 | H106: =IF($F106<>"", [1]FX!C105, "") -> 0.726164 | I106: =IF($F106<>"", [1]FX!D105, "") -> 0.62249 | J106: =IF($F106<>"", [1]FX!E105, "") -> 4.9638 | K106: =IF($F106<>"", [1]FX!F105, "") -> 0.99285 | L106: =IF($F106<>"", [1]FX!G105, "") -> 0.55808
F107: =IF([1]FX!A106>1, [1]FX!A106, "") -> 43373 | G107: =IF($F107<>"", [1]FX!B106, "") -> 1 | H107: =IF($F107<>"", [1]FX!C106, "") -> 0.720513 | I107: =IF($F107<>"", [1]FX!D106, "") -> 0.61906 | J107: =IF($F107<>"", [1]FX!E106, "") -> 4.9567 | K107: =IF($F107<>"", [1]FX!F106, "") -> 0.98554 | L107: =IF($F107<>"", [1]FX!G106, "") -> 0.5507
F108: =IF([1]FX!A107>1, [1]FX!A107, "") -> 43404 | G108: =IF($F108<>"", [1]FX!B107, "") -> 1 | H108: =IF($F108<>"", [1]FX!C107, "") -> 0.709925 | I108: =IF($F108<>"", [1]FX!D107, "") -> 0.6256 | J108: =IF($F108<>"", [1]FX!E107, "") -> 4.9392 | K108: =IF($F108<>"", [1]FX!F107, "") -> 0.98326 | L108: =IF($F108<>"", [1]FX!G107, "") -> 0.55853
F109: =IF([1]FX!A108>1, [1]FX!A108, "") -> 43434 | G109: =IF($F109<>"", [1]FX!B108, "") -> 1 | H109: =IF($F109<>"", [1]FX!C108, "") -> 0.732188 | I109: =IF($F109<>"", [1]FX!D108, "") -> 0.64262 | J109: =IF($F109<>"", [1]FX!E108, "") -> 5.076 | K109: =IF($F109<>"", [1]FX!F108, "") -> 1.0028 | L109: =IF($F109<>"", [1]FX!G108, "") -> 0.57269
F110: =IF([1]FX!A109>1, [1]FX!A109, "") -> 43465 | G110: =IF($F110<>"", [1]FX!B109, "") -> 1 | H110: =IF($F110<>"", [1]FX!C109, "") -> 0.704473 | I110: =IF($F110<>"", [1]FX!D109, "") -> 0.61574 | J110: =IF($F110<>"", [1]FX!E109, "") -> 4.8407 | K110: =IF($F110<>"", [1]FX!F109, "") -> 0.96235 | L110: =IF($F110<>"", [1]FX!G109, "") -> 0.55502
F111: =IF([1]FX!A110>1, [1]FX!A110, "") -> 43496 | G111: =IF($F111<>"", [1]FX!B110, "") -> 1 | H111: =IF($F111<>"", [1]FX!C110, "") -> 0.725468 | I111: =IF($F111<>"", [1]FX!D110, "") -> 0.63157 | J111: =IF($F111<>"", [1]FX!E110, "") -> 4.8649 | K111: =IF($F111<>"", [1]FX!F110, "") -> 0.97682 | L111: =IF($F111<>"", [1]FX!G110, "") -> 0.55301
F112: =IF([1]FX!A111>1, [1]FX!A111, "") -> 43524 | G112: =IF($F112<>"", [1]FX!B111, "") -> 1 | H112: =IF($F112<>"", [1]FX!C111, "") -> 0.714847 | I112: =IF($F112<>"", [1]FX!D111, "") -> 0.62806 | J112: =IF($F112<>"", [1]FX!E111, "") -> 4.7741 | K112: =IF($F112<>"", [1]FX!F111, "") -> 0.9631 | L112: =IF($F112<>"", [1]FX!G111, "") -> 0.5367
F113: =IF([1]FX!A112>1, [1]FX!A112, "") -> 43555 | G113: =IF($F113<>"", [1]FX!B112, "") -> 1 | H113: =IF($F113<>"", [1]FX!C112, "") -> 0.708316 | I113: =IF($F113<>"", [1]FX!D112, "") -> 0.63056 | J113: =IF($F113<>"", [1]FX!E112, "") -> 4.7655 | K113: =IF($F113<>"", [1]FX!F112, "") -> 0.9599 | L113: =IF($F113<>"", [1]FX!G112, "") -> 0.5423
... F500: =IF([1]FX!A499>1, [1]FX!A499, "") | G500: =IF($F500<>"", [1]FX!B499, "") | H500: =IF($F500<>"", [1]FX!C499, "") | I500: =IF($F500<>"", [1]FX!D499, "") | J500: =IF($F500<>"", [1]FX!E499, "") | K500: =IF($F500<>"", [1]FX!F499, "") | L500: =IF($F500<>"", [1]FX!G499, "")

Sheet Monthly
A1: =TODAY() -> 45836 | B1: 17|34 Hamilton St
B2: =INDEX(Summary!$C$3:$C$100, MATCH(B$1,Summary!$A$3:$A$100,0)) -> AUD
B3: =INDEX(Summary!$D$3:$D$100, MATCH(B$1,Summary!$A$3:$A$100,0)) -> Property
B4: =INDEX(Summary!$E$3:$E$100, MATCH(B$1,Summary!$A$3:$A$100,0)) -> Shaun Reichman
B5: AA
B6: Balance
A7: 43496 | B7: =IF($A7>$A$1, 0, IFERROR(IF(B$6="Balance", INDEX(INDIRECT("'"&B$1&"'!"&B$5&":"&B$5), MATCH($A7,INDIRECT("'"&B$1&"'!A:A"),1)), IF(B$6="Update", SUMIFS(INDIRECT("'"&B$1&"'!"&B$5&":"&B$5), INDIRECT("'"&B$1&"'!A:A"),$A7), "")) / INDEX(Inputs!$G$3:$Z$500, MATCH($A7,Inputs!$F$3:$F$500,0), MATCH(B$2,Inputs!$G$2:$Y$2,0)), 0)) -> 0
A8: 43524 | B8: =IF($A8>$A$1, 0, IFERROR(IF(B$6="Balance", INDEX(INDIRECT("'"&B$1&"'!"&B$5&":"&B$5), MATCH($A8,INDIRECT("'"&B$1&"'!A:A"),1)), IF(B$6="Update", SUMIFS(INDIRECT("'"&B$1&"'!"&B$5&":"&B$5), INDIRECT("'"&B$1&"'!A:A"),$A8), "")) / INDEX(Inputs!$G$3:$Z$500, MATCH($A8,Inputs!$F$3:$F$500,0), MATCH(B$2,Inputs!$G$2:$Y$2,0)), 0)) -> 0
A9: 43555 | B9: =IF($A9>$A$1, 0, IFERROR(IF(B$6="Balance", INDEX(INDIRECT("'"&B$1&"'!"&B$5&":"&B$5), MATCH($A9,INDIRECT("'"&B$1&"'!A:A"),1)), IF(B$6="Update", SUMIFS(INDIRECT("'"&B$1&"'!"&B$5&":"&B$5), INDIRECT("'"&B$1&"'!A:A"),$A9), "")) / INDEX(Inputs!$G$3:$Z$500, MATCH($A9,Inputs!$F$3:$F$500,0), MATCH(B$2,Inputs!$G$2:$Y$2,0)), 0)) -> 0
A10: 43585 | B10: =IF($A10>$A$1, 0, IFERROR(IF(B$6="Balance", INDEX(INDIRECT("'"&B$1&"'!"&B$5&":"&B$5), MATCH($A10,INDIRECT("'"&B$1&"'!A:A"),1)), IF(B$6="Update", SUMIFS(INDIRECT("'"&B$1&"'!"&B$5&":"&B$5), INDIRECT("'"&B$1&"'!A:A"),$A10), "")) / INDEX(Inputs!$G$3:$Z$500, MATCH($A10,Inputs!$F$3:$F$500,0), MATCH(B$2,Inputs!$G$2:$Y$2,0)), 0)) -> 0
A11: 43616 | B11: =IF($A11>$A$1, 0, IFERROR(IF(B$6="Balance", INDEX(INDIRECT("'"&B$1&"'!"&B$5&":"&B$5), MATCH($A11,INDIRECT("'"&B$1&"'!A:A"),1)), IF(B$6="Update", SUMIFS(INDIRECT("'"&B$1&"'!"&B$5&":"&B$5), INDIRECT("'"&B$1&"'!A:A"),$A11), "")) / INDEX(Inputs!$G$3:$Z$500, MATCH($A11,Inputs!$F$3:$F$500,0), MATCH(B$2,Inputs!$G$2:$Y$2,0)), 0)) -> 0
A12: 43646 | B12: =IF($A12>$A$1, 0, IFERROR(IF(B$6="Balance", INDEX(INDIRECT("'"&B$1&"'!"&B$5&":"&B$5), MATCH($A12,INDIRECT("'"&B$1&"'!A:A"),1)), IF(B$6="Update", SUMIFS(INDIRECT("'"&B$1&"'!"&B$5&":"&B$5), INDIRECT("'"&B$1&"'!A:A"),$A12), "")) / INDEX(Inputs!$G$3:$Z$500, MATCH($A12,Inputs!$F$3:$F$500,0), MATCH(B$2,Inputs!$G$2:$Y$2,0)), 0)) -> 0
A13: 43677 | B13: =IF($A13>$A$1, 0, IFERROR(IF(B$6="Balance", INDEX(INDIRECT("'"&B$1&"'!"&B$5&":"&B$5), MATCH($A13,INDIRECT("'"&B$1&"'!A:A"),1)), IF(B$6="Update", SUMIFS(INDIRECT("'"&B$1&"'!"&B$5&":"&B$5), INDIRECT("'"&B$1&"'!A:A"),$A13), "")) / INDEX(Inputs!$G$3:$Z$500, MATCH($A13,Inputs!$F$3:$F$500,0), MATCH(B$2,Inputs!$G$2:$Y$2,0)), 0)) -> 0
A14: 43708 | B14: =IF($A14>$A$1, 0, IFERROR(IF(B$6="Balance", INDEX(INDIRECT("'"&B$1&"'!"&B$5&":"&B$5), MATCH($A14,INDIRECT("'"&B$1&"'!A:A"),1)), IF(B$6="Update", SUMIFS(INDIRECT("'"&B$1&"'!"&B$5&":"&B$5), INDIRECT("'"&B$1&"'!A:A"),$A14), "")) / INDEX(Inputs!$G$3:$Z$500, MATCH($A14,Inputs!$F$3:$F$500,0), MATCH(B$2,Inputs!$G$2:$Y$2,0)), 0)) -> 0
A15: 43738 | B15: =IF($A15>$A$1, 0, IFERROR(IF(B$6="Balance", INDEX(INDIRECT("'"&B$1&"'!"&B$5&":"&B$5), MATCH($A15,INDIRECT("'"&B$1&"'!A:A"),1)), IF(B$6="Update", SUMIFS(INDIRECT("'"&B$1&"'!"&B$5&":"&B$5), INDIRECT("'"&B$1&"'!A:A"),$A15), "")) / INDEX(Inputs!$G$3:$Z$500, MATCH($A15,Inputs!$F$3:$F$500,0), MATCH(B$2,Inputs!$G$2:$Y$2,0)), 0)) -> 0
A16: 43769 | B16: =IF($A16>$A$1, 0, IFERROR(IF(B$6="Balance", INDEX(INDIRECT("'"&B$1&"'!"&B$5&":"&B$5), MATCH($A16,INDIRECT("'"&B$1&"'!A:A"),1)), IF(B$6="Update", SUMIFS(INDIRECT("'"&B$1&"'!"&B$5&":"&B$5), INDIRECT("'"&B$1&"'!A:A"),$A16), "")) / INDEX(Inputs!$G$3:$Z$500, MATCH($A16,Inputs!$F$3:$F$500,0), MATCH(B$2,Inputs!$G$2:$Y$2,0)), 0)) -> 0
A17: 43799 | B17: =IF($A17>$A$1, 0, IFERROR(IF(B$6="Balance", INDEX(INDIRECT("'"&B$1&"'!"&B$5&":"&B$5), MATCH($A17,INDIRECT("'"&B$1&"'!A:A"),1)), IF(B$6="Update", SUMIFS(INDIRECT("'"&B$1&"'!"&B$5&":"&B$5), INDIRECT("'"&B$1&"'!A:A"),$A17), "")) / INDEX(Inputs!$G$3:$Z$500, MATCH($A17,Inputs!$F$3:$F$500,0), MATCH(B$2,Inputs!$G$2:$Y$2,0)), 0)) -> 0
A18: 43830 | B18: =IF($A18>$A$1, 0, IFERROR(IF(B$6="Balance", INDEX(INDIRECT("'"&B$1&"'!"&B$5&":"&B$5), MATCH($A18,INDIRECT("'"&B$1&"'!A:A"),1)), IF(B$6="Update", SUMIFS(INDIRECT("'"&B$1&"'!"&B$5&":"&B$5), INDIRECT("'"&B$1&"'!A:A"),$A18), "")) / INDEX(Inputs!$G$3:$Z$500, MATCH($A18,Inputs!$F$3:$F$500,0), MATCH(B$2,Inputs!$G$2:$Y$2,0)), 0)) -> 0
... A96: 46203 | B96: =IF($A96>$A$1, 0, IFERROR(IF(B$6="Balance", INDEX(INDIRECT("'"&B$1&"'!"&B$5&":"&B$5), MATCH($A96,INDIRECT("'"&B$1&"'!A:A"),1)), IF(B$6="Update", SUMIFS(INDIRECT("'"&B$1&"'!"&B$5&":"&B$5), INDIRECT("'"&B$1&"'!A:A"),$A96), "")) / INDEX(Inputs!$G$3:$Z$500, MATCH($A96,Inputs!$F$3:$F$500,0), MATCH(B$2,Inputs!$G$2:$Y$2,0)), 0)) -> 0

Sheet Yearly Balances
C1: 3 | D1: 4 | E1: 5 | F1: 6 | G1: 7 | H1: 8 | I1: 9 | J1: 10 | M1: 3 | N1: 4 | O1: 5 | P1: 6 | Q1: 7 | R1: 8 | S1: 9 | T1: 10
C2: FY18 | D2: FY19 | E2: FY20 | F2: FY21 | G2: FY22 | H2: FY23 | I2: FY24 | J2: FY25 | M2: FY18 | N2: FY19 | O2: FY20 | P2: FY21 | Q2: FY22 | R2: FY23 | S2: FY24 | T2: FY25
A3: =Summary!A3 -> 17|34 Hamilton St | B3: BC | C3: {=IF(INDIRECT("'"&$A3&"'!"&$B3&C$1)<>0, INDIRECT("'"&$A3&"'!"&$B3&C$1), "")} | D3: {=IF(INDIRECT("'"&$A3&"'!"&$B3&D$1)<>0, INDIRECT("'"&$A3&"'!"&$B3&D$1), "")} | E3: {=IF(INDIRECT("'"&$A3&"'!"&$B3&E$1)<>0, INDIRECT("'"&$A3&"'!"&$B3&E$1), "")} | F3: {=IF(INDIRECT("'"&$A3&"'!"&$B3&F$1)<>0, INDIRECT("'"&$A3&"'!"&$B3&F$1), "")} -> 27 | G3: {=IF(INDIRECT("'"&$A3&"'!"&$B3&G$1)<>0, INDIRECT("'"&$A3&"'!"&$B3&G$1), "")} -> 365 | H3: {=IF(INDIRECT("'"&$A3&"'!"&$B3&H$1)<>0, INDIRECT("'"&$A3&"'!"&$B3&H$1), "")} -> 365 | I3: {=IF(INDIRECT("'"&$A3&"'!"&$B3&I$1)<>0, INDIRECT("'"&$A3&"'!"&$B3&I$1), "")} -> 366 | J3: {=IF(INDIRECT("'"&$A3&"'!"&$B3&J$1)<>0, INDIRECT("'"&$A3&"'!"&$B3&J$1), "")} -> 363 | L3: BD | M3: {=IFERROR(INDIRECT("'"&$A3&"'!"&$L3&C$1), "")} | N3: {=IFERROR(INDIRECT("'"&$A3&"'!"&$L3&D$1), "")} | O3: {=IFERROR(INDIRECT("'"&$A3&"'!"&$L3&E$1), "")} | P3: {=IFERROR(INDIRECT("'"&$A3&"'!"&$L3&F$1), "")} -> 172500 | Q3: {=IFERROR(INDIRECT("'"&$A3&"'!"&$L3&G$1), "")} -> 540545.38 | R3: {=IFERROR(INDIRECT("'"&$A3&"'!"&$L3&H$1), "")} -> 636307 | S3: {=IFERROR(INDIRECT("'"&$A3&"'!"&$L3&I$1), "")} -> 729079.84 | T3: {=IFERROR(INDIRECT("'"&$A3&"'!"&$L3&J$1), "")} -> 562311.48
A4: =Summary!A4 -> 0
A5: =Summary!A5 -> 0
A6: =Summary!A6 -> 0
A7: =Summary!A7 -> 0
A8: =Summary!A8 -> 0
A9: =Summary!A9 -> 0
A10: =Summary!A10 -> 0
